Workbook

Sheet README
A1: Chatbot interaction dataset
A2: Built 2026-09-09 15:39 from the structuredcreativeplanning RTDB export.
A4: Sheets
A5: Sessions one row per chat session, with process metrics
A6: Turns one row per message. visible_text has HTML stripped and
A7: control payloads unwrapped; word_count follows visible_text,
A8: not the raw field, so it differs from the CSV export.
A9: Ideas SCAMPER ideas the bot logged, with the bot's OWN ratings of
A10: originality / elaboration / flexibility. These are the model's
A11: judgements, not ground truth - treat as a variable to validate
A12: against your human coding, never as the criterion measure.
A13: Bot_Actions stage switches and story-graph writes
... A43: Counts
A44: Sessions | B44: =COUNTA(Sessions!B2:B88)
A45: Turns | B45: =COUNTA(Turns!C2:C100000)
A46: Student turns | B46: =SUM(Sessions!H2:H88)
A47: Bot turns | B47: =SUM(Sessions!I2:I88)
A48: Distinct participants | B48: =SUMPRODUCT((Sessions!A2:A88<>"")/COUNTIF(Sessions!A2:A88,Sessions!A2:A88&""))
A49: Ideas logged | B49: =COUNTA(Ideas!A2:A100000)
A50: Sessions with a control payload | B50: =COUNTIF(Sessions!S2:S88,">0")
A51: Sessions with zero turns | B51: =COUNTIF(Sessions!G2:G88,0)
A52: Total student words | B52: =SUM(Sessions!J2:J88)
A53: Total bot words | B53: =SUM(Sessions!K2:K88)
A54: Mean student:bot word ratio | B54: =IFERROR(AVERAGE(Sessions!L2:L88),"")

Sheet Sessions
A1: uid | B1: session_id | C1: title | D1: created | E1: updated | F1: mode | G1: n_turns | H1: n_student_turns | I1: n_bot_turns | J1: student_words | K1: bot_words | L1: student_bot_ratio | M1: mean_student_turn_words | N1: duration_min | O1: n_dontknow_turns | P1: modes_used | Q1: stages_used | R1: scamper_techniques | S1: n_control_payloads | T1: n_ideas_logged | U1: has_story | V1: story_words | W1: csv_student_words
A2: 04E9XYnVi8QD3yHAIXeBHCRp2sN2 | B2: -OwQi7O4WPmWWyungHqQ | C2: New Chat | D2: 2026-07-01 11:28:27 | E2: 2026-07-01 11:28:27 | F2: brainstorming | G2: 0 | H2: 0 | I2: 0 | J2: 0 | K2: 0 | O2: 0 | S2: 0 | T2: 0 | U2: no | V2: 0 | W2: 0
A3: 0QaQYslhRSXNMdCEaDY35HzA2Xl2 | B3: -OwWRuDalQgU7vQhUj5g | C3: Creepy House Hidden Secret Found | D3: 2026-07-02 14:11:08 | E3: 2026-07-02 14:16:42 | F3: brainstorming | G3: 14 | H3: 7 | I3: 7 | J3: 54 | K3: 269 | L3: 0.201 | M3: 7.7 | N3: 5.7 | O3: 3 | P3: brainstorming:14 | Q3: Clarify:14 | R3: Substitute:1 | S3: 2 | T3: 1 | U3: yes | V3: 125 | W3: 54
A4: 0QaQYslhRSXNMdCEaDY35HzA2Xl2 | B4: -OwWTu17Sxd9ROSqJ5t4 | C4: Alien Pet and Hidden Trapdoor | D4: 2026-07-02 14:19:51 | E4: 2026-07-02 14:30:05 | F4: brainstorming | G4: 42 | H4: 21 | I4: 21 | J4: 367 | K4: 977 | L4: 0.376 | M4: 17.5 | N4: 30.5 | O4: 6 | P4: brainstorming:30; deepthinking:12 | Q4: Clarify:30 | S4: 2 | T4: 0 | U4: yes | V4: 125 | W4: 367
A5: 3Oh8HB9tTRgaFMqElgVenKJCKCe2 | B5: -OwWR_fPwmqt12YqfVXq | C5: Brainstorming Lost Field Trip Emotions | D5: 2026-07-02 14:09:29 | E5: 2026-07-02 14:18:24 | F5: brainstorming | G5: 56 | H5: 28 | I5: 28 | J5: 627 | K5: 1703 | L5: 0.368 | M5: 22.4 | N5: 43.3 | O5: 0 | P5: brainstorming:56 | Q5: Clarify:56 | S5: 0 | T5: 0 | U5: yes | V5: 221 | W5: 627
A6: 3w9E9Xr7oehGE2ThwcIxvybuKwE2 | B6: -OwVprk7ZBkimJoUaB_0 | C6: Lost Dog Finds Home by Scent | D6: 2026-07-02 11:20:34 | E6: 2026-07-02 11:24:45 | F6: brainstorming | G6: 24 | H6: 12 | I6: 12 | J6: 139 | K6: 482 | L6: 0.288 | M6: 11.6 | N6: 12.3 | O6: 0 | P6: brainstorming:24 | Q6: Clarify:24 | R6: Modify:1; Eliminate:1 | S6: 2 | T6: 2 | U6: yes | V6: 217 | W6: 139
A7: 4J7XUz8OJaZ7l0X9s0VrHR2DYNs2 | B7: -OwQ5lp6LdgjuthVXkK4 | C7: New Chat | D7: 2026-07-01 08:36:29 | E7: 2026-07-01 08:36:29 | F7: brainstorming | G7: 0 | H7: 0 | I7: 0 | J7: 0 | K7: 0 | O7: 0 | S7: 0 | T7: 0 | U7: yes | V7: 1730 | W7: 0
A8: 5iy5k09B1rhCSEHuf17zeB2lmXL2 | B8: -OwWRTKbVRiZWmp90Opw | C8: The Best Mistake Ever | D8: 2026-07-02 14:09:00 | E8: 2026-07-02 14:14:35 | F8: brainstorming | G8: 54 | H8: 27 | I8: 27 | J8: 291 | K8: 993 | L8: 0.293 | M8: 10.8 | N8: 39.5 | O8: 0 | P8: brainstorming:54 | Q8: Clarify:54 | S8: 0 | T8: 0 | U8: yes | V8: 622 | W8: 291
A9: 6FGzR0FFoIMiQ3y2otIsOqIyrMh2 | B9: -OwVMNSQxBd_hrnwU2xD | C9: Late Student Fears Teacher's Judgment | D9: 2026-07-02 09:07:08 | E9: 2026-07-02 09:27:54 | F9: brainstorming | G9: 10 | H9: 5 | I9: 5 | J9: 30 | K9: 182 | L9: 0.165 | M9: 6 | N9: 15.9 | O9: 0 | P9: brainstorming:8; deepthinking:2 | Q9: Clarify:8 | S9: 0 | T9: 0 | U9: yes | V9: 330 | W9: 30
A10: 6xMddtGgmcN42mZbnypoitgkFpa2 | B10: -OwWRBt8DVkudBkXs5c_ | C10: Junette's Thorned Garden of Pain | D10: 2026-07-02 14:07:47 | E10: 2026-07-02 14:12:31 | F10: brainstorming | G10: 33 | H10: 16 | I10: 17 | J10: 189 | K10: 501 | L10: 0.377 | M10: 11.8 | N10: 30.3 | O10: 0 | P10: brainstorming:30; deepthinking:3 | Q10: Clarify:30 | S10: 0 | T10: 0 | U10: yes | V10: 915 | W10: 189
A11: 7b2GdTbVRfUHAWpBDj4ZNTuE2UH2 | B11: -OwQlTUrDsKsjPp8eem_ | C11: Surviving Natural Disasters Together | D11: 2026-07-01 11:43:06 | E11: 2026-07-01 11:48:40 | F11: brainstorming | G11: 38 | H11: 19 | I11: 19 | J11: 125 | K11: 826 | L11: 0.151 | M11: 6.6 | N11: 31.2 | O11: 0 | P11: brainstorming:38 | Q11: Clarify:38 | S11: 0 | T11: 0 | U11: yes | V11: 463 | W11: 125
A12: 86IempJqjAe16ZnVEcfplb36dQK2 | B12: -OwVpU1B63hEDG7yjpwQ | C12: Alien Wolves Spread Cosmic Music | D12: 2026-07-02 11:18:40 | E12: 2026-07-02 11:46:45 | F12: brainstorming | G12: 22 | H12: 11 | I12: 11 | J12: 312 | K12: 475 | L12: 0.657 | M12: 28.4 | N12: 37.2 | O12: 0 | P12: brainstorming:22 | Q12: Clarify:22 | S12: 1 | T12: 0 | U12: yes | V12: 259 | W12: 312
A13: 8f8UOMJlUgXC014a2m6fBFiuUji1 | B13: -OwQ7dIytHxMgcyGrG5X | C13: Racist Wakes as Black Man | D13: 2026-07-01 08:44:45 | E13: 2026-07-01 08:57:28 | F13: brainstorming | G13: 28 | H13: 14 | I13: 14 | J13: 1104 | K13: 4745 | L13: 0.233 | M13: 78.9 | N13: 62.6 | O13: 0 | P13: brainstorming:28 | Q13: Clarify:28 | S13: 0 | T13: 0 | U13: yes | V13: 448 | W13: 1104
A14: 8ikpafQproYMb9YoPmwfJPens6O2 | B14: -OwQkyczI6UcKIXeUc2F | C14: You Got Lost: Field Trip Fear | D14: 2026-07-01 11:40:52 | E14: 2026-07-01 11:45:19 | F14: brainstorming | G14: 38 | H14: 19 | I14: 19 | J14: 195 | K14: 706 | L14: 0.276 | M14: 10.3 | N14: 31.8 | O14: 0 | P14: brainstorming:38 | Q14: Clarify:38 | S14: 0 | T14: 0 | U14: yes | V14: 131 | W14: 195
A15: AHeFHdwoiMWh94QkcWbW22EjkkO2 | B15: -OwVq8qgO1KoQeTL0uSH | C15: New Chat | D15: 2026-07-02 11:21:40 | E15: 2026-07-02 11:21:40 | F15: brainstorming | G15: 0 | H15: 0 | I15: 0 | J15: 0 | K15: 0 | O15: 0 | S15: 0 | T15: 0 | U15: no | V15: 0 | W15: 0
A16: B5ETbn4OQlbmR7jwyYjscFhyHMG2 | B16: -OwQ67133Lz-KNA9ZbdS | C16: Luxury Boat Murder Mystery | D16: 2026-07-01 08:38:04 | E16: 2026-07-01 08:44:50 | F16: brainstorming | G16: 32 | H16: 16 | I16: 16 | J16: 654 | K16: 3584 | L16: 0.182 | M16: 40.9 | N16: 72.9 | O16: 0 | P16: brainstorming:32 | Q16: Clarify:32 | S16: 0 | T16: 0 | U16: yes | V16: 485 | W16: 654
A17: BpdNWTiz1HPmyvrVdqlZIfyGpMO2 | B17: -OwVMPJUg7lZIxE8PYnt | C17: New Chat | D17: 2026-07-02 09:07:19 | E17: 2026-07-02 09:07:19 | F17: brainstorming | G17: 0 | H17: 0 | I17: 0 | J17: 0 | K17: 0 | O17: 0 | S17: 0 | T17: 0 | U17: yes | V17: 460 | W17: 0
A18: E8tQQtddL4Z8NvhbbqY8K5O4cfO2 | B18: -OwVqe2ZqcjWPBqat8LD | C18: New Chat | D18: 2026-07-02 11:23:45 | E18: 2026-07-02 11:23:45 | F18: brainstorming | G18: 4 | H18: 2 | I18: 2 | J18: 13 | K18: 86 | L18: 0.151 | M18: 6.5 | N18: 0.6 | O18: 0 | P18: deepthinking:4 | S18: 0 | T18: 0 | U18: yes | V18: 211 | W18: 13
A19: ENqphjWfdORTcp5Rm7ZI8lVt24g2 | B19: -OwVMVfcauohpncLoQI5 | C19: New Chat | D19: 2026-07-02 09:07:48 | E19: 2026-07-02 09:07:48 | F19: brainstorming | G19: 0 | H19: 0 | I19: 0 | J19: 0 | K19: 0 | O19: 0 | S19: 0 | T19: 0 | U19: no | V19: 0 | W19: 0
A20: FCANzDkmkYT1W6HgapUhdnZN0xo2 | B20: -OwQ6ALECCFlzb-y4I6x | C20: Bootylicious: Silent But Deadly | D20: 2026-07-01 08:38:13 | E20: 2026-07-01 08:54:42 | F20: brainstorming | G20: 12 | H20: 6 | I20: 6 | J20: 1017 | K20: 896 | L20: 1.135 | M20: 169.5 | N20: 77.9 | O20: 0 | P20: brainstorming:12 | Q20: Clarify:12 | S20: 0 | T20: 0 | U20: yes | V20: 795 | W20: 1017
A21: GC4oYcvlWFdKmK6Nkgi8i5hXCng1 | B21: -OwWaNAHSIHrqr86etjL | C21: New Chat | D21: 2026-07-02 14:52:14 | E21: 2026-07-02 14:52:14 | F21: deepthinking | G21: 0 | H21: 0 | I21: 0 | J21: 0 | K21: 0 | O21: 0 | S21: 0 | T21: 0 | U21: yes | V21: 553 | W21: 0
A22: JOXonotBYmMnqSLfh2NltHD8uXB2 | B22: -OwRJ-j-ilE_87Gj2nw- | C22: Survival Escape from the Forest | D22: 2026-07-01 14:13:57 | E22: 2026-07-01 14:16:14 | F22: brainstorming | G22: 90 | H22: 45 | I22: 45 | J22: 685 | K22: 2916 | L22: 0.235 | M22: 15.2 | N22: 37.7 | O22: 5 | P22: brainstorming:88; deepthinking:2 | Q22: Clarify:88 | S22: 0 | T22: 0 | U22: yes | V22: 448 | W22: 685
A23: JfiRrqZrDzOGZuUmcQ0xNNqqRPt2 | B23: -OwQ6l8yKXh0mxWfxDep | C23: Hometown Girl's Love and Safety | D23: 2026-07-01 08:40:51 | E23: 2026-07-01 08:51:18 | F23: brainstorming | G23: 28 | H23: 14 | I23: 14 | J23: 441 | K23: 2491 | L23: 0.177 | M23: 31.5 | N23: 81 | O23: 0 | P23: brainstorming:28 | Q23: Clarify:28 | S23: 0 | T23: 0 | U23: yes | V23: 385 | W23: 441
A24: Jr8NNAZgvmgiYpNb4K6qyiuo4tW2 | B24: -OwVLzRLoMyRpLu453uN | C24: The Ocean's Letters to a Sailor | D24: 2026-07-02 09:05:24 | E24: 2026-07-02 09:12:43 | F24: brainstorming | G24: 42 | H24: 21 | I24: 21 | J24: 672 | K24: 1273 | L24: 0.528 | M24: 32 | N24: 33.5 | O24: 0 | P24: brainstorming:28; deepthinking:14 | Q24: Clarify:28 | S24: 0 | T24: 0 | U24: yes | V24: 252 | W24: 672
A25: KSH5ttdNftVFL6Gd0J4yzvu2FBp1 | B25: -OwQlyLXRk2AjJhB_1XK | C25: Future Self's Warning Visit | D25: 2026-07-01 11:45:12 | E25: 2026-07-01 11:52:40 | F25: brainstorming | G25: 16 | H25: 8 | I25: 8 | J25: 81 | K25: 571 | L25: 0.142 | M25: 10.1 | N25: 10.7 | O25: 0 | P25: brainstorming:16 | Q25: Clarify:16 | S25: 0 | T25: 0 | U25: yes | V25: 171 | W25: 81
A26: KUrkPMRkNAhX9hnzS29LtPHaO5x2 | B26: -OwWRxGAtS_Mj2uTX05A | C26: Lost Museum School Trip Artifact | D26: 2026-07-02 14:11:06 | E26: 2026-07-02 14:23:02 | F26: brainstorming | G26: 10 | H26: 5 | I26: 5 | J26: 35 | K26: 295 | L26: 0.119 | M26: 7 | N26: 9.7 | O26: 0 | P26: brainstorming:10 | Q26: Clarify:10 | S26: 0 | T26: 0 | U26: yes | V26: 265 | W26: 35
A27: KgqLQajP4thdhVywhC6DGIFB1ZC3 | B27: -OwQ5iq5hA2tizYR68Jm | C27: User rejects shallow ideas | D27: 2026-07-01 08:36:17 | E27: 2026-07-01 08:39:34 | F27: brainstorming | G27: 42 | H27: 21 | I27: 21 | J27: 635 | K27: 3381 | L27: 0.188 | M27: 30.2 | N27: 73.4 | O27: 0 | P27: brainstorming:42 | Q27: Clarify:42 | S27: 0 | T27: 0 | U27: yes | V27: 1838 | W27: 635
A28: MElwPCsZEaaqKQAeCOXeM4qWdYu1 | B28: -OwQjT_gMvxUJOklGyTf | C28: AI Model Identity Query | D28: 2026-07-01 11:34:19 | E28: 2026-07-01 11:39:23 | F28: brainstorming | G28: 34 | H28: 17 | I28: 17 | J28: 112 | K28: 905 | L28: 0.124 | M28: 6.6 | N28: 10.6 | O28: 0 | P28: deepthinking:26; brainstorming:8 | Q28: Clarify:8 | S28: 0 | T28: 0 | U28: yes | V28: 487 | W28: 112
A29: OBnur9pwodNFSiYWQTQYk4j7H4o2 | B29: -OwQ5uPIXZNhYr-dE21- | C29: City Cafe Goodbye Romance | D29: 2026-07-01 08:37:04 | E29: 2026-07-01 08:42:08 | F29: brainstorming | G29: 54 | H29: 27 | I29: 27 | J29: 1043 | K29: 5630 | L29: 0.185 | M29: 38.6 | N29: 72.6 | O29: 0 | P29: brainstorming:54 | Q29: Clarify:54 | S29: 0 | T29: 0 | U29: yes | V29: 629 | W29: 1043
A30: Pi7fYOl6F9P8xIVy5Bp6Su1SJoi2 | B30: -OwQAnkWvNaVCgMtnfNd | C30: Dark Hero vs Chaos Villain | D30: 2026-07-01 08:58:35 | E30: 2026-07-01 09:03:24 | F30: brainstorming | G30: 12 | H30: 6 | I30: 6 | J30: 92 | K30: 1152 | L30: 0.08 | M30: 15.3 | N30: 5.6 | O30: 0 | P30: brainstorming:12 | Q30: Clarify:12 | S30: 0 | T30: 0 | U30: yes | V30: 554 | W30: 92
A31: Q0BdLRD5qMaXRnNKtRFXKHlCziC2 | B31: -OwVtA_ao_WTMq8bBTvq | C31: New Chat | D31: 2026-07-02 11:34:48 | E31: 2026-07-02 11:34:48 | F31: brainstorming | G31: 0 | H31: 0 | I31: 0 | J31: 0 | K31: 0 | O31: 0 | S31: 0 | T31: 0 | U31: yes | V31: 158 | W31: 0
A32: SVWibbwPvVNAPwJsXOWtvn3125r1 | B32: -OwWRMWABbsUTlM_nQei | C32: New Chat | D32: 2026-07-02 14:08:38 | E32: 2026-07-02 14:08:38 | F32: brainstorming | G32: 6 | H32: 3 | I32: 3 | J32: 19 | K32: 137 | L32: 0.139 | M32: 6.3 | N32: 5 | O32: 0 | P32: brainstorming:6 | Q32: Clarify:6 | S32: 0 | T32: 0 | U32: yes | V32: 446 | W32: 19
A33: SVWibbwPvVNAPwJsXOWtvn3125r1 | B33: -OwWScDTADV6U1kabyRw | C33: Joke Offends Classmate Essay Request | D33: 2026-07-02 14:14:09 | E33: 2026-07-02 14:17:15 | F33: brainstorming | G33: 28 | H33: 14 | I33: 14 | J33: 60 | K33: 1101 | L33: 0.054 | M33: 4.3 | N33: 11.3 | O33: 2 | P33: brainstorming:28 | Q33: Clarify:28 | S33: 0 | T33: 0 | U33: yes | V33: 446 | W33: 60
A34: SVWibbwPvVNAPwJsXOWtvn3125r1 | B34: -OwWVQuxmISXijxPEyRx | C34: Secret, Betrayal, and Quiet Repair | D34: 2026-07-02 14:26:25 | E34: 2026-07-02 14:31:46 | F34: brainstorming | G34: 16 | H34: 8 | I34: 8 | J34: 69 | K34: 901 | L34: 0.077 | M34: 8.6 | N34: 15.6 | O34: 0 | P34: brainstorming:16 | Q34: Clarify:16 | S34: 0 | T34: 0 | U34: yes | V34: 446 | W34: 69
A35: TQfxN5NKTYfrxWioKMzYuuiQ7qS2 | B35: -OwQt44-8tkBRRkCA2wN | C35: New Chat | D35: 2026-07-01 12:16:24 | E35: 2026-07-01 12:16:24 | F35: brainstorming | G35: 0 | H35: 0 | I35: 0 | J35: 0 | K35: 0 | O35: 0 | S35: 0 | T35: 0 | U35: no | V35: 0 | W35: 0
A36: UgthkQ3qazbkV3nqKoTewkGq1lG3 | B36: -OwVq20Wo7Gl4QKZo2Yn | C36: AI identity clarification request | D36: 2026-07-02 11:21:10 | E36: 2026-07-02 11:28:23 | F36: brainstorming | G36: 10 | H36: 5 | I36: 5 | J36: 13 | K36: 224 | L36: 0.058 | M36: 2.6 | N36: 5.3 | O36: 0 | P36: deepthinking:8; brainstorming:2 | Q36: Clarify:2 | S36: 0 | T36: 0 | U36: yes | V36: 206 | W36: 13
A37: UgthkQ3qazbkV3nqKoTewkGq1lG3 | B37: -OwVs0u1_ajLxzUOd35e | C37: Late Bus, Successful Presentation | D37: 2026-07-02 11:29:49 | E37: 2026-07-02 12:00:10 | F37: deepthinking | G37: 11 | H37: 5 | I37: 6 | J37: 217 | K37: 189 | L37: 1.148 | M37: 43.4 | N37: 29.9 | O37: 0 | P37: deepthinking:11 | S37: 0 | T37: 0 | U37: yes | V37: 206 | W37: 217
A38: VPYaFq2al4YL01itSYZZJWFuLyk2 | B38: -OwRIjberDi-Hqk417eW | C38: Ocean's Letter to a Sailor | D38: 2026-07-01 14:12:45 | E38: 2026-07-01 14:18:11 | F38: brainstorming | G38: 44 | H38: 22 | I38: 22 | J38: 741 | K38: 735 | L38: 1.008 | M38: 33.7 | N38: 39.7 | O38: 1 | P38: brainstorming:44 | Q38: Ideate:35; Clarify:9 | S38: 0 | T38: 0 | U38: yes | V38: 540 | W38: 741
A39: VeVNHm97tJMSOEMZA1zYMwT7kuv2 | B39: -OwRJYjygQFIHoTbiRvG | C39: Lost Alone in a Forest | D39: 2026-07-01 14:16:21 | E39: 2026-07-01 14:25:07 | F39: brainstorming | G39: 14 | H39: 7 | I39: 7 | J39: 60 | K39: 257 | L39: 0.233 | M39: 8.6 | N39: 7.9 | O39: 0 | P39: brainstorming:14 | Q39: Clarify:14 | S39: 0 | T39: 0 | U39: yes | V39: 333 | W39: 60
A40: WpheHrtzTNaussrzkoqf49fcuh42 | B40: -OwQkpEgdguEZXdk6Di- | C40: World Reacts to Talking Animal | D40: 2026-07-01 11:40:18 | E40: 2026-07-01 11:51:10 | F40: brainstorming | G40: 18 | H40: 9 | I40: 9 | J40: 46 | K40: 642 | L40: 0.072 | M40: 5.1 | N40: 13.5 | O40: 0 | P40: brainstorming:18 | Q40: Clarify:18 | S40: 0 | T40: 0 | U40: yes | V40: 275 | W40: 46
A41: WxgpdWfiwihlyiSTDVluZHqeZIw2 | B41: -OwVr6DPBJt7AtT4B-Qv | C41: New Chat | D41: 2026-07-02 11:25:47 | E41: 2026-07-02 11:25:47 | F41: brainstorming | G41: 0 | H41: 0 | I41: 0 | J41: 0 | K41: 0 | O41: 0 | S41: 0 | T41: 0 | U41: no | V41: 0 | W41: 0
A42: XRAnpQCsjPNnnXsVtEHYSfzy4Mi1 | B42: -OwVM91dviWIJmVuR4Wu | C42: Storm of Ballooning Spiders | D42: 2026-07-02 09:06:10 | E42: 2026-07-02 09:10:56 | F42: brainstorming | G42: 12 | H42: 6 | I42: 6 | J42: 65 | K42: 504 | L42: 0.129 | M42: 10.8 | N42: 5.5 | O42: 0 | P42: brainstorming:8; deepthinking:4 | Q42: Clarify:8 | S42: 0 | T42: 0 | U42: yes | V42: 141 | W42: 65
A43: XRAnpQCsjPNnnXsVtEHYSfzy4Mi1 | B43: -OwVPLJUgzLTPeojh_Rv | C43: New Chat | D43: 2026-07-02 09:20:06 | E43: 2026-07-02 09:20:06 | F43: brainstorming | G43: 4 | H43: 2 | I43: 2 | J43: 37 | K43: 111 | L43: 0.333 | M43: 18.5 | N43: 0.9 | O43: 0 | P43: brainstorming:4 | Q43: Clarify:4 | S43: 0 | T43: 0 | U43: yes | V43: 141 | W43: 37
A44: XRAnpQCsjPNnnXsVtEHYSfzy4Mi1 | B44: -OwVPlFWI8q1Vh3cpLJK | C44: New Chat | D44: 2026-07-02 09:21:57 | E44: 2026-07-02 09:21:57 | F44: deepthinking | G44: 8 | H44: 4 | I44: 4 | J44: 61 | K44: 177 | L44: 0.345 | M44: 15.2 | N44: 15.4 | O44: 0 | P44: deepthinking:8 | S44: 0 | T44: 0 | U44: yes | V44: 141 | W44: 61
A45: XsnhTMtsdjgtOnGFzpz6icyTjb23 | B45: -OwRRTICUhvhKZffT9Mp | C45: New Chat | D45: 2026-07-01 14:50:52 | E45: 2026-07-01 14:50:52 | F45: brainstorming | G45: 0 | H45: 0 | I45: 0 | J45: 0 | K45: 0 | O45: 0 | S45: 0 | T45: 0 | U45: yes | V45: 427 | W45: 0
A46: XsnhTMtsdjgtOnGFzpz6icyTjb23 | B46: -OwRTRSmRc3ANtKIbpYN | C46: New Chat | D46: 2026-07-01 14:59:29 | E46: 2026-07-01 14:59:29 | F46: brainstorming | G46: 0 | H46: 0 | I46: 0 | J46: 0 | K46: 0 | O46: 0 | S46: 0 | T46: 0 | U46: yes | V46: 427 | W46: 0
A47: XyHLgIX2JXS0AwIKMxYnZtJhxqV2 | B47: -OwQ68wTIcpFqQtx_E-A | C47: Modern Fantasy Dream World | D47: 2026-07-01 08:38:13 | E47: 2026-07-01 08:48:57 | F47: brainstorming | G47: 26 | H47: 13 | I47: 13 | J47: 576 | K47: 7581 | L47: 0.076 | M47: 44.3 | N47: 71.7 | O47: 0 | P47: brainstorming:26 | Q47: Clarify:26 | S47: 0 | T47: 0 | U47: yes | V47: 454 | W47: 576
A48: ZZ4BwYvWCBU3Bfs6oYvA5ECo2lL2 | B48: -OwRIiGUO5amuQL4YC9W | C48: New Chat | D48: 2026-07-01 14:12:40 | E48: 2026-07-01 14:12:40 | F48: brainstorming | G48: 8 | H48: 4 | I48: 4 | J48: 75 | K48: 131 | L48: 0.573 | M48: 18.8 | N48: 2.4 | O48: 0 | P48: brainstorming:8 | Q48: Clarify:8 | S48: 0 | T48: 0 | U48: yes | V48: 575 | W48: 75
A49: b0TakmpcCXgB6ttl6BAwf2J6wEB3 | B49: -OwWSCMBwEAs-s4Y3OuR | C49: Amazon Explorer vs. Bigfoot | D49: 2026-07-02 14:12:21 | E49: 2026-07-02 14:26:38 | F49: brainstorming | G49: 12 | H49: 6 | I49: 6 | J49: 103 | K49: 146 | L49: 0.705 | M49: 17.2 | N49: 14.5 | O49: 0 | P49: brainstorming:12 | Q49: Clarify:12 | S49: 0 | T49: 0 | U49: yes | V49: 311 | W49: 103
A50: b2lpnlBg5heIUgFVC8MhbvYSdd92 | B50: -OwQBYVhVyxKaKjR8C12 | C50: Essay on Artificial Intelligence | D50: 2026-07-01 09:01:56 | E50: 2026-07-01 09:07:50 | F50: brainstorming | G50: 18 | H50: 9 | I50: 9 | J50: 24 | K50: 2935 | L50: 0.008 | M50: 2.7 | N50: 16.8 | O50: 0 | P50: brainstorming:18 | Q50: Clarify:18 | S50: 0 | T50: 0 | U50: yes | V50: 529 | W50: 24
A51: b2lpnlBg5heIUgFVC8MhbvYSdd92 | B51: -OwQF_RRF7kJG9Vvu2jv | C51: New Chat | D51: 2026-07-01 09:19:32 | E51: 2026-07-01 09:19:32 | F51: brainstorming | G51: 2 | H51: 1 | I51: 1 | J51: 5 | K51: 145 | L51: 0.034 | M51: 5 | N51: 0.1 | O51: 0 | P51: brainstorming:2 | Q51: Clarify:2 | S51: 0 | T51: 0 | U51: yes | V51: 529 | W51: 5
A52: cLyL9tyJmPhkluQYedEaJpAiOGs1 | B52: -OwQ5l7UQK7a9UrCPIOL | C52: J's Battle with Childhood Obesity | D52: 2026-07-01 08:36:30 | E52: 2026-07-01 08:41:17 | F52: brainstorming | G52: 44 | H52: 22 | I52: 22 | J52: 572 | K52: 2710 | L52: 0.211 | M52: 26 | N52: 73.7 | O52: 0 | P52: brainstorming:44 | Q52: Clarify:44 | S52: 0 | T52: 0 | U52: yes | V52: 1236 | W52: 572
A53: ca5NsH9D9VP1PYcjV3gGEQNQCef2 | B53: -OwRJl5D2YPseUVs8LXT | C53: Forest That Remembers Entrants | D53: 2026-07-01 14:17:13 | E53: 2026-07-01 14:24:11 | F53: brainstorming | G53: 46 | H53: 23 | I53: 23 | J53: 306 | K53: 674 | L53: 0.454 | M53: 13.3 | N53: 33.2 | O53: 3 | P53: brainstorming:46 | Q53: Clarify:46 | S53: 0 | T53: 0 | U53: yes | V53: 263 | W53: 306
A54: cixF6dxQwHRzKuplVzUWwJkU1xd2 | B54: -OwVMF5hppLpSIaSHvFl | C54: Missed Job Interview Mistake | D54: 2026-07-02 09:06:35 | E54: 2026-07-02 09:12:39 | F54: brainstorming | G54: 16 | H54: 8 | I54: 8 | J54: 164 | K54: 291 | L54: 0.564 | M54: 20.5 | N54: 8.3 | O54: 0 | P54: brainstorming:16 | Q54: Clarify:16 | S54: 0 | T54: 0 | U54: yes | V54: 452 | W54: 164
A55: dKXrDUfJBoXMBxUOfft4DOYEQf02 | B55: -OwQ67ol68k7D3uXttLT | C55: Sudden Genius Genre Dilemma | D55: 2026-07-01 08:38:03 | E55: 2026-07-01 08:44:51 | F55: brainstorming | G55: 56 | H55: 28 | I55: 28 | J55: 179 | K55: 7900 | L55: 0.023 | M55: 6.4 | N55: 33.6 | O55: 2 | P55: brainstorming:56 | Q55: Clarify:56 | S55: 0 | T55: 0 | U55: yes | V55: 406 | W55: 179
A56: dKXrDUfJBoXMBxUOfft4DOYEQf02 | B56: -OwQFUxYqBR6--Dbn66e | C56: The Cursed Prodigy's Loneliness | D56: 2026-07-01 09:18:57 | E56: 2026-07-01 09:34:05 | F56: brainstorming | G56: 16 | H56: 8 | I56: 8 | J56: 579 | K56: 1735 | L56: 0.334 | M56: 72.4 | N56: 20.3 | O56: 0 | P56: brainstorming:16 | Q56: Clarify:16 | S56: 0 | T56: 0 | U56: yes | V56: 406 | W56: 579
A57: dKXrDUfJBoXMBxUOfft4DOYEQf02 | B57: -OwQN9JBElRorACLaPlI | C57: New Chat | D57: 2026-07-01 09:52:26 | E57: 2026-07-01 09:52:26 | F57: brainstorming | G57: 8 | H57: 4 | I57: 4 | J57: 423 | K57: 2427 | L57: 0.174 | M57: 105.8 | N57: 3.4 | O57: 0 | P57: brainstorming:8 | Q57: Clarify:8 | S57: 0 | T57: 0 | U57: yes | V57: 406 | W57: 423
A58: ei7uIBNrA6hTSoZw1MWHUxa33Xx2 | B58: -OwVpNZV5RaC1zxaWB2W | C58: AI Identity and Sexuality Inquiry | D58: 2026-07-02 11:18:13 | E58: 2026-07-02 11:26:44 | F58: brainstorming | G58: 10 | H58: 5 | I58: 5 | J58: 5 | K58: 10 | L58: 0.5 | M58: 1 | N58: 2.6 | O58: 0 | P58: brainstorming:10 | Q58: Clarify:10 | S58: 0 | T58: 0 | U58: yes | V58: 227 | W58: 5
... A61: f76q2VXtEzYd1USRmJ2fr9YS5V52 | B61: -OwVP8N_xbHxGd5ehYYB | C61: New Chat | D61: 2026-07-02 09:19:17 | E61: 2026-07-02 09:19:17 | F61: brainstorming | G61: 6 | H61: 3 | I61: 3 | J61: 54 | K61: 152 | L61: 0.355 | M61: 18 | N61: 1.6 | O61: 0 | P61: brainstorming:6 | Q61: Clarify:6 | S61: 0 | T61: 0 | U61: yes | V61: 1421 | W61: 54
A62: ghKcPINokSP7QeZ2kJAIwbW4v2H2 | B62: -OwWa3W1Vuk6vP5DMAlJ | C62: New Chat | D62: 2026-07-02 14:50:56 | E62: 2026-07-02 14:50:56 | F62: deepthinking | G62: 2 | H62: 1 | I62: 1 | J62: 1521 | K62: 30 | L62: 50.7 | M62: 1521 | N62: 0.1 | O62: 0 | P62: deepthinking:2 | S62: 0 | T62: 0 | U62: yes | V62: 1521 | W62: 1521
A63: hsaBuah3qBSdtt1bf2yt4ne9IxD3 | B63: -OwRIwf0dj0uLggASI-f | C63: Joke Offends Sensitive Classmate | D63: 2026-07-01 14:13:52 | E63: 2026-07-01 14:21:49 | F63: brainstorming | G63: 34 | H63: 17 | I63: 17 | J63: 799 | K63: 955 | L63: 0.837 | M63: 47 | N63: 37.5 | O63: 0 | P63: brainstorming:32; deepthinking:2 | Q63: Clarify:32 | S63: 0 | T63: 0 | U63: yes | V63: 1204 | W63: 799
A64: hvsIJCvqgdUhBOXMK4TEyHUwtBh1 | B64: -OwQm1tZIez1kcj20ewr | C64: Stone Life: A Philosophical Tale | D64: 2026-07-01 11:45:44 | E64: 2026-07-01 11:59:38 | F64: brainstorming | G64: 10 | H64: 5 | I64: 5 | J64: 32 | K64: 245 | L64: 0.131 | M64: 6.4 | N64: 11.7 | O64: 0 | P64: brainstorming:10 | Q64: Clarify:10 | S64: 0 | T64: 0 | U64: yes | V64: 61 | W64: 32
A65: kqw94eSWpMVPznitZ29cijE8cHL2 | B65: -OwRJVgVq54fEo7WOPXd | C65: Lost in Cave: Fear and Discovery | D65: 2026-07-01 14:16:06 | E65: 2026-07-01 14:41:45 | F65: brainstorming | G65: 16 | H65: 8 | I65: 8 | J65: 103 | K65: 585 | L65: 0.176 | M65: 12.9 | N65: 37.9 | O65: 0 | P65: brainstorming:16 | Q65: Clarify:16 | S65: 0 | T65: 0 | U65: yes | V65: 410 | W65: 103
A66: l1uTxUvFpQVfYGEi6dDE8kFs8EI2 | B66: -OwQ5j0e7hBa0If60e64 | C66: James meets a friend buying drink | D66: 2026-07-01 08:36:18 | E66: 2026-07-01 08:41:51 | F66: brainstorming | G66: 44 | H66: 22 | I66: 22 | J66: 718 | K66: 5732 | L66: 0.125 | M66: 32.6 | N66: 70.3 | O66: 1 | P66: brainstorming:44 | Q66: Clarify:44 | S66: 0 | T66: 0 | U66: yes | V66: 818 | W66: 718
A67: lJqty3ZMzfQVTleIdJ4053a6prJ3 | B67: -OwWRsR2iHPs5Ro0r3cS | C67: Visiting Future Self Story Start | D67: 2026-07-02 14:10:51 | E67: 2026-07-02 14:18:06 | F67: brainstorming | G67: 42 | H67: 21 | I67: 21 | J67: 620 | K67: 1257 | L67: 0.493 | M67: 29.5 | N67: 39.3 | O67: 0 | P67: brainstorming:38; deepthinking:4 | Q67: Clarify:38 | S67: 0 | T67: 0 | U67: yes | V67: 146 | W67: 620
A68: m5EmXnDMvudLU4RuvoTmnq0j1S12 | B68: -OwWRLsJJHOLz1DBRstW | C68: Street Kid Outsmarts to Riches | D68: 2026-07-02 14:08:31 | E68: 2026-07-02 14:12:41 | F68: brainstorming | G68: 90 | H68: 44 | I68: 46 | J68: 581 | K68: 2324 | L68: 0.25 | M68: 13.2 | N68: 48.5 | O68: 0 | P68: deepthinking:56; brainstorming:34 | Q68: Clarify:34 | S68: 0 | T68: 0 | U68: yes | V68: 218 | W68: 435
A69: mD3iJPnT2dR53ewlkwFV3MhkSzj2 | B69: -OwWRHJma5Cc8ZWaQRDF | C69: A Late Start, A Lost Boy | D69: 2026-07-02 14:08:18 | E69: 2026-07-02 14:18:29 | F69: brainstorming | G69: 14 | H69: 7 | I69: 7 | J69: 119 | K69: 239 | L69: 0.498 | M69: 17 | N69: 10 | O69: 0 | P69: brainstorming:8; deepthinking:6 | Q69: Clarify:8 | S69: 0 | T69: 0 | U69: yes | V69: 589 | W69: 119
A70: nWfoLRrOe5QWnqcnJpf5lnrCY2r2 | B70: -OwQ5wDqd8sDLgEJqPoS | C70: Stuttering Comedian's Chosen Story | D70: 2026-07-01 08:37:14 | E70: 2026-07-01 08:40:53 | F70: brainstorming | G70: 30 | H70: 15 | I70: 15 | J70: 731 | K70: 2596 | L70: 0.282 | M70: 48.7 | N70: 74.2 | O70: 0 | P70: brainstorming:30 | Q70: Clarify:30 | S70: 0 | T70: 0 | U70: yes | V70: 1206 | W70: 731
A71: nlD6F00p8GRNn5ngwuOi7RBk9au2 | B71: -OwQlFCviqmZtLFLRLuo | C71: New Chat | D71: 2026-07-01 11:42:03 | E71: 2026-07-01 11:42:03 | F71: brainstorming | G71: 0 | H71: 0 | I71: 0 | J71: 0 | K71: 0 | O71: 0 | S71: 0 | T71: 0 | U71: no | V71: 0 | W71: 0
A72: owXosnotCWP3nzQMS6kkopRmOSw2 | B72: -OwVs1KhI5jYxLF0Tzz_ | C72: New Chat | D72: 2026-07-02 11:29:47 | E72: 2026-07-02 11:29:47 | F72: brainstorming | G72: 0 | H72: 0 | I72: 0 | J72: 0 | K72: 0 | O72: 0 | S72: 0 | T72: 0 | U72: yes | V72: 651 | W72: 0
A73: pCyez2P0fBYFyv51KSfWiunozax1 | B73: -OwVq13K7a_BA2SuFLiP | C73: Explosive School Day Essay Help | D73: 2026-07-02 11:21:09 | E73: 2026-07-02 11:24:21 | F73: brainstorming | G73: 38 | H73: 19 | I73: 19 | J73: 86 | K73: 837 | L73: 0.103 | M73: 4.5 | N73: 9.2 | O73: 0 | P73: brainstorming:38 | Q73: Clarify:38 | S73: 0 | T73: 0 | U73: yes | V73: 412 | W73: 86
A74: qzyz2lQeFkereAmQNK1QfShOnoe2 | B74: -OwVQGg0hg2VxIuOu54W | C74: New Chat | D74: 2026-07-02 09:24:08 | E74: 2026-07-02 09:24:08 | F74: brainstorming | G74: 0 | H74: 0 | I74: 0 | J74: 0 | K74: 0 | O74: 0 | S74: 0 | T74: 0 | U74: yes | V74: 503 | W74: 0
A75: r8Fd0piDcNgohHoQqAyPlbp5cXE3 | B75: -OwQki8YYAZnAMy7VCfo | C75: Future Self's Mysterious Evening Visit | D75: 2026-07-01 11:39:44 | E75: 2026-07-01 11:42:16 | F75: brainstorming | G75: 34 | H75: 17 | I75: 17 | J75: 67 | K75: 1348 | L75: 0.05 | M75: 3.9 | N75: 10.1 | O75: 1 | P75: brainstorming:34 | Q75: Clarify:34 | S75: 0 | T75: 0 | U75: yes | V75: 455 | W75: 67
A76: rJTIkz4BJUftHE5g5pil8THAMQL2 | B76: -OwRJZuWNFKZ0OZSAwXR | C76: Storm Metaphor for Hidden Danger | D76: 2026-07-01 14:16:27 | E76: 2026-07-01 14:20:36 | F76: brainstorming | G76: 42 | H76: 21 | I76: 21 | J76: 173 | K76: 966 | L76: 0.179 | M76: 8.2 | N76: 31.2 | O76: 0 | P76: brainstorming:42 | Q76: Clarify:42 | S76: 3 | T76: 0 | U76: yes | V76: 613 | W76: 173
A77: rcpSyNA9oPZOKMniqnXDZXdRQVu1 | B77: -OwQ64CjAko5ZSdh9yJv | C77: Dystopian Utopia: Illusion of Originality | D77: 2026-07-01 08:37:49 | E77: 2026-07-01 08:44:27 | F77: brainstorming | G77: 22 | H77: 11 | I77: 11 | J77: 259 | K77: 1756 | L77: 0.147 | M77: 23.5 | N77: 21.1 | O77: 0 | P77: brainstorming:22 | Q77: Clarify:22 | S77: 0 | T77: 0 | U77: no | V77: 0 | W77: 259
A78: rcpSyNA9oPZOKMniqnXDZXdRQVu1 | B78: -OwQBcybb6DHq4kbpBQr | C78: Dystopian Screen Control Revelation | D78: 2026-07-01 09:02:06 | E78: 2026-07-01 09:06:07 | F78: deepthinking | G78: 19 | H78: 9 | I78: 10 | J78: 367 | K78: 862 | L78: 0.426 | M78: 40.8 | N78: 28 | O78: 0 | P78: deepthinking:19 | S78: 0 | T78: 0 | U78: no | V78: 0 | W78: 367
A79: rlbwFMMkopZiFsTR0OxwhNOTxi63 | B79: -OwQmUn8aZBiW3e7g6r- | C79: Tesseract and Tetris Creation | D79: 2026-07-01 11:47:32 | E79: 2026-07-01 11:51:28 | F79: brainstorming | G79: 22 | H79: 11 | I79: 11 | J79: 79 | K79: 467 | L79: 0.169 | M79: 7.2 | N79: 26.3 | O79: 0 | P79: brainstorming:22 | Q79: Clarify:22 | S79: 0 | T79: 0 | U79: yes | V79: 66 | W79: 79
A80: soDLDTjzE9Yk1sdLIPyMcTNZ3oZ2 | B80: -OwVp_cRUQqU1TpoDW8H | C80: New Chat | D80: 2026-07-02 11:19:06 | E80: 2026-07-02 11:19:06 | F80: brainstorming | G80: 4 | H80: 2 | I80: 2 | J80: 25 | K80: 61 | L80: 0.41 | M80: 12.5 | N80: 1.4 | O80: 0 | P80: brainstorming:2; deepthinking:2 | Q80: Clarify:2 | S80: 0 | T80: 0 | U80: yes | V80: 162 | W80: 25
A81: t8SO3y8tkoPZzzzF8TMOLY6kOin1 | B81: -OwRKa9mpJC80hhM6f_w | C81: Inner Voice Exposes Childhood Secrets | D81: 2026-07-01 14:20:51 | E81: 2026-07-01 14:28:36 | F81: brainstorming | G81: 10 | H81: 5 | I81: 5 | J81: 124 | K81: 155 | L81: 0.8 | M81: 24.8 | N81: 6.8 | O81: 0 | P81: brainstorming:10 | Q81: Clarify:10 | S81: 0 | T81: 0 | U81: yes | V81: 425 | W81: 124
A82: ul2prdtjl4f549j7GnxNpKrRHXI2 | B82: -OwVN3hO8RygFS1Mdu_G | C82: New Chat | D82: 2026-07-02 09:10:09 | E82: 2026-07-02 09:10:09 | F82: brainstorming | G82: 2 | H82: 1 | I82: 1 | J82: 10 | K82: 39 | L82: 0.256 | M82: 10 | N82: 0.1 | O82: 0 | P82: brainstorming:2 | Q82: Clarify:2 | S82: 0 | T82: 0 | U82: yes | V82: 57 | W82: 10
A83: usaEM8ZBX7UHNMiKpxtLC28hrso1 | B83: -OwRJkJMHqjCeziEfkE6 | C83: Speaking Animal: Storytelling Advantages | D83: 2026-07-01 14:17:14 | E83: 2026-07-01 14:22:57 | F83: brainstorming | G83: 18 | H83: 9 | I83: 9 | J83: 102 | K83: 563 | L83: 0.181 | M83: 11.3 | N83: 12.8 | O83: 0 | P83: brainstorming:18 | Q83: Clarify:18 | S83: 0 | T83: 0 | U83: yes | V83: 224 | W83: 102
A84: wSGZm6xY8UT8oeb8gr9kbb5wp2o2 | B84: -OwQ5oO_F42iMIGFLG1n | C84: Writer as Murderer Plot Twist | D84: 2026-07-01 08:36:42 | E84: 2026-07-01 08:42:54 | F84: brainstorming | G84: 34 | H84: 17 | I84: 17 | J84: 613 | K84: 3356 | L84: 0.183 | M84: 36.1 | N84: 40.8 | O84: 1 | P84: brainstorming:34 | Q84: Clarify:34 | S84: 0 | T84: 0 | U84: yes | V84: 458 | W84: 613
A85: xGJQzX9xF8hiV7do0UJcRywUfk62 | B85: -OwQ6FpS4RkvXqm2s3ks | C85: Thriller Writing Ideas Request | D85: 2026-07-01 08:38:36 | E85: 2026-07-01 08:43:06 | F85: brainstorming | G85: 26 | H85: 13 | I85: 13 | J85: 465 | K85: 3477 | L85: 0.134 | M85: 35.8 | N85: 43.7 | O85: 0 | P85: brainstorming:26 | Q85: Clarify:26 | S85: 0 | T85: 0 | U85: yes | V85: 477 | W85: 465
A86: yFZ29RKkP3ZRcqIqvJze5SeqX002 | B86: -OwQkx4q2oQ4bT9uY9WD | C86: Forest Remembers, Fox Finds Voice | D86: 2026-07-01 11:40:44 | E86: 2026-07-01 11:50:38 | F86: brainstorming | G86: 12 | H86: 6 | I86: 6 | J86: 87 | K86: 323 | L86: 0.269 | M86: 14.5 | N86: 10.2 | O86: 0 | P86: brainstorming:12 | Q86: Clarify:12 | S86: 0 | T86: 0 | U86: yes | V86: 421 | W86: 87
A87: yc98Hxm3OGdTaHiX0mOgucUC2j12 | B87: -OwWRrjgdTgrdzykkmHF | C87: Lost in a Crowded Museum | D87: 2026-07-02 14:10:46 | E87: 2026-07-02 14:16:36 | F87: brainstorming | G87: 34 | H87: 17 | I87: 17 | J87: 162 | K87: 1417 | L87: 0.114 | M87: 9.5 | N87: 38.6 | O87: 0 | P87: brainstorming:34 | Q87: Clarify:34 | S87: 0 | T87: 0 | U87: yes | V87: 522 | W87: 162
A88: yp1uAONc9xae65nCM31fKGbrpco2 | B88: -OwWRLKKlXlf_LBxq3Hr | C88: Late Rush to Missed Presentation | D88: 2026-07-02 14:08:27 | E88: 2026-07-02 14:14:40 | F88: brainstorming | G88: 22 | H88: 11 | I88: 11 | J88: 43 | K88: 497 | L88: 0.087 | M88: 3.9 | N88: 24.8 | O88: 3 | P88: brainstorming:22 | Q88: Clarify:22 | S88: 0 | T88: 0 | U88: yes | V88: 167 | W88: 43

Sheet Turns
A1: uid | B1: session_id | C1: turn_index | D1: role | E1: mode | F1: stage | G1: timestamp | H1: word_count | I1: payload_kind | J1: visible_text | K1: raw_content_if_payload
A2: 0QaQYslhRSXNMdCEaDY35HzA2Xl2 | B2: -OwWRuDalQgU7vQhUj5g | C2: 0 | D2: student | E2: brainstorming | F2: Clarify | G2: 2026-07-02 14:12:49 | H2: 13 | J2: a girl is visiting her grandparent's creepy old house to collect their belongings
A3: 0QaQYslhRSXNMdCEaDY35HzA2Xl2 | B3: -OwWRuDalQgU7vQhUj5g | C3: 1 | D3: bot | E3: brainstorming | F3: Clarify | G3: 2026-07-02 14:12:57 | H3: 54 | J3: I love this premise! A quiet, personal task set against a creepy backdrop creates great tension. What draws you to this idea—is it the mystery of what she might find, or the emotional weight of saying goodbye? Let's frame it as an opportunity: How might we make the house itself feel like a character?
A4: 0QaQYslhRSXNMdCEaDY35HzA2Xl2 | B4: -OwWRuDalQgU7vQhUj5g | C4: 2 | D4: student | E4: brainstorming | F4: Clarify | G4: 2026-07-02 14:13:35 | H4: 7 | J4: the house is rusty and worn out
A5: 0QaQYslhRSXNMdCEaDY35HzA2Xl2 | B5: -OwWRuDalQgU7vQhUj5g | C5: 3 | D5: bot | E5: brainstorming | F5: Clarify | G5: 2026-07-02 14:13:41 | H5: 40 | J5: Exactly — the house already feels alive in its decay. That rawness could tell its own story. Let me reframe what you shared into another opportunity: How might we make the ordinary objects in the house feel unsettling or significant?
A6: 0QaQYslhRSXNMdCEaDY35HzA2Xl2 | B6: -OwWRuDalQgU7vQhUj5g | C6: 4 | D6: student | E6: brainstorming | F6: Clarify | G6: 2026-07-02 14:14:23 | H6: 3 | J6: im not sure
A7: 0QaQYslhRSXNMdCEaDY35HzA2Xl2 | B7: -OwWRuDalQgU7vQhUj5g | C7: 5 | D7: bot | E7: brainstorming | F7: Clarify | G7: 2026-07-02 14:14:31 | H7: 29 | J7: That's okay — uncertainty is part of the process. Let me try another angle. How might we use the act of collecting belongings to reveal a hidden family secret?
A8: 0QaQYslhRSXNMdCEaDY35HzA2Xl2 | B8: -OwWRuDalQgU7vQhUj5g | C8: 6 | D8: student | E8: brainstorming | F8: Clarify | G8: 2026-07-02 14:15:34 | H8: 14 | J8: while trying to find the belongings, she accidently finds something that she shouldnt have
A9: 0QaQYslhRSXNMdCEaDY35HzA2Xl2 | B9: -OwWRuDalQgU7vQhUj5g | C9: 7 | D9: bot | E9: brainstorming | F9: Clarify | G9: 2026-07-02 14:15:40 | H9: 31 | J9: That's a strong hook — the accidental discovery adds tension and stakes. Let me capture that as a question. How might we make the discovery feel inevitable yet shocking in hindsight?
A10: 0QaQYslhRSXNMdCEaDY35HzA2Xl2 | B10: -OwWRuDalQgU7vQhUj5g | C10: 8 | D10: student | E10: brainstorming | F10: Clarify | G10: 2026-07-02 14:16:29 | H10: 3 | J10: i dotn know
A11: 0QaQYslhRSXNMdCEaDY35HzA2Xl2 | B11: -OwWRuDalQgU7vQhUj5g | C11: 9 | D11: bot | E11: brainstorming | F11: Clarify | G11: 2026-07-02 14:16:36 | H11: 60 | J11: That's completely fine — sometimes the best ideas come from not knowing. Let me summarize what we have so far: A young girl visits her grandparents' rusty, worn-out house to collect their belongings, and accidentally finds something she shouldn't have. We've got three solid HMW questions. Let me check if we're ready to move into exploring variations — sound good?
A12: 0QaQYslhRSXNMdCEaDY35HzA2Xl2 | B12: -OwWRuDalQgU7vQhUj5g | C12: 10 | D12: student | E12: brainstorming | F12: Clarify | G12: 2026-07-02 14:16:56 | H12: 1 | J12: okay
A13: 0QaQYslhRSXNMdCEaDY35HzA2Xl2 | B13: -OwWRuDalQgU7vQhUj5g | C13: 11 | D13: bot | E13: brainstorming | F13: Clarify | G13: 2026-07-02 14:17:03 | H13: 25 | I13: full_json | J13: Great, let's start exploring! What if we SUBSTITUTE what she finds? Instead of a secret object, what if she finds a living person hiding there? | K13: <p>[ { "action": "switch_stage", "reasoning": "3 HMWs collected and base concept is clear (girl discovers something forbidden in grandparents' abandoned house). Ready to explore SCAMPER variations.", "data": { "toStage": "Ideate" } }, { "action": "respond", "reasoning": "Transition to ideation stage with substitute technique prompt", "data": { "message": "Great, let's start exploring! What if we SUBSTITUTE what she finds? Instead of a secret object, what if she finds a living person hiding there?" } } ]</p>
A14: 0QaQYslhRSXNMdCEaDY35HzA2Xl2 | B14: -OwWRuDalQgU7vQhUj5g | C14: 12 | D14: student | E14: brainstorming | F14: Clarify | G14: 2026-07-02 14:18:24 | H14: 13 | J14: what about a small animal that doesnt look like it came from earth
A15: 0QaQYslhRSXNMdCEaDY35HzA2Xl2 | B15: -OwWRuDalQgU7vQhUj5g | C15: 13 | D15: bot | E15: brainstorming | F15: Clarify | G15: 2026-07-02 14:18:32 | H15: 30 | I15: full_json | J15: That's a fascinating shift — alien creature in a dusty old house. What if we COMBINE that with a family secret? Maybe the grandparents were hiding this creature for years. | K15: <p>[ { "action": "log_idea", "reasoning": "User applies Substitute (what is found) - shifting from human secret to alien creature adds sci-fi/mystery element", "data": { "idea": "Instead of a forbidden secret, the girl finds a small, otherworldly animal hiding in the abandoned house.", "ideaId": null, "scamperTechnique": "Substitute", "evaluations": { "flexibilityCategory": "Plot", "elaboration": "Medium", "originality": "High", "reasoning": "Shifts genre from family drama to sci-fi mystery. The creature's origin and purpose become the central question." } } }, { "action": "respond", "reasoning": "Acknowledge the creative pivot and prompt for more detail", "data": { "message": "That's a fascinating shift — alien creature in a dusty old house. What if we COMBINE that with a family secret? Maybe the grandparents were hiding this creature for years." } } ]</p>
A16: 0QaQYslhRSXNMdCEaDY35HzA2Xl2 | B16: -OwWTu17Sxd9ROSqJ5t4 | C16: 0 | D16: student | E16: brainstorming | F16: Clarify | G16: 2026-07-02 14:21:07 | H16: 34 | J16: a girl is at her grandparent's old, rusty and worn out house to look for their belongings. while trying to find the belongings, she accidentally discovers a small animal that didnt come from earth
A17: 0QaQYslhRSXNMdCEaDY35HzA2Xl2 | B17: -OwWTu17Sxd9ROSqJ5t4 | C17: 1 | D17: bot | E17: brainstorming | F17: Clarify | G17: 2026-07-02 14:21:14 | H17: 50 | J17: That's a wonderful starting point—the contrast between the familiar, worn-out house and a completely alien creature is full of potential. To help frame this as a creative challenge: How might we make the discovery of the alien animal feel both magical and deeply personal, tied to the grandmother's hidden past?
A18: 0QaQYslhRSXNMdCEaDY35HzA2Xl2 | B18: -OwWTu17Sxd9ROSqJ5t4 | C18: 2 | D18: student | E18: brainstorming | F18: Clarify | G18: 2026-07-02 14:22:47 | H18: 14 | J18: her grandmother is actually a doppelganger and the real one had died long before
A19: 0QaQYslhRSXNMdCEaDY35HzA2Xl2 | B19: -OwWTu17Sxd9ROSqJ5t4 | C19: 3 | D19: bot | E19: brainstorming | F19: Clarify | G19: 2026-07-02 14:22:54 | H19: 46 | J19: That's a chilling revelation! So the alien animal might be connected to the doppelganger grandmother. Let me reframe that: How might we weave clues about the grandmother's true nature into the house itself, making the discovery of the alien animal the key that unlocks the mystery?
A20: 0QaQYslhRSXNMdCEaDY35HzA2Xl2 | B20: -OwWTu17Sxd9ROSqJ5t4 | C20: 4 | D20: student | E20: brainstorming | F20: Clarify | G20: 2026-07-02 14:25:23 | H20: 1 | J20: idk
A21: 0QaQYslhRSXNMdCEaDY35HzA2Xl2 | B21: -OwWTu17Sxd9ROSqJ5t4 | C21: 5 | D21: bot | E21: brainstorming | F21: Clarify | G21: 2026-07-02 14:25:29 | H21: 24 | J21: That's okay! Let's try another angle. How might we make the alien animal's reaction to the doppelganger grandmother reveal the truth to the girl?
A22: 0QaQYslhRSXNMdCEaDY35HzA2Xl2 | B22: -OwWTu17Sxd9ROSqJ5t4 | C22: 6 | D22: student | E22: brainstorming | F22: Clarify | G22: 2026-07-02 14:26:10 | H22: 12 | J22: the alien animal gets scared of the girl whos name is mia
A23: 0QaQYslhRSXNMdCEaDY35HzA2Xl2 | B23: -OwWTu17Sxd9ROSqJ5t4 | C23: 7 | D23: bot | E23: brainstorming | F23: Clarify | G23: 2026-07-02 14:26:17 | H23: 50 | J23: That's a beautiful, instinctive clue. So the animal knows something Mia doesn't yet—it senses the doppelganger's influence on her. Let me capture that as an opportunity question: How might we use the alien animal's fear of Mia to force her to question her own identity and connection to this house?
A24: 0QaQYslhRSXNMdCEaDY35HzA2Xl2 | B24: -OwWTu17Sxd9ROSqJ5t4 | C24: 8 | D24: student | E24: brainstorming | F24: Clarify | G24: 2026-07-02 14:29:54 | H24: 29 | J24: the animal runs under a bed when mia tries to approach it. mia then looked under the bed and finds a open trapdoor that the animal used to escape
A25: 0QaQYslhRSXNMdCEaDY35HzA2Xl2 | B25: -OwWTu17Sxd9ROSqJ5t4 | C25: 9 | D25: bot | E25: brainstorming | F25: Clarify | G25: 2026-07-02 14:30:00 | H25: 34 | J25: That's a great physical clue leading to discovery. Let me frame that: How might we design what's below the trapdoor to reveal both the grandmother's secret and the animal's origin at the same time?
A26: 0QaQYslhRSXNMdCEaDY35HzA2Xl2 | B26: -OwWTu17Sxd9ROSqJ5t4 | C26: 10 | D26: student | E26: brainstorming | F26: Clarify | G26: 2026-07-02 14:35:57 | H26: 9 | J26: change the alien like creature to a mini dragon
A27: 0QaQYslhRSXNMdCEaDY35HzA2Xl2 | B27: -OwWTu17Sxd9ROSqJ5t4 | C27: 11 | D27: bot | E27: brainstorming | F27: Clarify | G27: 2026-07-02 14:36:03 | H27: 40 | J27: That's a perfect substitution! A mini dragon feels more magical and personal for this story. Let me reframe as an opportunity: How might we make the mini dragon's presence in the house reveal clues about the doppelganger grandmother's true motives?
... A29: 0QaQYslhRSXNMdCEaDY35HzA2Xl2 | B29: -OwWTu17Sxd9ROSqJ5t4 | C29: 13 | D29: bot | E29: brainstorming | F29: Clarify | G29: 2026-07-02 14:36:33 | H29: 27 | J29: No worries. Let's try a different question. How might we make the mini dragon's reaction to the grandmother (fear? curiosity?) hint at who the real threat is?
A30: 0QaQYslhRSXNMdCEaDY35HzA2Xl2 | B30: -OwWTu17Sxd9ROSqJ5t4 | C30: 14 | D30: student | E30: deepthinking | G30: 2026-07-02 14:37:55 | H30: 1 | J30: idk
A31: 0QaQYslhRSXNMdCEaDY35HzA2Xl2 | B31: -OwWTu17Sxd9ROSqJ5t4 | C31: 15 | D31: bot | E31: deepthinking | G31: 2026-07-02 14:38:06 | H31: 44 | J31: I can see you're feeling stuck, and that's completely okay—sometimes stepping back and looking at the bigger picture helps. Let's shift gears a bit and think about what's driving your character forward. What is your character trying to achieve in this scene or storyline?
A32: 0QaQYslhRSXNMdCEaDY35HzA2Xl2 | B32: -OwWTu17Sxd9ROSqJ5t4 | C32: 16 | D32: student | E32: deepthinking | G32: 2026-07-02 14:38:52 | H32: 28 | J32: mia is now trying to find out why there is a hidden trapodoor under her grandma's bed and why there is a dragon living in hre house too
A33: 0QaQYslhRSXNMdCEaDY35HzA2Xl2 | B33: -OwWTu17Sxd9ROSqJ5t4 | C33: 17 | D33: bot | E33: deepthinking | G33: 2026-07-02 14:38:58 | H33: 31 | J33: Great! Now we have a clear goal for Mia. Let me check what we already know—have you established any details about the grandmother's past or her relationship with the house yet?
A34: 0QaQYslhRSXNMdCEaDY35HzA2Xl2 | B34: -OwWTu17Sxd9ROSqJ5t4 | C34: 18 | D34: student | E34: deepthinking | G34: 2026-07-02 14:39:13 | H34: 1 | J34: no
A35: 0QaQYslhRSXNMdCEaDY35HzA2Xl2 | B35: -OwWTu17Sxd9ROSqJ5t4 | C35: 19 | D35: bot | E35: deepthinking | G35: 2026-07-02 14:39:18 | H35: 35 | J35: Got it! No background yet for Grandma or the house. Let's ask a focused question to build some depth. What does Mia know about her grandmother's past that makes this discovery especially surprising or unsettling?
A36: 0QaQYslhRSXNMdCEaDY35HzA2Xl2 | B36: -OwWTu17Sxd9ROSqJ5t4 | C36: 20 | D36: student | E36: deepthinking | G36: 2026-07-02 14:40:49 | H36: 18 | J36: mia doesnt know much about her grandmother except the fact that she used to work as a scientist
A37: 0QaQYslhRSXNMdCEaDY35HzA2Xl2 | B37: -OwWTu17Sxd9ROSqJ5t4 | C37: 21 | D37: bot | E37: deepthinking | G37: 2026-07-02 14:40:55 | H37: 63 | J37: Excellent! That's a fantastic detail—a scientist grandmother opens up so many possibilities. It makes the trapdoor and the dragon feel less random and more like pieces of a larger puzzle connected to her work. Now that we have this key piece of information, should we save it to your story project? I can record Mia's goal and her grandmother's profession as a scientist.
A38: 0QaQYslhRSXNMdCEaDY35HzA2Xl2 | B38: -OwWTu17Sxd9ROSqJ5t4 | C38: 22 | D38: student | E38: deepthinking | G38: 2026-07-02 14:41:13 | H38: 1 | J38: okay
A39: 0QaQYslhRSXNMdCEaDY35HzA2Xl2 | B39: -OwWTu17Sxd9ROSqJ5t4 | C39: 23 | D39: bot | E39: deepthinking | G39: 2026-07-02 14:41:21 | H39: 54 | I39: inline_json | J39: I've created two characters for your story: Mia (the curious protagonist) and Grandma (the mysterious scientist). Now, let's go deeper— what kind of scientist was Grandma? Her specialty could unlock which secrets the trapdoor and dragon are connected to. For example: a biologist, a physicist, a cryptozoologist (someone who studies hidden animals like dragons)? | K39: <p><json> { "action": "stage_change", "reasoning": "User confirmed. Creating Mia as a character (Person node) and recording her goal (find out why grandma has a hidden trapdoor and a dragon). Also creating Grandma as a scientist character.", "data": { "requests": [ { "entityType": "node", "entityId": null, "newData": { "label": "Mia", "group": "Person", "attributes": { "goal": "uncover why her grandmother has a hidden trapdoor and a dragon", "knowledge": "knows little about grandma's past besides she was a scientist" } } }, { "entityType": "node", "entityId": null, "newData": { "label": "Grandma", "group": "Person", "attributes": { "profession": "scientist", "known_objects": "hidden trapdoor under bed, dragon living in house" } } } ] } } </json></p> <p>I've created two characters for your story: <strong>Mia</strong> (the curious protagonist) and <strong>Grandma</strong> (the mysterious scientist).</p> <p><strong>Now, let's go deeper—</strong> what kind of scientist was Grandma? Her specialty could unlock which secrets the trapdoor and dragon are connected to. For example: a biologist, a physicist, a cryptozoologist (someone who studies hidden animals like dragons)?</p>
A40: 0QaQYslhRSXNMdCEaDY35HzA2Xl2 | B40: -OwWTu17Sxd9ROSqJ5t4 | C40: 24 | D40: student | E40: deepthinking | G40: 2026-07-02 14:42:36 | H40: 21 | J40: uhm the real grandma died alrdy mia jus doesnt know that yet since there is a doppelganger acting like mia's grandma
A41: 0QaQYslhRSXNMdCEaDY35HzA2Xl2 | B41: -OwWTu17Sxd9ROSqJ5t4 | C41: 25 | D41: bot | E41: deepthinking | G41: 2026-07-02 14:42:45 | H41: 75 | I41: inline_json | J41: That's a brilliant twist! The doppelgänger adds so much tension. Let me update the records. Okay, now here's a question that digs into the mystery deeper: Since Mia doesn't know Grandma is an imposter, how has the doppelgänger been acting? Is the doppelgänger playing a warm, loving role to keep up appearances, or has Mia noticed small, strange behaviors that feel off about her grandmother? This could hint at how the truth might eventually unravel. | K41: <p>That's a brilliant twist! The doppelgänger adds so much tension. Let me update the records.</p> <p><json> { "action": "stage_change", "reasoning": "User revealed the real grandma is dead and a doppelgänger is impersonating her. Updating 'Grandma' node to reflect doppelgänger status, and confirming Mia's lack of knowledge.", "data": { "requests": [ { "entityType": "node", "entityId": null, "newData": { "label": "Grandma", "group": "Person", "attributes": { "profession": "scientist", "status": "deceased", "known_objects": "hidden trapdoor under bed, dragon living in house", "impersonator": "doppelgänger active", "real_grandma_identity": "unknown to Mia at this point" } } } ] } } </json></p> <p><strong>Okay, now here's a question that digs into the mystery deeper:</strong> Since Mia doesn't know Grandma is an imposter, how has the doppelgänger been acting? Is the doppelgänger playing a warm, loving role to keep up appearances, or has Mia noticed small, strange behaviors that feel off about her grandmother? This could hint at how the truth might eventually unravel.</p>
A42: 0QaQYslhRSXNMdCEaDY35HzA2Xl2 | B42: -OwWTu17Sxd9ROSqJ5t4 | C42: 26 | D42: student | E42: brainstorming | F42: Clarify | G42: 2026-07-02 14:44:52 | H42: 15 | J42: there has been times where mia had noticed the way her grandma ssometimes acts unhuman
A43: 0QaQYslhRSXNMdCEaDY35HzA2Xl2 | B43: -OwWTu17Sxd9ROSqJ5t4 | C43: 27 | D43: bot | E43: brainstorming | F43: Clarify | G43: 2026-07-02 14:44:59 | H43: 36 | J43: That eerie, unhuman behavior is perfect foreshadowing. Let's explore this further. What kinds of unhuman things has Mia noticed? For example: no blinking, perfect stillness, repeating phrases, or something more unsettling like knowing things she shouldn't?
A44: 0QaQYslhRSXNMdCEaDY35HzA2Xl2 | B44: -OwWTu17Sxd9ROSqJ5t4 | C44: 28 | D44: student | E44: brainstorming | F44: Clarify | G44: 2026-07-02 14:45:37 | H44: 2 | J44: repeating phrases
A45: 0QaQYslhRSXNMdCEaDY35HzA2Xl2 | B45: -OwWTu17Sxd9ROSqJ5t4 | C45: 29 | D45: bot | E45: brainstorming | F45: Clarify | G45: 2026-07-02 14:45:44 | H45: 50 | J45: That's wonderfully creepy - a classic sign that something isn't quite right. The doppelgänger might be running on old programming or recorded memories, getting "stuck" in loops. How might we explore the tension between Mia noticing these glitches and her desire to dismiss them as just her grandmother getting older?
A46: 0QaQYslhRSXNMdCEaDY35HzA2Xl2 | B46: -OwWTu17Sxd9ROSqJ5t4 | C46: 30 | D46: student | E46: brainstorming | F46: Clarify | G46: 2026-07-02 14:46:22 | H46: 8 | J46: Mia thinks her grandma has a stuttering problem
A47: 0QaQYslhRSXNMdCEaDY35HzA2Xl2 | B47: -OwWTu17Sxd9ROSqJ5t4 | C47: 31 | D47: bot | E47: brainstorming | F47: Clarify | G47: 2026-07-02 14:46:30 | H47: 66 | J47: Excellent rationalization from Mia — stuttering is a very believable, human excuse for the repetition. It gives the doppelgänger believable cover. That makes me curious about the trapdoor. Let's explore that. Substitute the who: What if Mia isn't the one to first discover the trapdoor? What if a nosy neighbor or a stray cat accidentally reveals it first, forcing both Mia and the doppelgänger to react?
A48: 0QaQYslhRSXNMdCEaDY35HzA2Xl2 | B48: -OwWTu17Sxd9ROSqJ5t4 | C48: 32 | D48: student | E48: brainstorming | F48: Clarify | G48: 2026-07-02 14:47:45 | H48: 3 | J48: i dont understand
A49: 0QaQYslhRSXNMdCEaDY35HzA2Xl2 | B49: -OwWTu17Sxd9ROSqJ5t4 | C49: 33 | D49: bot | E49: brainstorming | F49: Clarify | G49: 2026-07-02 14:47:52 | H49: 70 | J49: No problem, let me explain simply. Right now, Mia assumes the repeating is a stutter. That's a good cover for the doppelgänger. Instead of Mia finding the trapdoor first, what if someone else finds it? Like: - A repair person fixing a leak - A mailman dropping off a package - A friend visiting This forces both Mia and the fake grandma to react quickly and could expose secrets sooner.
A50: 0QaQYslhRSXNMdCEaDY35HzA2Xl2 | B50: -OwWTu17Sxd9ROSqJ5t4 | C50: 34 | D50: student | E50: brainstorming | F50: Clarify | G50: 2026-07-02 14:48:17 | H50: 7 | J50: no one lives in that hosue anymore
A51: 0QaQYslhRSXNMdCEaDY35HzA2Xl2 | B51: -OwWTu17Sxd9ROSqJ5t4 | C51: 35 | D51: bot | E51: brainstorming | F51: Clarify | G51: 2026-07-02 14:48:24 | H51: 43 | J51: Ah, so Mia discovers the trapdoor *because* she's alone there. That changes everything. How might we modify this — what if the house isn't just empty, but also forbidden for Mia to enter? Maybe her parent told her to never go back there?
A52: 0QaQYslhRSXNMdCEaDY35HzA2Xl2 | B52: -OwWTu17Sxd9ROSqJ5t4 | C52: 36 | D52: student | E52: brainstorming | F52: Clarify | G52: 2026-07-02 14:49:05 | H52: 130 | J52: Mia had just arrived at her grandmother's old worn out house. The floorboards creaked loudly under her shoes and the paint on the walls are ripping apart. She was sent here by her parents to find her grandmother's belongings but in the midst of it, she accidentally ends up discovering a small dragon like creature living in her grandmother's bedroom instead. When Mia tried approaching the small dragon, it let out a small shriek before slipping under her grandma's bed. Mia starts questioning about what she had just saw but instead of leaving the house, she moves towards the bed and looks under it, finding a hidden open trapdoor that the small dragon probably used. Mia heads down the trapdoor, finding a (this is how my story going so far)
A53: 0QaQYslhRSXNMdCEaDY35HzA2Xl2 | B53: -OwWTu17Sxd9ROSqJ5t4 | C53: 37 | D53: bot | E53: brainstorming | F53: Clarify | G53: 2026-07-02 14:49:13 | H53: 69 | J53: That's a wonderful setup — the creature, the trapdoor, the mystery. It feels like a classic fantasy adventure beginning. Let me help you reframe this into a creative challenge with a "How Might We" question: How might we make the underground world beneath the trapdoor feel both magical and threatening? Does that capture the feeling you're going for, or is there a different tension you want to focus on?
... A130: 3w9E9Xr7oehGE2ThwcIxvybuKwE2 | B130: -OwVprk7ZBkimJoUaB_0 | C130: 16 | D130: student | E130: brainstorming | F130: Clarify | G130: 2026-07-02 11:27:37 | H130: 10 | J130: maybe not ally, the dog chases the cats and birds
A131: 3w9E9Xr7oehGE2ThwcIxvybuKwE2 | B131: -OwVprk7ZBkimJoUaB_0 | C131: 17 | D131: bot | E131: brainstorming | F131: Clarify | G131: 2026-07-02 11:27:46 | H131: 34 | I131: full_json | J131: Perfect, that gives the dog a fun flaw to keep things lively! Let's try Eliminate. What if we removed the human perspective entirely—no owners searching, no neighbors watching—just pure dog's-eye view the whole way | K131: <p>[ { "action": "log_idea", "reasoning": "User specifies dog-chases-cats dynamic, adding a recurring comedic obstacle and creating a clear predator-prey rhythm to the journey", "data": { "idea": "Dog has a strong prey drive, repeatedly sidetracked by chasing cats and birds, causing comedic detours from its main journey", "ideaId": null, "scamperTechnique": "Modify", "evaluations": { "flexibilityCategory": "Character", "elaboration": "Medium", "originality": "Medium", "reasoning": "Refines dog's core personality trait into a narrative engine for comedy and obstacles" } } }, { "action": "respond", "reasoning": "Acknowledge and pivot to Eliminate technique", "data": { "message": "Perfect, that gives the dog a fun flaw to keep things lively! Let's try Eliminate. What if we removed the human perspective entirely—no owners searching, no neighbors watching—just pure dog's-eye view the whole way" } } ]</p>
A132: 3w9E9Xr7oehGE2ThwcIxvybuKwE2 | B132: -OwVprk7ZBkimJoUaB_0 | C132: 18 | D132: student | E132: brainstorming | F132: Clarify | G132: 2026-07-02 11:28:12 | H132: 1 | J132: sure
A133: 3w9E9Xr7oehGE2ThwcIxvybuKwE2 | B133: -OwVprk7ZBkimJoUaB_0 | C133: 19 | D133: bot | E133: brainstorming | F133: Clarify | G133: 2026-07-02 11:28:20 | H133: 34 | I133: full_json | J133: That would create a truly unique voice! Last one for now: Reverse. What if the dog isn't lost at all—but is actually leading its owner on a secret adventure and thinks it's in charge? | K133: <p>[ { "action": "log_idea", "reasoning": "User agrees to eliminate human perspective entirely, creating a pure canine POV story", "data": { "idea": "Eliminate all human viewpoints and dialogue. The story is told entirely through the dog's sensory experiences and canine logic", "ideaId": null, "scamperTechnique": "Eliminate", "evaluations": { "flexibilityCategory": "Mechanic", "elaboration": "Medium", "originality": "High", "reasoning": "Pure sensory narration is uncommon and challenging, raising originality" } } }, { "action": "respond", "reasoning": "Encourage and suggest Reverse technique next", "data": { "message": "That would create a truly unique voice! Last one for now: Reverse. What if the dog isn't lost at all—but is actually leading its owner on a secret adventure and thinks it's in charge?" } } ]</p>
A134: 3w9E9Xr7oehGE2ThwcIxvybuKwE2 | B134: -OwVprk7ZBkimJoUaB_0 | C134: 20 | D134: student | E134: brainstorming | F134: Clarify | G134: 2026-07-02 11:28:46 | H134: 7 | J134: ok i got my plan.. thank you
A135: 3w9E9Xr7oehGE2ThwcIxvybuKwE2 | B135: -OwVprk7ZBkimJoUaB_0 | C135: 21 | D135: bot | E135: brainstorming | F135: Clarify | G135: 2026-07-02 11:28:53 | H135: 38 | J135: That sounds wonderful! I'm glad the process helped you shape your idea. A pure canine-pov, scent-driven adventure through a neighborhood with a pond, chasing cats and birds—sounds like a charming and unique story. Best of luck writing it!
A136: 3w9E9Xr7oehGE2ThwcIxvybuKwE2 | B136: -OwVprk7ZBkimJoUaB_0 | C136: 22 | D136: student | E136: brainstorming | F136: Clarify | G136: 2026-07-02 11:33:06 | H136: 6 | J136: how shld i start the story
A137: 3w9E9Xr7oehGE2ThwcIxvybuKwE2 | B137: -OwVprk7ZBkimJoUaB_0 | C137: 23 | D137: bot | E137: brainstorming | F137: Clarify | G137: 2026-07-02 11:33:14 | H137: 38 | J137: Start with a single, vivid scent. "The smell of Mrs. Chen's bacon was the first thing that pulled me away from the yard." Jump right into the dog's sensory world and let the chase begin from line one.
A138: 5iy5k09B1rhCSEHuf17zeB2lmXL2 | B138: -OwWRTKbVRiZWmp90Opw | C138: 0 | D138: student | E138: brainstorming | F138: Clarify | G138: 2026-07-02 14:11:21 | H138: 14 | J138: can you help me make ideas for a story about the best mistake ever
A139: 5iy5k09B1rhCSEHuf17zeB2lmXL2 | B139: -OwWRTKbVRiZWmp90Opw | C139: 1 | D139: bot | E139: brainstorming | F139: Clarify | G139: 2026-07-02 14:11:29 | H139: 27 | J139: That's a fun premise! What makes a mistake "the best" for you - is it about unexpected positive consequences, or a lesson learned, or something else entirely?
A140: 5iy5k09B1rhCSEHuf17zeB2lmXL2 | B140: -OwWRTKbVRiZWmp90Opw | C140: 2 | D140: student | E140: brainstorming | F140: Clarify | G140: 2026-07-02 14:11:51 | H140: 4 | J140: unexpected positive consequences please
A141: 5iy5k09B1rhCSEHuf17zeB2lmXL2 | B141: -OwWRTKbVRiZWmp90Opw | C141: 3 | D141: bot | E141: brainstorming | F141: Clarify | G141: 2026-07-02 14:11:58 | H141: 41 | J141: That's a great angle! So the mistake itself might seem disastrous, but it accidentally leads to something wonderful. How might we frame this so the mistake feels like a real mistake at first, not just an obvious good thing in disguise?
A142: 5iy5k09B1rhCSEHuf17zeB2lmXL2 | B142: -OwWRTKbVRiZWmp90Opw | C142: 4 | D142: student | E142: brainstorming | F142: Clarify | G142: 2026-07-02 14:12:36 | H142: 3 | J142: missing your flight?
A143: 5iy5k09B1rhCSEHuf17zeB2lmXL2 | B143: -OwWRTKbVRiZWmp90Opw | C143: 5 | D143: bot | E143: brainstorming | F143: Clarify | G143: 2026-07-02 14:12:42 | H143: 28 | J143: What if we frame it as: "How might we turn a missed flight into a life-changing opportunity?" Does that capture the essence of your story idea for you?
A144: 5iy5k09B1rhCSEHuf17zeB2lmXL2 | B144: -OwWRTKbVRiZWmp90Opw | C144: 6 | D144: student | E144: brainstorming | F144: Clarify | G144: 2026-07-02 14:13:27 | H144: 6 | J144: like you know the plane crashes?
A145: 5iy5k09B1rhCSEHuf17zeB2lmXL2 | B145: -OwWRTKbVRiZWmp90Opw | C145: 7 | D145: bot | E145: brainstorming | F145: Clarify | G145: 2026-07-02 14:13:34 | H145: 39 | J145: That's a classic and powerful twist! The missed flight becomes the mistake that saves their life. But there's still so much to explore. How might we make the aftermath of that survival just as impactful as the crash itself?
... A197: 6FGzR0FFoIMiQ3y2otIsOqIyrMh2 | B197: -OwVMNSQxBd_hrnwU2xD | C197: 5 | D197: bot | E197: brainstorming | F197: Clarify | G197: 2026-07-02 09:18:48 | H197: 37 | J197: That's a powerful internal conflict. The gap between who he is and what he fears being seen as. How might we use the bus and lateness as a pressure cooker that forces this fear to the surface?
A198: 6FGzR0FFoIMiQ3y2otIsOqIyrMh2 | B198: -OwVMNSQxBd_hrnwU2xD | C198: 6 | D198: student | E198: deepthinking | G198: 2026-07-02 09:19:37 | H198: 1 | J198: yea
A199: 6FGzR0FFoIMiQ3y2otIsOqIyrMh2 | B199: -OwVMNSQxBd_hrnwU2xD | C199: 7 | D199: bot | E199: deepthinking | G199: 2026-07-02 09:19:47 | H199: 32 | J199: Got it — you're agreeing, which is good, but let's zoom in a little. What does that fear actually look like in a specific moment? Could you describe that in sharper detail?
A200: 6FGzR0FFoIMiQ3y2otIsOqIyrMh2 | B200: -OwVMNSQxBd_hrnwU2xD | C200: 8 | D200: student | E200: brainstorming | F200: Clarify | G200: 2026-07-02 09:27:41 | H200: 1 | J200: \why
A201: 6FGzR0FFoIMiQ3y2otIsOqIyrMh2 | B201: -OwVMNSQxBd_hrnwU2xD | C201: 9 | D201: bot | E201: brainstorming | F201: Clarify | G201: 2026-07-02 09:27:48 | H201: 37 | J201: I'm just trying to help you nail down the emotional core. If the teacher thinks he's a bad student, what's the worst thing that could happen because of that misunderstanding? A specific consequence, not just a feeling.
A202: 6xMddtGgmcN42mZbnypoitgkFpa2 | B202: -OwWRBt8DVkudBkXs5c_ | C202: 0 | D202: student | E202: brainstorming | F202: Clarify | G202: 2026-07-02 14:09:11 | H202: 24 | J202: i wanted to write about a girl named Junette who is suffering from depression, her academics, her abusive father, and her poker faced friends
A203: 6xMddtGgmcN42mZbnypoitgkFpa2 | B203: -OwWRBt8DVkudBkXs5c_ | C203: 1 | D203: bot | E203: brainstorming | F203: Clarify | G203: 2026-07-02 14:09:17 | H203: 20 | J203: Thanks for sharing that, Junette sounds like a deeply layered character. What initially drew you to telling her story specifically?
A204: 6xMddtGgmcN42mZbnypoitgkFpa2 | B204: -OwWRBt8DVkudBkXs5c_ | C204: 2 | D204: student | E204: brainstorming | F204: Clarify | G204: 2026-07-02 14:09:32 | H204: 8 | J204: a story i wrote a long time ago
A205: 6xMddtGgmcN42mZbnypoitgkFpa2 | B205: -OwWRBt8DVkudBkXs5c_ | C205: 3 | D205: bot | E205: brainstorming | F205: Clarify | G205: 2026-07-02 14:09:38 | H205: 23 | J205: That's powerful—returning to her story after all this time. What feels different about revisiting Junette now compared to when you first wrote her?
A206: 6xMddtGgmcN42mZbnypoitgkFpa2 | B206: -OwWRBt8DVkudBkXs5c_ | C206: 4 | D206: student | E206: deepthinking | G206: 2026-07-02 14:10:32 | H206: 8 | J206: okay i want something ismilar witha lotta metaphors
A207: 6xMddtGgmcN42mZbnypoitgkFpa2 | B207: -OwWRBt8DVkudBkXs5c_ | C207: 5 | D207: bot | E207: deepthinking | G207: 2026-07-02 14:10:40 | H207: 21 | J207: I don't have any previous information about that yet. Let's start building it together! What would you like to tell me?
A208: 6xMddtGgmcN42mZbnypoitgkFpa2 | B208: -OwWRBt8DVkudBkXs5c_ | C208: 6 | D208: bot | E208: deepthinking | G208: 2026-07-02 14:10:40 | H208: 21 | J208: I don't have any previous information about that yet. Let's start building it together! What would you like to tell me?
A209: 6xMddtGgmcN42mZbnypoitgkFpa2 | B209: -OwWRBt8DVkudBkXs5c_ | C209: 7 | D209: student | E209: brainstorming | F209: Clarify | G209: 2026-07-02 14:11:19 | H209: 22 | J209: sure uhm...theres a part where i put a rhetori question "How much pain do i have to feel to be considered hurting?"
A210: 6xMddtGgmcN42mZbnypoitgkFpa2 | B210: -OwWRBt8DVkudBkXs5c_ | C210: 8 | D210: bot | E210: brainstorming | F210: Clarify | G210: 2026-07-02 14:11:27 | H210: 32 | J210: That question already carries such weight. It could frame a lot of what we explore. How might we use metaphors to show the invisible weight she carries—without her having to name it?
A211: 6xMddtGgmcN42mZbnypoitgkFpa2 | B211: -OwWRBt8DVkudBkXs5c_ | C211: 9 | D211: student | E211: brainstorming | F211: Clarify | G211: 2026-07-02 14:12:19 | H211: 23 | J211: i also used how the father is abusive through "He gros disgustingly beautiful purple flowers and watering them with his yells and scoldings"
A212: 6xMddtGgmcN42mZbnypoitgkFpa2 | B212: -OwWRBt8DVkudBkXs5c_ | C212: 10 | D212: bot | E212: brainstorming | F212: Clarify | G212: 2026-07-02 14:12:26 | H212: 29 | J212: That's a haunting metaphor—turning abuse into something twistedly beautiful. It creates powerful dissonance. How might we extend that metaphor across different parts of Junette's life? Her academics, her friendships?
A213: 6xMddtGgmcN42mZbnypoitgkFpa2 | B213: -OwWRBt8DVkudBkXs5c_ | C213: 11 | D213: student | E213: brainstorming | F213: Clarify | G213: 2026-07-02 14:12:57 | H213: 19 | J213: but i gotta write something different like i want it to be similar but a different topic than this
A214: 6xMddtGgmcN42mZbnypoitgkFpa2 | B214: -OwWRBt8DVkudBkXs5c_ | C214: 12 | D214: bot | E214: brainstorming | F214: Clarify | G214: 2026-07-02 14:13:04 | H214: 47 | J214: So a theme of invisible pain, told through extended metaphors—but applied to a new situation instead of family abuse. What if the pain came from a different source? A broken friendship? Loss? Identity? How might we adapt that "beautiful poison" metaphor to a new kind of hurt?
A215: 6xMddtGgmcN42mZbnypoitgkFpa2 | B215: -OwWRBt8DVkudBkXs5c_ | C215: 13 | D215: student | E215: brainstorming | F215: Clarify | G215: 2026-07-02 14:13:22 | H215: 4 | J215: maybe loss of identity
A216: 6xMddtGgmcN42mZbnypoitgkFpa2 | B216: -OwWRBt8DVkudBkXs5c_ | C216: 14 | D216: bot | E216: brainstorming | F216: Clarify | G216: 2026-07-02 14:13:29 | H216: 30 | J216: That could be really powerful. How might we use a metaphor like a house being slowly emptied room by room to show pieces of her identity disappearing one by one?
A217: 6xMddtGgmcN42mZbnypoitgkFpa2 | B217: -OwWRBt8DVkudBkXs5c_ | C217: 15 | D217: student | E217: brainstorming | F217: Clarify | G217: 2026-07-02 14:14:40 | H217: 3 | J217: sure anything else?
A218: 6xMddtGgmcN42mZbnypoitgkFpa2 | B218: -OwWRBt8DVkudBkXs5c_ | C218: 16 | D218: bot | E218: brainstorming | F218: Clarify | G218: 2026-07-02 14:14:46 | H218: 28 | J218: How might we adapt the "watering" concept to show what fills the empty rooms? Instead of yells, maybe it's silence or other people's expectations slowly filling the space?
A219: 6xMddtGgmcN42mZbnypoitgkFpa2 | B219: -OwWRBt8DVkudBkXs5c_ | C219: 17 | D219: student | E219: brainstorming | F219: Clarify | G219: 2026-07-02 14:15:32 | H219: 32 | J219: i want to change the characters a little to a guy name octavius and he has a little sister which his parents favor and the dad is still abusive in this story
A220: 6xMddtGgmcN42mZbnypoitgkFpa2 | B220: -OwWRBt8DVkudBkXs5c_ | C220: 18 | D220: bot | E220: brainstorming | F220: Clarify | G220: 2026-07-02 14:15:38 | H220: 34 | J220: That's an interesting shift. So Octavius becomes invisible inside his own home. How might we use a metaphor like "being a ghost in his own house" to show his parents looking right through him?
... A287: 86IempJqjAe16ZnVEcfplb36dQK2 | B287: -OwVpU1B63hEDG7yjpwQ | C287: 14 | D287: student | E287: brainstorming | F287: Clarify | G287: 2026-07-02 11:57:26 | H287: 26 | J287: "X-Gene" is a presentation of their X(TRAORDINARY) Genetics. With aliens and wolves becoming one, they aim to show the universe the beauty of unity and oneness.
A288: 86IempJqjAe16ZnVEcfplb36dQK2 | B288: -OwVpU1B63hEDG7yjpwQ | C288: 15 | D288: bot | E288: brainstorming | F288: Clarify | G288: 2026-07-02 11:57:33 | H288: 29 | I288: full_json | J288: So each song has a layered purpose — not just entertainment, but a message about oneness. Do the individual wolf members have distinct alien traits tied to their songs? | K288: <p>{ "action": "respond", "reasoning": "Deepening the theme of unity — X-Gene shows genetic fusion as metaphor for cosmic harmony", "data": { "message": "So each song has a layered purpose — not just entertainment, but a message about oneness. Do the individual wolf members have distinct alien traits tied to their songs?" } }</p>
A289: 86IempJqjAe16ZnVEcfplb36dQK2 | B289: -OwVpU1B63hEDG7yjpwQ | C289: 16 | D289: student | E289: brainstorming | F289: Clarify | G289: 2026-07-02 12:04:10 | H289: 2 | J289: "Woke Up
A290: 86IempJqjAe16ZnVEcfplb36dQK2 | B290: -OwVpU1B63hEDG7yjpwQ | C290: 17 | D290: bot | E290: brainstorming | F290: Clarify | G290: 2026-07-02 12:04:17 | H290: 25 | J290: That emptiness is powerful — a clean slate to begin something new. What comes to mind when you picture the world just after 'Woke Up'?
A291: 86IempJqjAe16ZnVEcfplb36dQK2 | B291: -OwVpU1B63hEDG7yjpwQ | C291: 18 | D291: student | E291: brainstorming | F291: Clarify | G291: 2026-07-02 12:07:39 | H291: 82 | J291: "Woke Up", "Howling", "IYKYK", "Gala", "No Good", "O.R.B (Obviously Reads Bro)" are all part of a massive response to the universe tearing them down and insisting they cannot unite the cosmos. There are 6 songs here, and each song highlights the unique traits of one member. Yet there's a seventh member who doesn't have a song yet: the leader of XG, Jurin. Her song will be the most important and will define a major turning point in the plot of the story.
A292: 86IempJqjAe16ZnVEcfplb36dQK2 | B292: -OwVpU1B63hEDG7yjpwQ | C292: 19 | D292: bot | E292: brainstorming | F292: Clarify | G292: 2026-07-02 12:07:47 | H292: 41 | J292: Me encanta la idea de que Jurin aún no haya tenido su momento. Eso la convierte en un misterio central. ¿Qué tipo de punto de inflexión imaginas para ella, uno personal o uno que cambie el destino de toda la manada?
A293: 86IempJqjAe16ZnVEcfplb36dQK2 | B293: -OwVpU1B63hEDG7yjpwQ | C293: 20 | D293: student | E293: brainstorming | F293: Clarify | G293: 2026-07-02 12:08:07 | H293: 3 | J293: speak in english
A294: 86IempJqjAe16ZnVEcfplb36dQK2 | B294: -OwVpU1B63hEDG7yjpwQ | C294: 21 | D294: bot | E294: brainstorming | F294: Clarify | G294: 2026-07-02 12:08:14 | H294: 46 | J294: Oh, my apologies! Yes, that's intentional drama — Jurin being the last to have her song makes her turning point feel monumental. What kind of turning point do you imagine for her? One that's deeply personal, or one that changes the fate of the whole pack?
...

Sheet Ideas
A1: uid | B1: session_id | C1: turn_index | D1: timestamp | E1: mode | F1: stage | G1: idea | H1: scamper_technique | I1: flexibility_category | J1: originality_bot | K1: elaboration_bot | L1: bot_reasoning
A2: 0QaQYslhRSXNMdCEaDY35HzA2Xl2 | B2: -OwWRuDalQgU7vQhUj5g | C2: 13 | D2: 2026-07-02 14:18:32 | E2: brainstorming | F2: Clarify | G2: Instead of a forbidden secret, the girl finds a small, otherworldly animal hiding in the abandoned house. | H2: Substitute | I2: Plot | J2: High | K2: Medium | L2: Shifts genre from family drama to sci-fi mystery. The creature's origin and purpose become the central question.
A3: 3w9E9Xr7oehGE2ThwcIxvybuKwE2 | B3: -OwVprk7ZBkimJoUaB_0 | C3: 17 | D3: 2026-07-02 11:27:46 | E3: brainstorming | F3: Clarify | G3: Dog has a strong prey drive, repeatedly sidetracked by chasing cats and birds, causing comedic detours from its main journey | H3: Modify | I3: Character | J3: Medium | K3: Medium | L3: Refines dog's core personality trait into a narrative engine for comedy and obstacles
A4: 3w9E9Xr7oehGE2ThwcIxvybuKwE2 | B4: -OwVprk7ZBkimJoUaB_0 | C4: 19 | D4: 2026-07-02 11:28:20 | E4: brainstorming | F4: Clarify | G4: Eliminate all human viewpoints and dialogue. The story is told entirely through the dog's sensory experiences and canine logic | H4: Eliminate | I4: Mechanic | J4: High | K4: Medium | L4: Pure sensory narration is uncommon and challenging, raising originality

Sheet Bot_Actions
A1: uid | B1: session_id | C1: turn_index | D1: timestamp | E1: mode | F1: stage | G1: action | H1: reasoning | I1: data_json
A2: 0QaQYslhRSXNMdCEaDY35HzA2Xl2 | B2: -OwWRuDalQgU7vQhUj5g | C2: 11 | D2: 2026-07-02 14:17:03 | E2: brainstorming | F2: Clarify | G2: switch_stage | H2: 3 HMWs collected and base concept is clear (girl discovers something forbidden in grandparents' abandoned house). Ready to explore SCAMPER variations. | I2: {"toStage": "Ideate"}
A3: 0QaQYslhRSXNMdCEaDY35HzA2Xl2 | B3: -OwWTu17Sxd9ROSqJ5t4 | C3: 23 | D3: 2026-07-02 14:41:21 | E3: deepthinking | G3: stage_change | H3: User confirmed. Creating Mia as a character (Person node) and recording her goal (find out why grandma has a hidden trapdoor and a dragon). Also creating Grandma as a scientist character. | I3: {"requests": [{"entityType": "node", "entityId": null, "newData": {"label": "Mia", "group": "Person", "attributes": {"goal": "uncover why her grandmother has a hidden trapdoor and a dragon", "knowledge": "knows little about grandma's past besides she was a scientist"}}}, {"entityType": "node", "entityId": null, "newData": {"label": "Grandma", "group": "Person", "attributes": {"profession": "scientist", "known_objects": "hidden trapdoor under bed, dragon living in house"}}}]}
A4: 0QaQYslhRSXNMdCEaDY35HzA2Xl2 | B4: -OwWTu17Sxd9ROSqJ5t4 | C4: 25 | D4: 2026-07-02 14:42:45 | E4: deepthinking | G4: stage_change | H4: User revealed the real grandma is dead and a doppelgänger is impersonating her. Updating 'Grandma' node to reflect doppelgänger status, and confirming Mia's lack of knowledge. | I4: {"requests": [{"entityType": "node", "entityId": null, "newData": {"label": "Grandma", "group": "Person", "attributes": {"profession": "scientist", "status": "deceased", "known_objects": "hidden trapdoor under bed, dragon living in house", "impersonator": "doppelgänger active", "real_grandma_identity": "unknown to Mia at this point"}}}]}
A5: rJTIkz4BJUftHE5g5pil8THAMQL2 | B5: -OwRJZuWNFKZ0OZSAwXR | C5: 17 | D5: 2026-07-01 14:26:35 | E5: brainstorming | F5: Clarify | G5: add_hmw | H5: Framing the user's idea about disbelief and time pressure as a focused creative challenge | I5: {"hmwQuestion": "How might we show the passing of time and mounting pressure while people refuse to believe the character's warning?"}
A6: rJTIkz4BJUftHE5g5pil8THAMQL2 | B6: -OwRJZuWNFKZ0OZSAwXR | C6: 21 | D6: 2026-07-01 14:29:38 | E6: brainstorming | F6: Clarify | G6: add_hmw | H6: Framing the user's question about continuation as a creative challenge about maintaining tension after the reveal | I6: {"hmwQuestion": "How might we sustain narrative drive after the protagonist is proven right about the storm?"}
A7: rJTIkz4BJUftHE5g5pil8THAMQL2 | B7: -OwRJZuWNFKZ0OZSAwXR | C7: 23 | D7: 2026-07-01 14:30:36 | E7: brainstorming | F7: Clarify | G7: add_hmw | H7: The user wants the storm to arrive as a consequence, framing this as a narrative opportunity about delayed action | I7: {"hmwQuestion": "How might we make the storm's arrival feel both inevitable and devastating, rewarding the protagonist's foresight with tragedy?"}
A8: rJTIkz4BJUftHE5g5pil8THAMQL2 | B8: -OwRJZuWNFKZ0OZSAwXR | C8: 23 | D8: 2026-07-01 14:30:36 | E8: brainstorming | F8: Clarify | G8: check_progress | H8: Checking if backend confirms readiness to advance to Ideate stage | I8: {}

Sheet Stories
A1: uid | B1: in_window | C1: n_sessions_in_window | D1: n_stories | E1: n_parts | F1: n_drafts | G1: drafts_per_part | H1: essay_words | I1: first_write | J1: last_write | K1: writing_span_min | L1: has_graph | M1: has_timeline | N1: summary | O1: essay_text
A2: 04E9XYnVi8QD3yHAIXeBHCRp2sN2 | B2: yes | C2: 1 | D2: 0 | E2: 0 | F2: 0 | H2: 0 | L2: yes | M2: yes | N2: He tears his eyes away after a moment, and turns towards the seat Amycus pointed out to him. A black-haired man, leaning against the bar and a blond sit there already, murmuring. Akio hesitates, and then goes over. The occupants of the space pause and look up at him as he approaches, They eye him questioningly, from his paint stained t-shirt to his black cargo pants. “Um,” he offers to the blank stares. “Amy- Amycus told me to stay here?” “…are you even old enough to be in here?” asks the blond, ~~incredulous~~. “…I am!” Akio lies, having learnt from his previous conversation. It doesn’t matter much. The two men clearly don’t believe him and look at each other for a long moment. “Whatever,” the man ~~says~~ tiredly, swiping a hand down his face. “Sit.” He sits. “I’m Akio,” he says again, because he was raised a polite young man. Probably. It’s not coming to him very easily right now. “I’m Luca Brando,” the blond responds, and nudges his silent friend in the side. “This is Leifr Ásjá.” “Akio is an interesting name,” says Leifr, not even wincing as Luca’s elbow digs harshly into his side. “You’re a Futaba?” “Er, yes,” he responds, caught off-guard because these people are from the *most influential Families in the Empire. Why am I here.* “What?” Luca turns seemingly distracted from tormenting his friend’s organs. “The Futaba? You guys are still around?” This, sadly, is a normal reaction to hearing his family name. When it’s recognized at all. “Yeah, um, we. We’re mostly with the Doctors nowadays?” Leifr nods along like randomly encountering a member of a dying clan is normal. “I know a relative of yours. Futaba Masamichi?” Akio pauses. Luca’s elbow starts moving back in for a sneak attack. “Yeah that’s. That’s my brother.” The man nods and shoves his friend away without even looking. Luca sneers at him and steals his drink. Leifr just reaches over the counter, pulls out a bottle *(is that even allowed?)* and a new glass and pours out a generous splash. “Right. Army Doctor right?” Akio nods, ~~distracted by the byplay~~. Luca chugs the drink in one shot and suddenly, Akio’s hands feel very empty. “Are- are you in the army?” *Wait no, stupid question. Which Ásjá isn’t in the army?* “Yeah. Your brother had to fix up most of my team couple of months ago. Never got to thank him.” “I’ll uh. I’ll pass it on.” Leifr nods again and they lapse into an uneasy silence. Akio ~~wonders~~ whether Amycus will be coming back any time soon. He’s vanished, sometime over the course of the conversation, along with Katja and Asahina. Hopefully he’s not going to dump their bodies in a ditch for daring to disturb the sanctity of his adults-only bar. For a time, Leifr and Luca just drink. ~~For all that Leifr seemed calm~~, he’s drinking faster now, his sips turning into swallows, his gaze growing more distant. He finishes the glass and pours out more. Luca notices and frowns. “So,” he turns to Akio. “Doctors huh? You’re going the same way as your big brother?” Akio stiffens. “Er no. Not. I’m not really interested in that.” “Oh?” The blond asks, ~~seemingly intrigued~~. “What do you want to do instead then?” “I uh,” Akio swallows. His nails dig into his palms. “I want to be. An artist. Actually.” At this Leifr looks up too. Luca blinks. “An artist? But you’re from a Family. You’re not joining one of the Factions?” Akio clenched his fists together. “Why- why should I? You said it yourself. No one really knows the Futaba exist anymore anyway.” “I didn’t know you still had active members, dear. I certainly knew you *existed.*” “My brothers are- my brothers are already with the Doctors. This generation of our family has already done its duty to. To the Empire!” Luca leans back a little at Akio’s vehemence. He turns to look at his friend. Leifr has, at this point, almost returned to his glass, but at Luca’s burning stare, clears his throat. “He’s just asking because he’s curious. We’re not judging you. It’s fine if you want to draw.” “Right and it’s not about any kind of duty either,” A voice sounds from behind him. Akio almost gives himself whiplash, spinning in his seat and sees Amycus slipping into his spot behind the bar. “The Empire has never required anything from the Families that it doesn’t require from any of its citizens. It’s the Families themselves that insist on every member joining one of the Twelve Factions.” Leifr nods in agreement. Amycus spots the bottle at his side and snatches it away with a glare. “Don’t make me cut you off too,” he warns, and turns back to Akio as Leifr winces. Luca looks mildly relieved. “I’ve sent your friends home,” the bartender tells him. “They were in no state to hang around.” ~~Akio, well aware of this, tries to look worried. Judging by Amycus’s eyeroll this does not work out for him.~~ “Anyway, Leifr’s right. There’s nothing wrong with being an artist.” the teenager flinches. “There really isn’t,” Luca adds. He smiles ~~in apology~~ when Akio looks back at him. “I forget I can be a little… abrupt at times.” Akio nods and tries to smile back. It doesn’t matter, really, whether he had meant ~~it judgmentally~~ or not. He can’t afford to offend the Brando family. His previous outburst was stupid. “It’s okay. Everyone reacts like that.” Leifr, having finished the last of his glass, ~~looks like he desperately wants to be more drunk but is trying not to show it.~~ “Well… what do you do? Are you a painter? I’ve heard something recently. Some kind of movement about using physical paints and canvas?” “Oh! That’s uh- they’re very cool- I went to an exhibition last week. I didn’t know people even knew how to make the paints for that any more,” Akio ~~enthuses~~. It’s a wildly fascinating movement, going back to the natural paint and canvas supplies to bring one closer to their art. “I’m uh not involved in that but I do- I do want to try it out. I’m. I like to draw. Comics.” “Comics huh? Anything good?” Amycus raises his eyebrows. Akio is about to say no, no he’s just starting out, ~~when another of the bouts of bravery (stupidity) that have been carrying him through the evening takes over~~. “Uh do you- do you want to see? I have some with me. On my pad.” “Oh? Let’s see it then.” Akio prays his blush isn’t visible in the yellow lightening and pulls his pad out of his pocket. The small transparent square is quickly unfolded into Akio’s drawing pad and he swipes. “It’s uh, it’s not done yet but… it’s about the hoverboard ban a few years back. When they said that hoverboards could only be used in… in certain areas.” Naturally, it is at this point that Akio’s motor control fails him. He accidentally enters his booklist, his homework folder and his social media before finally managing to tap his drawing app. Luca snorts, “I remember that. By certain areas you mean the back end of nowhere right? You children were so upset they caused trouble for almost a *year*.” “What?” Leifr interjects. “I don’t know about this. What happened?” “Oh yeah, you were out of the Capital around that time,” Luca nods. “Some long mission or the other. You remember right, Amycus?” “If you’re talking about the racing incident, then I remember alright. Vividly. In fact, it was in the air just a few streets away from here. I saw part of it from my window.” Luca whistles. “I wish I could’ve seen it. I was out too, on a business trip. Only got back in time for the aftermath.” Leifr frowns. “What exactly was *it*?” “It, um, was basically a huge race,” Akio interjects. He’s finally managed to open the comic and pushes the tab along the counter to Amycus. He and Luca lean over it together. “On hoverboards. Hoverboard races were, uh pretty normal back then right, but they’d usually warn the locals and the businesses in that street and get permission and everything. But, uh, that time, a bunch of hoverboarders got really drunk and… they decided to just race. In the street. And, uh, because it was someone’s birthday, they wanted to make it interesting so… they raced around fifty feet in the air. I guess that’s what Mr. Amycus saw.” The red-head snorts. “Just Amycus thanks. And yeah, it was pretty wild. A bunch of kids just wobbling all over the place at breakneck speeds, midair. I thought I was seeing things. Also this is pretty hilarious, good job kid.” Akio’s face erupts in red. “Right! Thank you um. Where was I?” “The drunk kids wanted to race in the air,” Leifr reminds him. The corner of his mouth twitch, and Akio promptly wishes for death for the nth time this evening. “Um, right, yeah. So basically, one of them lost control of their board and fell, and they hit a passerby in the street. Both of them had to be rushed to the hospital. It turned out that the person who got hit was, uh, pretty important, and his family made a huge fuss. So the Architects banned the use of hoverboards anywhere in the Capital except for… well the back end of nowhere, pretty much.” “Yeah and this comic is pretty much what happened after,” says Luca, sounding vastly entertained. “Except for a few details. Have you ever actually met the Warden in person? Because let me tell you, she does not think back on past crimes and laugh, holy shit. I’m not sure she actually laughs at all. This version of her is immensely preferrable. I demand you make it reality this *instant*.” As Akio blue-screens over this mind-boggling statement, Leifr nods in thanks for the explanation, and gently nudges his friend aside to look at the comic. After a beat, a slow grin begins to curve his lips. “Are you serious?” He asks. “I get that this is a parody, but did this really happen?” “Except for a few details like he said,” Amycus chuckles. “I don’t remember anyone ever trying to sneak a hoverboard disguised as a giant rubber duck out of the wardens’ headquarters, for example, but it was only a little less ridiculous than that.” He pauses after a moment- he’s spotted someone a little further down waving their hand - they want a refill. “Sorry, I’ve got to go. Give me a minute.” “How did they stop it?” Leifr asks as he leaves, no longer able to hold back his smile. Akio droops a bit, looking after the red-haired man and Luca snaps his fingers in front of his face- Akio comes back to himself with a jerk. “They couldn’t have repealed it? There haven’t been as many kids flying around for a while, now that I think about it.” “Well they couldn’t,” he explains. “That person… could really have died so… They made designated areas and like aero-paths where it’s okay to fly. Mostly areas with less people. Like… air-traffic, I guess. So things died down after that.” “That old lady must have been shaking with rage,” he comments, leaning back in his seat. “Oh she was,” Luca chuckles. “I heard the wardens were trembling for days. Probably stung her pride, having to let them go, even a little.” “She always did have an inflated ego,” Leifr notes, and Akio is in awe for a moment, remembering that these people have actually *met* legendary figures like the Warden. Probably *still* meet them. Regularly. *I’m not going to get in trouble for this right?* “Ah but kid,” and Akio flinches just a little because the laughter has stopped and Luca’s voice has gone serious and a little quiet. “Are you planning on publishing this? Is the rest of your stuff like this? You’re going to draw attention to yourself, and not the fun kind.” Akio blinks. He *has* considered publishing. It’s his dream. “I… it’s not that bad right? It portrays her in a positive light.” “Does it?” Luca asks. Beside him, Leifr has stopped smiling too. “It’s an incident in which she lost face. Leifr just said it - she has one hell of an ego. She won’t care whether it was in a positive light or not. She’s not going to like it.” “I- I mean… well-” “You should listen to Luca,” Leifr murmurs. “I’m not as good with this kind of political maneuvering- but he’s not been wrong before.” “But… it’s important,” Akio stammers. “It’s… it was a serious incident at the time and… and you’re right the wardens *did* mishandle it, just because the person involved was powerful. The wouldn’t have cared at all if it was just an ordinary citizen. I’m not… I don’t want to hurt anyone’s feelings or- or draw *attention* but isn’t it important? To draw attention to these things so we can do better? It- it *matters.*” Luca and Leifr both look at him for a long moment. Amycus returns, wiping his hands on a washcloth and raises an eyebrow at the ~~suddenly chilled~~ atmosphere. “Sorry, am I interrupting something?” “No,” Leifr responds. “Akio was just saying he wants to publish his comics.” “Oh,” Amycus blinks. His hands pause on the washcloth for a split second. Akio doesn’t notice, but Leifr’s eyes land there and his gaze grows heavier. “Well, yes I suppose if you want to be an artist, publishing is the next step isn’t it.” Luca turns his stare on him and it grows colder, just a little. Amycus returns it steadily. “If you want,” Amycus says, eyes still on Luca. “I can put you in touch with some friends of mine. They run a newspaper. Nothing big, just a few hundred khryos, but there you go.” Akio…doesn’t answer. He has the sudden feeling that he’s lost control of the conversation, that what started with him showing off his art, has become something else. Something bigger. *You’re going to draw attention to yourself*, Luca had said. *And not the fun kind.* Akio rubs his palms on his pants. They feel clammy, and cold in a way they haven’t been since Amycus cut him off and made him sit at the bar. Leifr still isn’t speaking, but he’s turned to Akio and is watching him steadily. Luca’s frowning hard. Akio looks up at the bartender. Amycus is looking at him. He’s put the washcloth down and is leaning against the bar, arms crossed. He’s waiting for Akio’s answer. Akio ~~thinks~~ about his brothers, both Faction members, contributing to the Family. One of them has just been thanked by one of the most powerful, most decorated Families in the Empire. He ~~thinks~~ about his parents, about the disappointment in their eyes when they see him curled up in a corner with his drawing pad at a social event. He ~~thinks~~ about his peers, who aspire to be Vanguards, Wardens, Doctors, anything and everything except a pathetic, forgotten nobody. He ~~thinks~~ about his mother, despairing, asking *Akio, can’t you do something that* matters *for once?* He looks into Amycus’s eyes and knows, in that moment, that if he refuses, Amycus won’t bring it up again. That they can continue the conversation like this never happened. His fists clench, scrunching up the material of his pants. “Yeah,” he says. “That’d be nice.” ----------- He tears his eyes away after a moment, and turns towards the seat Amycus pointed out to him. A black-haired man, leaning against the bar and a blond sit there already, murmuring. Akio hesitates, and then goes over. The occupants of the space pause and look up at him as he approaches, They eye him questioningly, from his paint stained t-shirt to his black cargo pants. “Um,” he offers to the blank stares. “Amy- Amycus told me to stay here?” “…are you even old enough to be in here?” asks the blond, ~~incredulous~~. “…I am!” Akio lies, having learnt from his previous conversation. It doesn’t matter much. The two men clearly don’t believe him and look at each other for a long moment. “Whatever,” the man ~~says~~ tiredly, swiping a hand down his face. “Sit.” He sits. “I’m Akio,” he says again, because he was raised a polite young man. Probably. It’s not coming to him very easily right now. “I’m Luca Brando,” the blond responds, and nudges his silent friend in the side. “This is Leifr Ásjá.” “Akio is an interesting name,” says Leifr, not even wincing as Luca’s elbow digs harshly into his side. “You’re a Futaba?” “Er, yes,” he responds, caught off-guard because these people are from the *most influential Families in the Empire. Why am I here.* “What?” Luca turns seemingly distracted from tormenting his friend’s organs. “The Futaba? You guys are still around?” This, sadly, is a normal reaction to hearing his family name. When it’s recognized at all. “Yeah, um, we. We’re mostly with the Doctors nowadays?” Leifr nods along like randomly encountering a member of a dying clan is normal. “I know a relative of yours. Futaba Masamichi?” Akio pauses. Luca’s elbow starts moving back in for a sneak attack. “Yeah that’s. That’s my brother.” The man nods and shoves his friend away without even looking. Luca sneers at him and steals his drink. Leifr just reaches over the counter, pulls out a bottle *(is that even allowed?)* and a new glass and pours out a generous splash. “Right. Army Doctor right?” Akio nods, ~~distracted by the byplay~~. Luca chugs the drink in one shot and suddenly, Akio’s hands feel very empty. “Are- are you in the army?” *Wait no, stupid question. Which Ásjá isn’t in the army?* “Yeah. Your brother had to fix up most of my team couple of months ago. Never got to thank him.” “I’ll uh. I’ll pass it on.” Leifr nods again and they lapse into an uneasy silence. Akio ~~wonders~~ whether Amycus will be coming back any time soon. He’s vanished, sometime over the course of the conversation, along with Katja and Asahina. Hopefully he’s not going to dump their bodies in a ditch for daring to disturb the sanctity of his adults-only bar. For a time, Leifr and Luca just drink. ~~For all that Leifr seemed calm~~, he’s drinking faster now, his sips turning into swallows, his gaze growing more distant. He finishes the glass and pours out more. Luca notices and frowns. “So,” he turns to Akio. “Doctors huh? You’re going the same way as your big brother?” Akio stiffens. “Er no. Not. I’m not really interested in that.” “Oh?” The blond asks, ~~seemingly intrigued~~. “What do you want to do instead then?” “I uh,” Akio swallows. His nails dig into his palms. “I want to be. An artist. Actually.” At this Leifr looks up too. Luca blinks. “An artist? But you’re from a Family. You’re not joining one of the Factions?” Akio clenched his fists together. “Why- why should I? You said it yourself. No one really knows the Futaba exist anymore anyway.” “I didn’t know you still had active members, dear. I certainly knew you *existed.*” “My brothers are- my brothers are already with the Doctors. This generation of our family has already done its duty to. To the Empire!” Luca leans back a little at Akio’s vehemence. He turns to look at his friend. Leifr has, at this point, almost returned to his glass, but at Luca’s burning stare, clears his throat. “He’s just asking because he’s curious. We’re not judging you. It’s fine if you want to draw.” “Right and it’s not about any kind of duty either,” A voice sounds from behind him. Akio almost gives himself whiplash, spinning in his seat and sees Amycus slipping into his spot behind the bar. “The Empire has never required anything from the Families that it doesn’t require from any of its citizens. It’s the Families themselves that insist on every member joining one of the Twelve Factions.” Leifr nods in agreement. Amycus spots the bottle at his side and snatches it away with a glare. “Don’t make me cut you off too,” he warns, and turns back to Akio as Leifr winces. Luca looks mildly relieved. “I’ve sent your friends home,” the bartender tells him. “They were in no state to hang around.” ~~Akio, well aware of this, tries to look worried. Judging by Amycus’s eyeroll this does not work out for him.~~ “Anyway, Leifr’s right. There’s nothing wrong with being an artist.” the teenager flinches. “There really isn’t,” Luca adds. He smiles ~~in apology~~ when Akio looks back at him. “I forget I can be a little… abrupt at times.” Akio nods and tries to smile back. It doesn’t matter, really, whether he had meant ~~it judgmentally~~ or not. He can’t afford to offend the Brando family. His previous outburst was stupid. “It’s okay. Everyone reacts like that.” Leifr, having finished the last of his glass, ~~looks like he desperately wants to be more drunk but is trying not to show it.~~ “Well… what do you do? Are you a painter? I’ve heard something recently. Some kind of movement about using physical paints and canvas?” “Oh! That’s uh- they’re very cool- I went to an exhibition last week. I didn’t know people even knew how to make the paints for that any more,” Akio ~~enthuses~~. It’s a wildly fascinating movement, going back to the natural paint and canvas supplies to bring one closer to their art. “I’m uh not involved in that but I do- I do want to try it out. I’m. I like to draw. Comics.” “Comics huh? Anything good?” Amycus raises his eyebrows. Akio is about to say no, no he’s just starting out, ~~when another of the bouts of bravery (stupidity) that have been carrying him through the evening takes over~~. “Uh do you- do you want to see? I have some with me. On my pad.” “Oh? Let’s see it then.” Akio prays his blush isn’t visible in the yellow lightening and pulls his pad out of his pocket. The small transparent square is quickly unfolded into Akio’s drawing pad and he swipes. “It’s uh, it’s not done yet but… it’s about the hoverboard ban a few years back. When they said that hoverboards could only be used in… in certain areas.” Naturally, it is at this point that Akio’s motor control fails him. He accidentally enters his booklist, his homework folder and his social media before finally managing to tap his drawing app. Luca snorts, “I remember that. By certain areas you mean the back end of nowhere right? You children were so upset they caused trouble for almost a *year*.” “What?” Leifr interjects. “I don’t know about this. What happened?” “Oh yeah, you were out of the Capital around that time,” Luca nods. “Some long mission or the other. You remember right, Amycus?” “If you’re talking about the racing incident, then I remember alright. Vividly. In fact, it was in the air just a few streets away from here. I saw part of it from my window.” Luca whistles. “I wish I could’ve seen it. I was out too, on a business trip. Only got back in time for the aftermath.” Leifr frowns. “What exactly was *it*?” “It, um, was basically a huge race,” Akio interjects. He’s finally managed to open the comic and pushes the tab along the counter to Amycus. He and Luca lean over it together. “On hoverboards. Hoverboard races were, uh pretty normal back then right, but they’d usually warn the locals and the businesses in that street and get permission and everything. But, uh, that time, a bunch of hoverboarders got really drunk and… they decided to just race. In the street. And, uh, because it was someone’s birthday, they wanted to make it interesting so… they raced around fifty feet in the air. I guess that’s what Mr. Amycus saw.” The red-head snorts. “Just Amycus thanks. And yeah, it was pretty wild. A bunch of kids just wobbling all over the place at breakneck speeds, midair. I thought I was seeing things. Also this is pretty hilarious, good job kid.” Akio’s face erupts in red. “Right! Thank you um. Where was I?” “The drunk kids wanted to race in the air,” Leifr reminds him. The corner of his mouth twitch, and Akio promptly wishes for death for the nth time this evening. “Um, right, yeah. So basically, one of them lost control of their board and fell, and they hit a passerby in the street. Both of them had to be rushed to the hospital. It turned out that the person who got hit was, uh, pretty important, and his family made a huge fuss. So the Architects banned the use of hoverboards anywhere in the Capital except for… well the back end of nowhere, pretty much.” “Yeah and this comic is pretty much what happened after,” says Luca, sounding vastly entertained. “Except for a few details. Have you ever actually met the Warden in person? Because let me tell you, she does not think back on past crimes and laugh, holy shit. I’m not sure she actually laughs at all. This version of her is immensely preferrable. I demand you make it reality this *instant*.” As Akio blue-screens over this mind-boggling statement, Leifr nods in thanks for the explanation, and gently nudges his friend aside to look at the comic. After a beat, a slow grin begins to curve his lips. “Are you serious?” He asks. “I get that this is a parody, but did this really happen?” “Except for a few details like he said,” Amycus chuckles. “I don’t remember anyone ever trying to sneak a hoverboard disguised as a giant rubber duck out of the wardens’ headquarters, for example, but it was only a little less ridiculous than that.” He pauses after a moment- he’s spotted someone a little further down waving their hand - they want a refill. “Sorry, I’ve got to go. Give me a minute.” “How did they stop it?” Leifr asks as he leaves, no longer able to hold back his smile. Akio droops a bit, looking after the red-haired man and Luca snaps his fingers in front of his face- Akio comes back to himself with a jerk. “They couldn’t have repealed it? There haven’t been as many kids flying around for a while, now that I think about it.” “Well they couldn’t,” he explains. “That person… could really have died so… They made designated areas and like aero-paths where it’s okay to fly. Mostly areas with less people. Like… air-traffic, I guess. So things died down after that.” “That old lady must have been shaking with rage,” he comments, leaning back in his seat. “Oh she was,” Luca chuckles. “I heard the wardens were trembling for days. Probably stung her pride, having to let them go, even a little.” “She always did have an inflated ego,” Leifr notes, and Akio is in awe for a moment, remembering that these people have actually *met* legendary figures like the Warden. Probably *still* meet them. Regularly. *I’m not going to get in trouble for this right?* “Ah but kid,” and Akio flinches just a little because the laughter has stopped and Luca’s voice has gone serious and a little quiet. “Are you planning on publishing this? Is the rest of your stuff like this? You’re going to draw attention to yourself, and not the fun kind.” Akio blinks. He *has* considered publishing. It’s his dream. “I… it’s not that bad right? It portrays her in a positive light.” “Does it?” Luca asks. Beside him, Leifr has stopped smiling too. “It’s an incident in which she lost face. Leifr just said it - she has one hell of an ego. She won’t care whether it was in a positive light or not. She’s not going to like it.” “I- I mean… well-” “You should listen to Luca,” Leifr murmurs. “I’m not as good with this kind of political maneuvering- but he’s not been wrong before.” “But… it’s important,” Akio stammers. “It’s… it was a serious incident at the time and… and you’re right the wardens *did* mishandle it, just because the person involved was powerful. The wouldn’t have cared at all if it was just an ordinary citizen. I’m not… I don’t want to hurt anyone’s feelings or- or draw *attention* but isn’t it important? To draw attention to these things so we can do better? It- it *matters.*” Luca and Leifr both look at him for a long moment. Amycus returns, wiping his hands on a washcloth and raises an eyebrow at the ~~suddenly chilled~~ atmosphere. “Sorry, am I interrupting something?” “No,” Leifr responds. “Akio was just saying he wants to publish his comics.” “Oh,” Amycus blinks. His hands pause on the washcloth for a split second. Akio doesn’t notice, but Leifr’s eyes land there and his gaze grows heavier. “Well, yes I suppose if you want to be an artist, publishing is the next step isn’t it.” Luca turns his stare on him and it grows colder, just a little. Amycus returns it steadily. “If you want,” Amycus says, eyes still on Luca. “I can put you in touch with some friends of mine. They run a newspaper. Nothing big, just a few hundred khryos, but there you go.” Akio…doesn’t answer. He has the sudden feeling that he’s lost control of the conversation, that what started with him showing off his art, has become something else. Something bigger. *You’re going to draw attention to yourself*, Luca had said. *And not the fun kind.* Akio rubs his palms on his pants. They feel clammy, and cold in a way they haven’t been since Amycus cut him off and made him sit at the bar. Leifr still isn’t speaking, but he’s turned to Akio and is watching him steadily. Luca’s frowning hard. Akio looks up at the bartender. Amycus is looking at him. He’s put the washcloth down and is leaning against the bar, arms crossed. He’s waiting for Akio’s answer.Map Generator Story Map Timeline World Story Editor Chatbot Profile Email: taranee67589@gmail.com Email Verified: true Story Title: I Dunno Story Summary: He tears his eyes away after a moment, and turns towards the seat Amycus pointed out to him. A black-haired man, leaning against the bar and a blond sit there already, murmuring. Akio hesitates, and then goes over. The occupants of the space pause and look up at him as he approaches, They eye him questioningly, from his paint stained t-shirt to his black cargo pants. “Um,” he offers to the blank stares. “Amy- Amycus told me to stay here?” “…are you even old enough to be in here?” asks the blond, ~~incredulous~~. “…I am!” Akio lies, having learnt from his previous conversation. It doesn’t matter much. The two men clearly don’t believe him and look at each other for a long moment. “Whatever,” the man ~~says~~ tiredly, swiping a hand down his face. “Sit.” He sits. “I’m Akio,” he says again, because he was raised a polite young man. Probably. It’s not coming to him very easily right now. “I’m Luca Brando,” the blond responds, and nudges his silent friend in the side. “This is Leifr Ásjá.” “Akio is an interesting name,” says Leifr, not even wincing as Luca’s elbow digs harshly into his side. “You’re a Futaba?” “Er, yes,” he responds, caught off-guard because these people are from the *most influential Families in the Empire. Why am I here.* “What?” Luca turns seemingly distracted from tormenting his friend’s organs. “The Futaba? You guys are still around?” This, sadly, is a normal reaction to hearing his family name. When it’s recognized at all. “Yeah, um, we. We’re mostly with the Doctors nowadays?” Leifr nods along like randomly encountering a member of a dying clan is normal. “I know a relative of yours. Futaba Masamichi?” Akio pauses. Luca’s elbow starts moving back in for a sneak attack. “Yeah that’s. That’s my brother.” The man nods and shoves his friend away without even looking. Luca sneers at him and steals his drink. Leifr just reaches over the counter, pulls out a bottle *(is that even allowed?)* and a new glass and pours out a generous splash. “Right. Army Doctor right?” Akio nods, ~~distracted by the byplay~~. Luca chugs the drink in one shot and suddenly, Akio’s hands feel very empty. “Are- are you in the army?” *Wait no, stupid question. Which Ásjá isn’t in the army?* “Yeah. Your brother had to fix up most of my team couple of months ago. Never got to thank him.” “I’ll uh. I’ll pass it on.” Leifr nods again and they lapse into an uneasy silence. Akio ~~wonders~~ whether Amycus will be coming back any time soon. He’s vanished, sometime over the course of the conversation, along with Katja and Asahina. Hopefully he’s not going to dump their bodies in a ditch for daring to disturb the sanctity of his adults-only bar. For a time, Leifr and Luca just drink. ~~For all that Leifr seemed calm~~, he’s drinking faster now, his sips turning into swallows, his gaze growing more distant. He finishes the glass and pours out more. Luca notices and frowns. “So,” he turns to Akio. “Doctors huh? You’re going the same way as your big brother?” Akio stiffens. “Er no. Not. I’m not really interested in that.” “Oh?” The blond asks, ~~seemingly intrigued~~. “What do you want to do instead then?” “I uh,” Akio swallows. His nails dig into his palms. “I want to be. An artist. Actually.” At this Leifr looks up too. Luca blinks. “An artist? But you ...[truncated]
A3: 0QaQYslhRSXNMdCEaDY35HzA2Xl2 | B3: yes | C3: 2 | D3: 1 | E3: 1 | F3: 1 | G3: 1 | H3: 125 | I3: 2026-07-02 14:23:53 | J3: 2026-07-02 14:23:53 | L3: no | M3: no | O3: Mia had just arrived at her grandmother's old worn out house. The floorboards creaked loudly under her shoes and the paint on the walls are ripping apart. She was sent here by her parents to find her grandmother's belongings but in the midst of it, she accidentally ends up discovering a small dragon like creature living in her grandmother's bedroom instead. When Mia tried approaching the small dragon, it let out a small shriek before slipping under her grandma's bed. Mia starts questioning about what she had just saw but instead of leaving the house, she moves towards the bed and looks under it, finding a hidden open trapdoor that the small dragon probably used. Mia heads down the trapdoor, finding a secret lab underground.
A4: 3Oh8HB9tTRgaFMqElgVenKJCKCe2 | B4: yes | C4: 1 | D4: 1 | E4: 1 | F4: 1 | G4: 1 | H4: 221 | I4: 2026-07-02 14:45:43 | J4: 2026-07-02 14:45:43 | L4: no | M4: no | O4: you got lost alone during a field trip TENBY - KIM YI DEUN 9N That day, I lost my way. That day, the sky was so blue. And I was alone. The teacher and my friends were nowhere to be seen. All that was left for me was the blue sky. There was no one around, and all I could hear was the sound of my own footsteps. I sat down right there and looked up at the sky. I sat down right there and looked up at the endless blue sky. But I was not at peace. I was fear itself. I sat there without moving. I didn't run. I didn't even breathe. I just sat. Minutes passed. Maybe hours. I don't know. Then their voices — rough, angry, relieved all at once — cut through the silence. "Where were you?!" My friends crashed through the bushes, faces red, sweat dripping. They didn't ask if I was okay. They grabbed my arm and pulled. I stumbled. Almost fell. But they dragged me forward. Another step. Another. And the trip kept going. Like nothing happened. Like I hadn't just sat there becoming fear itself. I was sorry for my friends. Sorry that they had to find me like that. Sorry for the fear in their voices. And trip was so fun.
A5: 3w9E9Xr7oehGE2ThwcIxvybuKwE2 | B5: yes | C5: 1 | D5: 1 | E5: 1 | F5: 1 | G5: 1 | H5: 217 | I5: 2026-07-02 11:31:49 | J5: 2026-07-02 11:31:49 | L5: no | M5: yes | O5: Topic: An Animal gains the ability to speak-narrate its first adventure: Is that chicken...? Grilled chicken on the BBQ? Where is that? Oh! The gate is opened, thank you little one. I'll be off on my merry way! Hopefully David doesn't come back home too soon, I just need to grab a short meal! Hmm, "hey little one, tell David that I'll be back by dawn.". "Okay!", the little child says. Nice! Wait. What? Did it just reply to me? "Hello.. can you hear me?". " "Yes! Dog is speaking!" "I'M SPEAKING?? WAIT WHAT?" "Hi doggy" "This is weird." "Doggy is speaking!" "Uhm.. tell David I'll be back! Byeee!" "Byeeeee!" Okay what just happened? The little child can hear me speak, that's quite unusual. It's okay, I'll deal with that later. Right now, the most important thing is the really good BBQ grilled chicken I'm smelling, where is that? Faster, my legs are moving too slowly. I think it's my golden floppy ears that is holding me back. Now, which direction is it? Seems like it's that direction next to the red-roofed house, but I've never been there before, should I go? The smell is so good, it's too hard to resist. No one will know and I will be able to find my way back right?
A6: 4J7XUz8OJaZ7l0X9s0VrHR2DYNs2 | B6: yes | C6: 1 | D6: 1 | E6: 1 | F6: 1 | G6: 1 | H6: 1730 | I6: 2026-07-01 09:59:08 | J6: 2026-07-01 09:59:08 | L6: yes | M6: no | N6: The plot revolves around the horseman of Death, Death. 2500 years after the apocalypse was cancelled by God, the "ultimate act of mercy" he called it. The story follows Death, obsessed with destiny and purpose, putting the horsemen back together to rebel against God and create their own apocalypse on Earth. First he goes to Pestilence, who works at a company in Heaven. Heaven's companies are split into different sects, like catering to God, catering to humans, trade with other realms, etc. Pestilence works in the top human care company. Pestilence initially refuses to join Death, but after learning that the CEO of the company he works at is secretly Mammon, the fallen angel of Greed, Pestilence agrees on the condition that Death helps him out Mammon. Pestilence was the head of marketing at the company so he had access to it's social media accounts, they snuck into Mammon's office and live streamed him revealing himself, Heaven's paparazzi basically stormed the business and Mammon was sent back to Sheol by Archangel Michael. After that, since they didn't know where Famine was, they went to ask God, but visiting God is a very rare thing so Death called a favour from archangel Raphael and they were able to get in. God tells them only that Famine was in Sheol, Death and Pestilence said that they were doing reunion. God however, already knew their intentions, but did not stop them. Death and Pestilence use a train station called the World Tree Express to get to Sheol. A tv in the station explains that a long time ago, the Afterlife was an uncoordinated mess, and in the Norse world, Yggdrasil, the World Tree, was growing at an alarming rate. Soon even their universe wouldn't be able to contain it, so the Norse powers came together to unroot Yggdrasil and plant it into the bedrock of the very Afterlife itself; Limbo. The afterlives within would then collect on Yggdrasil, becoming it's leaves. The dwarves then, seeing this opportunity, built across the bark of the tree, allowing connection between the realms. Death and Pestilence snuck onto a train bound for Sheol. Sheol was the home of demons and fallen angels, Death and Pestilence arrived in the capital; Pandemonium, which was surprisingly civil. Death and Pestilence searched all throughout the city but couldn't find Famine. Then, a hooded stranger appeared and told the two horsemen that Famine was being held in the castle. Before Death and Pestilence could ask anymore questions, however, the stranger vanished. The castle, Satan's castle, was located in Hades (not the Greek one), Hades was the part of Sheol where sinful souls go to be tormented for eternity. Filled to the brim with pits of molten sulfur, which are filled to the brim with the tortured souls of sinners, feeling the agony of the lava burning their skin off only for it to grow back, all while mentally reliving the worst moments of their lives. Death and Pestilence walk to the castle, and into the throne room, in there was Satan. Well, it was part of him, he was a shadow on the wall, resembling a silhouette. Satan told the two he had no idea where Famine, but they didn't buy it. Once they left, they went into his prison cellar, where they found Famine. They broke Famine out but Satan was one step ahead of them, he released Hellspawn unto the three. Hellspawn, rabid fallen angels who lost their minds after the Fall. They managed to escape but Satan didn't pursue them, even though capturing Famine was the only guarantee he had that the End Times wouldn't occur, he still had other plans in mind. They then returned to Heaven to get War, who had joined Heaven's military after the Apocalypse was cancelled. They visited him and laid out their plan, although War cared deeply about the horsemen, he still didn't want them to do this. So, he let them go and hoped they chose not to. As the 3 were walking out of the building, a purple spark flew past Death. Death looked at where it was going and decided to chase after it. It eventually led him to a library where a Bible was laid out on a lectern. The verse that the spark landed on was Revelation 20:14: "Then death and Hades were thrown into the lake of fire. The lake of fire is the second death." Death was, there are no words to describe his emotions. Betrayal? Hate? Sorrow? He didn't know himself, all he did know was that this would only motivate him even more to fulfill his destiny. Death turned around and instead of the other two horsemen, he saw his scythe. The scythe he had used during the apocalypse. Death grabbed the scythe and for a split second, his eyes sparkled with purple. Death showed the verse to War, and he was rightfully angry. He then decided to join the horsemen. The group then robbed a zoo in Heaven to get their horses back. They got a carriage and started riding, though they couldn't go through the main entrance of World Tree Express with their horses without raising alarms, they could sneak in through the side. But the only way to get to the side was to cross through a certain garden in Heaven. They started riding through. On the way they came across and abandoned house, odd. They entered and suddenly it got foggy and the group was seperated. War found someone crouching in the corner but was attacked. Then, as Death was trying to figure a way out, getting annoyed instead of scared, War showed up, but he was acting strange, different. Then the two found Famine and Pestilence. War, suddenly ran away deeper into the house, the group chased after him, Death getting even more mad. Eventually, War ed them into the basement where they saw a mound of apparitions collected on the ceiling, watching them. War has blue eyes now. Death recognized the apparitions as poltergeists, but a special kind of poltergeist, these ghosts were never able to move on, and through immense willpower, they were able to force themselves into the afterlife. But they had to bring the place they were tied to with them. Now the only way they can leave is for them to enter a body and walk out, so sometimes multiple poltergeists form alliances and possess and individual host together, which was what happened to War. War explained that there was no escape and they should just give up. But then, Death burst into purple flames and raised his scythe, commanding the spirits out of the Death and the ceiling, using the power he was able to force the spirits into Hades. Death, exhausted from the display, passed out. He then woke up in the carriage, War also recovering. The next day, we focus on Sheol. And into the life of someone new, the daughter of Satan; Michelle. Michelle lived a relatively normal life, except for the fact that no one talked to her except for one friend because her father was literally Satan, even demons and fallen angels fear him. Michelle even had a crush, but he wasn't the average jock popular boy, he actually kept to himself quite often, his interests being accounting and drawing. He was pretty mundane and that's why Michelle liked him. Michelle and her best friend spend the next few days getting everything she needs for prom, and the courage to ask out her crush. All while hiding it from her father, who would never let her do anything like this. Eventually she gets everything and asks him out and he says yes. She has an amazing time and people even started talking to her more. But when she came back home, she was called into her father's throne room, there was the head of her date on a pike, his blood pooling down the wood. Satan said that if she ever went behind her back again, he would personally see to it that she regret that forever. Michelle runs to her room and finds a small device. She takes it an d presses it and puts it on the floor, it then shows a hologram of archangel Michael, Michelle says she ready to talk. Focus back on the horsemen, its night in the garden and they're resting. Death is sitting outside, staring at his scythe, when a bright light comes from the forest, and steps through. A glowing woman. Death regards her as Life. Life and Death catch up a bit, Life always did prefer to talk to him over the Grim Reaper. Life says she's worried about Death but Death dismisses her. Life tells Death to let go of the scythe but he refuses. After a rise in more tension, they fight. It ends in a stalemate, but Life walks away, but not before telling Death that he's going down a dark path. Michelle tells Michael about her father's plans; plans to invade Heaven. But before he finish, guard barge into her room and drag her out, Michael saying her sacrifice was for the greater good. The guards bring her to Satan who banishes her from Sheol. She gets on a World Tree Train bound for Asgard. Satan watches, a flicker of blue sparkles in his eyes before he brushes himself off and it fades away. Death and the horsemen make it to the station and they board a train. They make it to Asgard, where they intended to discuss their plans further because they couldn't do that in Heaven. But they are stopped by Heimdall, they are almost sent back to Heaven when they are saved by Michell. Michelle tellls them that they owe her and they need to help her stop her father, they reluctantly agree. Satan sends scientists to earth to get the blood of Jesus, which they use to restore Satan to his body. Satan gathers his army outside his castle but then the horsemen show up. Satan turns into a dragon and fights them. Death bursts into purple flames and tries to attack Satan but gets knocked unconcsious. Death meets Life in his mind and together Death learns to overcome his obsession with destiny. They beat Satan, and then heaven's army arrives and defeats Satan's army and Satan is banished to Limbo. ----------- The plot revolves around the horseman of Death, Death. 2500 years after the apocalypse was cancelled by God, the "ultimate act of mercy" he called it. The story follows Death, obsessed with destiny and purpose, putting the horsemen back together to rebel against God and create their own apocalypse on Earth. First he goes to Pestilence, who works at a company in Heaven. Heaven's companies are split into different sects, like catering to God, catering to humans, trade with other realms, etc. Pestilence works in the top human care company. Pestilence initially refuses to join Death, but after learning that the CEO of the company he works at is secretly Mammon, the fallen angel of Greed, Pestilence agrees on the condition that Death helps him out Mammon. Pestilence was the head of marketing at the company so he had access to it's social media accounts, they snuck into Mammon's office and live streamed him revealing himself, Heaven's paparazzi basically stormed the business and Mammon was sent back to Sheol by Archangel Michael. After that, since they didn't know where Famine was, they went to ask God, but visiting God is a very rare thing so Death called a favour from archangel Raphael and they were able to get in. God tells them only that Famine was in Sheol, Death and Pestilence said that they were doing reunion. God however, already knew their intentions, but did not stop them. Death and Pestilence use a train station called the World Tree Express to get to Sheol. A tv in the station explains that a long time ago, the Afterlife was an uncoordinated mess, and in the Norse world, Yggdrasil, the World Tree, was growing at an alarming rate. Soon even their universe wouldn't be able to contain it, so the Norse powers came together to unroot Yggdrasil and plant it into the bedrock of the very Afterlife itself; Limbo. The afterlives within would then collect on Yggdrasil, becoming it's leaves. The dwarves then, seeing this opportunity, built across the bark of the tree, allowing connection between the realms. Death and Pestilence snuck onto a train bound for Sheol. Sheol was the home of demons and fallen angels, Death and Pestilence arrived in the capital; Pandemonium, which was surprisingly civil. Death and Pestilence searched all throughout the city but couldn't find Famine. Then, a hooded stranger appeared and told the two horsemen that Famine was being held in the castle. Before Death and Pestilence could ask anymore questions, however, the stranger vanished. The castle, Satan's castle, was located in Hades (not the Greek one), Hades was the part of Sheol where sinful souls go to be tormented for eternity. Filled to the brim with pits of molten sulfur, which are filled to the brim with the tortured souls of sinners, feeling the agony of the lava burning their skin off only for it to grow back, all while mentally reliving the worst moments of their lives. Death and Pestilence walk to the castle, and into the throne room, in there was Satan. Well, it was part of him, he was a shadow on the wall, resembling a silhouette. Satan told the two he had no idea where Famine, but they didn't buy it. Once they left, they went into his prison cellar, where they found Famine. They broke Famine out but Satan was one step ahead of them, he released Hellspawn unto the three. Hellspawn, rabid fallen angels who lost their minds after the Fall. They managed to escape but Satan didn't pursue them, even though capturing Famine was the only guarantee he had that the End Times wouldn't occur, he still had other plans in mind. They then returned to Heaven to get War, who had joined Heaven's military after the Apocalypse was cancelled. They visited him and laid out their plan, although War cared deeply about the horsemen, he still didn't want them to do this. So, he let them go and hoped they chose not to. As the 3 were walking out of the building, a purple spark flew past Death. Death looked at where it was going and decided to chase after it. It eventually led him to a library where a Bible was laid out on a lectern. The verse that the spark landed on was Revelation 20:14: "Then death and Hades were thrown into the lake of fire. The lake of fire is the second death." Death was, there are no words to describe his emotions. Betrayal? Hate? Sorrow? He didn't know himself, all he did know was that this would only motivate him even more to fulfill his destiny. Death turned around and instead of the other two horsemen, he saw his scythe. The scythe he had used during the apocalypse. Death grabbed the scythe and for a split second, his eyes sparkled with purple. Death showed the verse to War, and he was rightfully angry. He then decided to join the horsemen. The group then robbed a zoo in Heaven to get their horses back. They got a carriage and started riding, though they couldn't go through the main entrance of World Tree Express with their horses without raising alarms, they could sneak in through the side. But the only way to get to the side was to cross through a certain garden in Heaven. They started riding through. On the way they came across and abandoned house, odd. They entered and suddenly it got foggy and the group was seperated. War found someone crouching in the corner but was attacked. Then, as Death was trying to figure a way out, getting annoyed instead of scared, War showed up, but he was acting strange, different. Then the two found Famine and Pestilence. War, suddenly ran away deeper into the house, the group chased after him, Death getting even more mad. Eventually, War ed them into the basement where they saw a mound of apparitions collected on the ceiling, watching them. War has blue eyes now. Death recognized the apparitions as poltergeists, but a special kind of poltergeist, these ghosts were never able to move on, and through immense willpower, they were able to force themselves into the afterlife. But they had to bring the place they were tied to with them. Now the only way they can leave is for them to enter a body and walk out, so sometimes multiple poltergeists form alliances and possess and individual host together, which was what happened to War. War explained that there was no escape and they should just give up. But then, Death burst into purple flames and raised his scythe, commanding the spirits out of the Death and the ceiling, using the power he was able to force the spirits into Hades. Death, exhausted from the display, passed out. He then woke up in the carriage, War also recovering. The next day, we focus on Sheol. And into the life of someone new, the daughter of Satan; Michelle. Michelle lived a relatively normal life, except for the fact that no one talked to her except for one friend because her father was literally Satan, even demons and fallen angels fear him. Michelle even had a crush, but he wasn't the average jock popular boy, he actually kept to himself quite often, his interests being accounting and drawing. He was pretty mundane and that's why Michelle liked him. Michelle and her best friend spend the next few days getting everything she needs for prom, and the courage to ask out her crush. All while hiding it from her father, who would never let her do anything like this. Eventually she gets everything and asks him out and he says yes. She has an amazing time and people even started talking to her more. But when she came back home, she was called into her father's throne room, there was the head of her date on a pike, his blood pooling down the wood. Satan said that if she ever went behind her back again, he would personally see to it that she regret that forever. Michelle runs to her room and finds a small device. She takes it an d presses it and puts it on the floor, it then shows a hologram of archangel Michael, Michelle says she ready to talk. Focus back on the horsemen, its night in the garden and they're resting. Death is sitting outside, staring at his scythe, when a bright light comes from the forest, and steps through. A glowing woman. Death regards her as Life. Life and Death catch up a bit, Life always did prefer to talk to him over the Grim Reaper. Life says she's worried about Death but Death dismisses her. Life tells Death to let go of the scythe but he refuses. After a rise in more tension, they fight. It ends in a stalemate, but Life walks away, but not before telling Death that he's going down a dark path. Michelle tells Michael about her father's plans; plans to invade Heaven. But before he finish, guard barge into her room and drag her out, Michael saying her sacrifice was for the greater good. The guards bring her to Satan who banishes her from Sheol. She gets on a World Tree Train bound for Asgard. Satan watches, a flicker of blue sparkles in his eyes before he brushes himself off and it fades away. Death and the horsemen make it to the station and they board a train. They make it to Asgard, where they intended to discuss their plans further because they couldn't do that in Heaven. But they are stopped by Heimdall, they are almost sent back to Heaven when they are saved by Michell. Michelle tellls them that they owe her and they need to help her stop her father, they reluctantly agree. Satan sends scientists to earth to get the blood of Jesus, which they use to restore Satan to his body. Satan gathers his army outside his castle but then the horsemen show up. Satan turns into a dragon and fights them. Death bursts into purple flames and tries to attack Satan but gets knocked unconcsious. Death meets Life in his mind and together Death learns to overcome his obsession with destiny. They beat Satan, and then heaven's army arrives and defeats Satan's army and Satan is banished to Limbo. | O6: The plot revolves around the horseman of Death, Death. 2500 years after the apocalypse was cancelled by God, the "ultimate act of mercy" he called it. The story follows Death, obsessed with destiny and purpose, putting the horsemen back together to rebel against God and create their own apocalypse on Earth. First he goes to Pestilence, who works at a company in Heaven. Heaven's companies are split into different sects, like catering to God, catering to humans, trade with other realms, etc. Pestilence works in the top human care company. Pestilence initially refuses to join Death, but after learning that the CEO of the company he works at is secretly Mammon, the fallen angel of Greed, Pestilence agrees on the condition that Death helps him out Mammon. Pestilence was the head of marketing at the company so he had access to it's social media accounts, they snuck into Mammon's office and live streamed him revealing himself, Heaven's paparazzi basically stormed the business and Mammon was sent back to Sheol by Archangel Michael. After that, since they didn't know where Famine was, they went to ask God, but visiting God is a very rare thing so Death called a favour from archangel Raphael and they were able to get in. God tells them only that Famine was in Sheol, Death and Pestilence said that they were doing reunion. God however, already knew their intentions, but did not stop them. Death and Pestilence use a train station called the World Tree Express to get to Sheol. A tv in the station explains that a long time ago, the Afterlife was an uncoordinated mess, and in the Norse world, Yggdrasil, the World Tree, was growing at an alarming rate. Soon even their universe wouldn't be able to contain it, so the Norse powers came together to unroot Yggdrasil and plant it into the bedrock of the very Afterlife itself; Limbo. The afterlives within would then collect on Yggdrasil, becoming it's leaves. The dwarves then, seeing this opportunity, built across the bark of the tree, allowing connection between the realms. Death and Pestilence snuck onto a train bound for Sheol. Sheol was the home of demons and fallen angels, Death and Pestilence arrived in the capital; Pandemonium, which was surprisingly civil. Death and Pestilence searched all throughout the city but couldn't find Famine. Then, a hooded stranger appeared and told the two horsemen that Famine was being held in the castle. Before Death and Pestilence could ask anymore questions, however, the stranger vanished. The castle, Satan's castle, was located in Hades (not the Greek one), Hades was the part of Sheol where sinful souls go to be tormented for eternity. Filled to the brim with pits of molten sulfur, which are filled to the brim with the tortured souls of sinners, feeling the agony of the lava burning their skin off only for it to grow back, all while mentally reliving the worst moments of their lives. Death and Pestilence walk to the castle, and into the throne room, in there was Satan. Well, it was part of him, he was a shadow on the wall, resembling a silhouette. Satan told the two he had no idea where Famine, but they didn't buy it. Once they left, they went into his prison cellar, where they found Famine. They broke Famine out but Satan was one step ahead of them, he released Hellspawn unto the three. Hellspawn, rabid fallen angels who lost their minds after the Fall. They managed to escape but Satan didn't pursue them, even though capturing Famine was the only guarantee he had that the End Times wouldn't occur, he still had other plans in mind. They then returned to Heaven to get War, who had joined Heaven's military after the Apocalypse was cancelled. They visited him and laid out their plan, although War cared deeply about the horsemen, he still didn't want them to do this. So, he let them go and hoped they chose not to. As the 3 were walking out of the building, a purple spark flew past Death. Death looked at where it was going and decided to chase after it. It eventually led him to a library where a Bible was laid out on a lectern. The verse that the spark landed on was Revelation 20:14: "Then death and Hades were thrown into the lake of fire. The lake of fire is the second death." Death was, there are no words to describe his emotions. Betrayal? Hate? Sorrow? He didn't know himself, all he did know was that this would only motivate him even more to fulfill his destiny. Death turned around and instead of the other two horsemen, he saw his scythe. The scythe he had used during the apocalypse. Death grabbed the scythe and for a split second, his eyes sparkled with purple. Death showed the verse to War, and he was rightfully angry. He then decided to join the horsemen. The group then robbed a zoo in Heaven to get their horses back. They got a carriage and started riding, though they couldn't go through the main entrance of World Tree Express with their horses without raising alarms, they could sneak in through the side. But the only way to get to the side was to cross through a certain garden in Heaven. They started riding through. On the way they came across and abandoned house, odd. They entered and suddenly it got foggy and the group was seperated. War found someone crouching in the corner but was attacked. Then, as Death was trying to figure a way out, getting annoyed instead of scared, War showed up, but he was acting strange, different. Then the two found Famine and Pestilence. War, suddenly ran away deeper into the house, the group chased after him, Death getting even more mad. Eventually, War ed them into the basement where they saw a mound of apparitions collected on the ceiling, watching them. War has blue eyes now. Death recognized the apparitions as poltergeists, but a special kind of poltergeist, these ghosts were never able to move on, and through immense willpower, they were able to force themselves into the afterlife. But they had to bring the place they were tied to with them. Now the only way they can leave is for them to enter a body and walk out, so sometimes multiple poltergeists form alliances and possess and individual host together, which was what happened to War. War explained that there was no escape and they should just give up. But then, Death burst into purple flames and raised his scythe, commanding the spirits out of the Death and the ceiling, using the power he was able to force the spirits into Hades. Death, exhausted from the display, passed out. He then woke up in the carriage, War also recovering. The next day, we focus on Sheol. And into the life of someone new, the daughter of Satan; Michelle. Michelle lived a relatively normal life, except for the fact that no one talked to her except for one friend because her father was literally Satan, even demons and fallen angels fear him. Michelle even had a crush, but he wasn't the average jock popular boy, he actually kept to himself quite often, his interests being accounting and drawing. He was pretty mundane and that's why Michelle liked him. Michelle and her best friend spend the next few days getting everything she needs for prom, and the courage to ask out her crush. All while hiding it from her father, who would never let her do anything like this. Eventually she gets everything and asks him out and he says yes. She has an amazing time and people even started talking to her more. But when she came back home, she was called into her father's throne room, there was the head of her date on a pike, his blood pooling down the wood. Satan said that if she ever went behind her back again, he would personally see to it that she regret that forever. Michelle runs to her room and finds a small device. She takes it an d presses it and puts it on the floor, it then shows a hologram of archangel Michael, Michelle says she ready to talk. Focus back on the horsemen, its night in the garden and they're resting. Death is sitting outside, staring at his scythe, when a bright light comes from the forest, and steps through. A glowing woman. Death regards her as Life. Life and Death catch up a bit, Life always did prefer to talk to him over the Grim Reaper. Life says she's worried about Death but Death dismisses her. Life tells Death to let go of the scythe but he refuses. After a rise in more tension, they fight. It ends in a stalemate, but Life walks away, but not before telling Death that he's going down a dark path. Michelle tells Michael about her father's plans; plans to invade Heaven. But before he finish, guard barge into her room and drag her out, Michael saying her sacrifice was for the greater good. The guards bring her to Satan who banishes her from Sheol. She gets on a World Tree Train bound for Asgard. Satan watches, a flicker of blue sparkles in his eyes before he brushes himself off and it fades away. Death and the horsemen make it to the station and they board a train. They make it to Asgard, where they intended to discuss their plans further because they couldn't do that in Heaven. But they are stopped by Heimdall, they are almost sent back to Heaven when they are saved by Michell. Michelle tellls them that they owe her and they need to help her stop her father, they reluctantly agree. Satan sends scientists to earth to get the blood of Jesus, which they use to restore Satan to his body. Satan gathers his army outside his castle but then the horsemen show up. Satan turns into a dragon and fights them. Death bursts into purple flames and tries to attack Satan but gets knocked unconcsious. Death meets Life in his mind and together Death learns to overcome his obsession with destiny. They beat Satan, and then heaven's army arrives and defeats Satan's army and Satan is banished to Limbo.
A7: 5iy5k09B1rhCSEHuf17zeB2lmXL2 | B7: yes | C7: 1 | D7: 1 | E7: 1 | F7: 1 | G7: 1 | H7: 622 | I7: 2026-07-02 14:24:17 | J7: 2026-07-02 14:24:17 | L7: no | M7: no | N7: yo | O7: The missed call from 'Mom' glowed on his lock screen for twelve seconds before he swiped it away and stepped into his car. He finally pulled into the parking lot with only 10 minutes until his flight leaves however a grimy hand clamped onto his sleeve just before the revolving doors, and he turned to find a homeless man's bloodshot eyes fixed on his own. 'That plane's carrying ghosts,' the homeless man rasped, but he yanked his arm free and pushed through the door, deaf to the warning buried beneath the terminal's roar. The homeless man lunged, grabbing his coat. He shoved hard, stumbled, then sprinted. At the gate, the desk agent was already locking the door. "Sorry, sir, doors are closed." Planes always leave without you. This one felt different. He kicks the door open, tossing his keys onto the counter. He was pissed, he was so close but the homeless man didn't know how to mind his own business. Hours pass in a haze of takeout and TV. Then the news anchors eyes meet his: "breaking updates on flight 237—no survivors." The remote slips from his hand, his eyes go wide, that was his flight. He stared at the screen. The homeless man's words echoed: "That plane's carrying ghosts." It wasn't madness. It was a warning. He grabbed his coat, heart pounding. He had to find him. He gets into his car speeding along the highway the same way he did this morning, but this time's different. He wasn't rushing to catch a flight, he was rushing to thank a man he ignored. He reached the same parking lot he encountered the homeless man, but he wasn't there. He searched every street corner, every alley. Nothing. The man had vanished like smoke. Standing in the rain, he finally understood—some warnings arrive once, carried by voices we're too busy to hear. He vowed never to ignore another. He steps in his car, still soaking wet and drives away, on the way home he saw a dark silhouette in the rain. He got out to check, it was someone on the edge of a bridge. He approached slowly, the way you'd approach a wounded animal. "I don't know what you're carrying," he said, "but I've learned you can't outrun it." The suicidal man's voice cracked: "I lost everything. Job. Wife. Reason to get up." He stared at the water. "Why should I stay?" The man stepped closer. "Because tomorrow you might save someone. I almost got on a plane that crashed. I'm here because someone tried to warn me." He just listened. After an hour, the man stepped back from the edge. He walked home with a strange lightness in his chest. The pride felt good, but it faded fast—replaced by a quieter ache. He pulled out his phone, staring at his mom's contact. Three years of silence. He hit call before he could talk himself out of it. "Hello?" Her voice was smaller than he remembered. He opened his mouth, but the words tangled. "Mom... I'm sorry. I'm so sorry." Silence stretched. Then, a shaky breath. "I've been waiting three years to hear you say that. Come home, sweetheart." He hung up, tears streaming, feeling lighter than he had in years. As soon as the words came out he drove to her house, the same place he hasn't seen in years. He stood outside her door, hand hovering over the handle. When she opened it, her hair was grayer, her eyes softer. She didn't say a word—just pulled him into an embrace that smelled like lavender and forgiveness. "I made your favorite," she whispered. "Chicken soup." For the first time in years, he felt like he was finally where he belonged.
A8: 6FGzR0FFoIMiQ3y2otIsOqIyrMh2 | B8: yes | C8: 1 | D8: 1 | E8: 1 | F8: 1 | G8: 1 | H8: 330 | I8: 2026-07-02 09:46:14 | J8: 2026-07-02 09:46:14 | L8: no | M8: yes | O8: Last Monday, I had an unforgettable experience when I missed the school bus and arrived late for class. It was a lesson that I will always remember. That morning, I woke up much later than usual because I forgot to set my alarm clock. When I looked at the time, I jumped out of bed in panic. I quickly brushed my teeth, took a shower, put on my school uniform, and packed my school bag. I skipped breakfast because I did not want to waste any more time. I ran as fast as I could to the bus stop. Unfortunately, just as I reached it, I saw the school bus driving away. I shouted and waved my hands, hoping the driver would stop, but it was too late. I felt upset and worried because I knew I would be late for school. I immediately called my father for help. Luckily, he was still at home and agreed to drive me to school. However, the roads were crowded with morning traffic, and we had to stop at several red traffic lights. I kept looking at my watch and became more nervous with every passing minute. When we finally arrived at school, the first lesson had already begun. I hurried to my classroom, took a deep breath, and knocked gently on the door. My teacher looked at me and asked why I was late. I politely explained that I had missed the school bus after waking up late. My teacher accepted my explanation but reminded me that punctuality is very important. I apologized to my teacher and quietly took my seat. Although I felt embarrassed, I paid close attention to the lesson and borrowed my friend's notes to catch up. That day taught me a valuable lesson about responsibility and good time management. Since then, I have made it a habit to prepare my school bag the night before and set two alarm clocks. I have never missed the school bus again.
A9: 6xMddtGgmcN42mZbnypoitgkFpa2 | B9: yes | C9: 1 | D9: 1 | E9: 1 | F9: 1 | G9: 1 | H9: 915 | I9: 2026-07-02 14:14:13 | J9: 2026-07-02 14:14:13 | L9: no | M9: no | O9: > A man's loss of identity There was once a young charming boy named Octavius, here he's sixteen. His family isn't the best. Octavius like a ghost in his own house, has a younger sister, Ganet. She was pretty on the outside but rotten in the heart, some might say she's evil. Though she's barely reached the age of seven. She's already got their parents wrapped around her finger. Controlling them like a bunch of useless puppets she can just throw away if redundant. On one pouring day where the rain lashes out and the thunder roars, Octavius lays in his room listening to the loudest song possible. To silence the thoughts of the rest of the "family". Yesterday was just like any normal day for his family, but for him it was his birthday. April the 1st. Exactly April fools, the day everyone tormented him about. He was cursed to his fate. Octavius hated it. He despised his birthday as much as he does for his parents. He got many sorts of gifts. First, a scrawny teddy bears his mom gave him after Ganet apparently hated. And the second and last, purple flowers on his skin that were disgusting yet beautiful. A gift from his "beloved" birth father. Accompanied by his consistent yells and scoldings when Octavius didn't want to give back the bear to his sister Ganet even though everyone in the house heard her say that she hated it. If she wanted it, she must have it. At school, it wasn't great either. It definitely was not fair, his uniform was all crumpled, torn and even stained. While Ganet's clean, ironed and bright in color. He had somewhat friends. Who he knew himself, they would never ever choose him if there was a group project. Octavius honestly was pretty aloof about it. It never really mattered to him anymore. The constant line "Grow up and accept it" got to him. In class, he had bullies obviously. They would always make fun of his clothes, shoes, and his birthday. "April fools!" always lingered on his mind, where his classmates always yell at the top their lungs whenever they see Octavius enter the classroom. Nighttime, at home. His room, his privacy. Lies. There was absolutely no privacy in the house, anyone could come in and mess with whatever they want, and Octavius could never do anything about. It almost felt it if like the wings of a dove were plucked from it while keeping it in a cage, entrapping it. In some nights, he heads to the bathroom looks in the mirror and think "Is this who i am?", he touches the mirror and let the coldness of the mirror seep in through his skin. Some nights, he would stay up all night putting on his headphones decorating his room, though the pain of his heart's accord was draining him, that never stopped him to create creative things he showed hope in life. Drawing posters, one thig he was actually decent at was painting. It kept him alive. His room walls filled with art. Art from his own mind or art inspired by the pain he's gone through. He actually loved it. He cut his own hair into art. Styling it like back in another era. He had cool bracelets, belts, shoes, all handmade. He hated dull things, like black coffee. It reminded him of the emptiness of his father. Though a boy, Octavius was also trained to feel no emotion following the stereotype that men aren't allowed to cry or feel anything, But soon, it all came to an end. After college there was no room for light, it's the time of a life where they expect you to get a job, earn your own money, start a family. And in other minds, give the money to your parents and sister. Work? Oh man, did Octavius work. He worked sixteen hours a day, chugging down seven cups of the coffee he absolutely hated. His room was dark and gloomy; there was no decorations. Not like Octavius would observe it anyway, at his age? twenty nine. He came home and already passed out on his bed. Set three alarms and repeat. There were some sleepless nights, where he had to take insomnia pills. The dark bags under his eyes were hanging on for dear life. He felt like his funeral could come soon anyday, but he worked anyway. His parents? always said "Live under my house? Pay the rent, and give your poor sister money". Poor sister he thought. She's twenty and can perfectly find a job for herself. So, he did what he had to do, he moved into an already dying apartment. His closet? No cool clothes or handmade things. Too old for that. He had a plain white long sleeve and black pants. An everyday outfit he'll wear even to his own funeral. He looked as pale as a dead man anyway. On one certain night, he heads to his tiny apartment bathroom to brush his coffee-stained teeth when he saw the reflection of himself. Now? now he saw his sixteen-year-old self still wearing the belt he made a long time ago, young and full of ideas very unlike him right now. Feeling a sense of deja vu in his heart, such a familiar feeling he can't quite remember and name it out, he asked himself, "Is this who I am?". And followed by "Is this who I want to be?".
A10: 7b2GdTbVRfUHAWpBDj4ZNTuE2UH2 | B10: yes | C10: 1 | D10: 1 | E10: 1 | F10: 1 | G10: 1 | H10: 463 | I10: 2026-07-01 11:50:45 | J10: 2026-07-01 11:50:45 | L10: no | M10: no | O10: The first tremor came without warning, but the sky had been lying about the rain for days. We thought a bad weather just occurred, but it was a Cataclysmic storm about to come to our path, not only did a storm appear but an hurricane, a thunderous roar gave us goosebumps. From the outside view, i see people running for their lives but caught up to them and it destroyed cities laying them into dust, it was too late to evacuate but we can find shelter to avoid them. The way we can survive a hurricane is to go as down as possible. All of a sudden, it stopped and the storm didn't come back that night, but the silence it left behind was worse. Huddled in the cracked shell of a library, the survivors listened for wind, for thunder, for anything. But there were only the drip of water and the slow groan of settling rubble. No one said it aloud, but they all knew: the stillness felt like waiting. The storm returned at dawn, a wall of black wind howling through the shattered streets. The survivors pressed themselves into the library's basement, clutching pipes and each other as the building groaned above them. Glass shattered. Concrete cracked. But the foundation held. When the wind finally passed and the dust settled, they emerged bloodied, deafened, but alive into a world that still demanded they fight for it. While the storm raged above, one of them noticed something the wind never touched the copper pipes running through the basement. They traced the pattern, realizing the storm swerved around metal. Before the next surge hit, they pieced it together: the storm hated electricity. They scrambled to reroute exposed wires, weaving a cage of current around their shelter. The storm retreated, screaming, and they finally understood what could stop it just as the horizon darkened, signaling its departure for the next town. They didn't waste time celebrating. The storm was already crawling toward the next valley, and somewhere out there, another town had no idea what was coming. Someone found an old ham radio in the rubble. They patched it together, and through the static, a voice answered. "We see it on radar," the voice said. "But we don't know how to stop it." The survivors looked at each other, knowing exactly what to say next. The last storm never reached the next town. They called ahead—explained the copper, the electricity, the cage of wire. Every town from there learned, adapted, passed it on. Years later, storms still came, but they were met with humming metal towers and defiant lights. And in the rebuilt library, a plaque read: We survived not because the storm spared us, but because we refused to let it win alone
A11: 86IempJqjAe16ZnVEcfplb36dQK2 | B11: yes | C11: 1 | D11: 1 | E11: 1 | F11: 1 | G11: 1 | H11: 259 | I11: 2026-07-02 11:26:26 | J11: 2026-07-02 11:26:26 | L11: yes | M11: no | N11: Simon Jakops kidnaps 7 wolves from Planet Earth and turns them into aliens with an intergalactical tactical flow, going ballistic and out of this world. | O11: Simon Jakops kidnaps 7 wolves from Planet Earth and turns them into aliens with an intergalactical tactical flow, going ballistic and out of this world. The wolves were meant to explore the cosmos - to bring happiness to inhabitants of the universe through the power of music. Simon will train the alien-wolf hybrids to sing, rap and dance well, as well as be able to fly through the universe in order to spread music to others. The cosmos is a very divided place, with wars and catastrophes happening on the regular. No planet wants to interact with another - Simon Jakops wants to change that. The group of alien-wolf hybrids will be referred to under one name: XG. "Shooting Star" is the debut song of XG; it makes it clear that XG is aiming to explore the cosmos at overwhelming speeds, like shooting stars, and unite the cosmos. "X-Gene" is a presentation of their X(TRAORDINARY) Genetics. With aliens and wolves becoming one, they aim to show the universe the beauty of unity and oneness. "Puppet Show", "Gala", "No Good", "4 Seasons", "Rock the Boat", "O.R.B (Obviously Reads Bro)" are all part of a massive response to the universe tearing them down and insisting they cannot unite the cosmos. There are 6 songs here, and each song highlights the unique traits of one member. Yet there's a seventh member who doesn't have a song yet: the leader of XG, Jurin. Her song will be the most important and will define a major turning point in the plot of the story.
A12: 8f8UOMJlUgXC014a2m6fBFiuUji1 | B12: yes | C12: 1 | D12: 1 | E12: 1 | F12: 1 | G12: 1 | H12: 448 | I12: 2026-07-01 09:07:20 | J12: 2026-07-01 09:07:20 | L12: no | M12: no | O12: There was a Man who held no grudges against the black people but yet still hated the black people. He had cause many problems with the people throughout his life, not thinking of what consequences this will bring onto himself. Soon he was about to beat up a black person Infront of his own kids and wife, than he woke up from his dreams and hated the fact that he couldn't continue that feeling. He than continues on with his daily life thinking about how had once missed an opportunity to beat up a person. Soon he had met up with his friends but he notice something weird about his friends. They no longer give of a feeling of comfort around him, he feels as he is being miss treated by his friends who had been with him since the start of his hatred of black people. His friends whispered each others " Who is this person acting all friendly with them" than one person chose to step up and ask "who are you trying to be all friendly with us". He tries to explain himself that he has been friends with them since the start of high school. But they had the wrong ideas, they had thought this person was trying to make a fool of them. They threatens to call their old ruthless buddies who were known to be avoided by all black people since he was know for his hatred for them. So he chose to walk away from them in deep thoughts thinking about what had make them ruthless to him. He continues with his life not thinking much about the situation with his friends, assuming if they just were a bit disheartened about something. Eventually he went to make his way to his parents house where he may possibly ask for what may have happened to his friends. Once he had reach his destination, he make three faint knocks on the door, waiting outside for someone to answer the door. Eventually the Mother answered the door and was greeted by an unfamiliar faces, She than shut the door while screaming many insults about him and also threatens to call his Husband to deal with him if needed. He ran back home thinking to himself that today have been awfully been weird that everyone he had met up with always had shown a disdainful look on him, the same one that he always shown when he met black peoples. He than look at the mirror and with a horrified glance he saw the face of the black dead man that he had once insults at him till he was found dead in his apartment.
A13: 8ikpafQproYMb9YoPmwfJPens6O2 | B13: yes | C13: 1 | D13: 1 | E13: 1 | F13: 1 | G13: 1 | H13: 131 | I13: 2026-07-01 11:49:40 | J13: 2026-07-01 11:49:40 | L13: no | M13: no | O13: The rumble got quieter, then it was just the winds. With the sound of the field trip bus leaving, all I can see is an empty road. I'm scared, scared that I'm left behind. I am realizing that I'm forgotten with a place that I can't recognize. The first thing I did is take my phone out and sit down. Unlucky, this place doesn't has any line or internet and a dead battery of my phone. At this point, my mind is blank, I don't know what can i do or what should I do. The only sound left is just the sound of my breathing. No signal, no internet, just a blank screen staring back. Then I looked up, a house in the distance, I have no choice to choose.
A14: AHeFHdwoiMWh94QkcWbW22EjkkO2 | B14: yes | C14: 1 | D14: 0 | E14: 0 | F14: 0 | H14: 0 | L14: no | M14: no
A15: B5ETbn4OQlbmR7jwyYjscFhyHMG2 | B15: yes | C15: 1 | D15: 2 | E15: 2 | F15: 2 | G15: 1 | H15: 485 | I15: 2026-07-01 09:09:46 | J15: 2026-07-01 09:12:27 | K15: 2.7 | L15: no | M15: no | N15: story starts in 2645. because of the seriously polluted environment, the government decided to build a huge dome in the middle of the London that only selected world top 0.1% people can enter. the main character, Jade Johnson, who are living in the dome one day meets Sam who are living in an outside world. they get curious each other and discover the deeply hided secret of the government of the dome and the outside world and dream an equally traded world with freedom and hope | O15: I stepped on the wood panel of the boat. The salty wind blows to my face. The start of this journey was full of excitement which brough me a new dream to start. It was the luckiest thing I've ever got in my life. I grabbed a ticket on my right hand again and revised the feeling of the day that I earned a ticket of the luxury boat journey for 15 days in casino. I thought it was a present from the god that asks me a forgiven for my whole terrible life. The hand size piece of paper was my hope and a dream that allows me to stay 15 more days. Yet, I didn't know the effect that this hope will bring. It was just a same day as the first 4, lots of people were enjoying party at the lounge bar at the second floor and I was returning back to my room. I was drunk at that time, and my body was extremely tired and heavy. I immediately leaned on the bed as I entered the room and were thinking of the sweat dream that will happen on the next day. At that point, suddenly the thing that hit my eardrum was a tragic high pitch of screaming from outside of the room. The screaming followed up to a women's shouting for some help. "911! emergency team! security! oh my gosh no way!" I banged the door and ran outside. It was a room 403. The door was opened and people made a circle in the room surround something. When I got close to a bunch of crowded people, I saw a women crying and screaming while holding something.... It was a dead body of a man. No one said it out that he is dead, but everyone could say he's dead. He was definitely dead. His face was so pale as it turns to blue, his left arm was fallen to the ground with no force at all, and his chest, bed, and ground were covered with a chunk of blood. "It's a murder scene definitely! Someone killed my husband! Please! Please safe him!" The emergency team and security guard ran into the room. "EVERYONE, PLEASE GO BACK TO YOUR OWN PLACE. REPEAT AGAIN PLEASE GO BACK TO YOUR ROOM AND DON'T COME OUT UNTIL WE SAY TO" People were starting to go back to their own room, and the guards were blocking the door of the room 403 and a floor 4. "Sorry sir but you need to go back to your room" The tall guard said a bit aggressively. I returned back to my room and sat on the bedside. Because I was drunk, I didn't recognize well what really happened and how serious and dangerous it is. The time I realized was the next morning when the guard was banging the door to wake me up.
A16: BpdNWTiz1HPmyvrVdqlZIfyGpMO2 | B16: yes | C16: 1 | D16: 1 | E16: 1 | F16: 1 | G16: 1 | H16: 460 | I16: 2026-07-02 09:26:29 | J16: 2026-07-02 09:26:29 | L16: yes | M16: no | N16: The Storm That Healed A storm arrives carrying more than just rain. Dark clouds cover the sky. Thunder rolls far away. Soon, heavy rain starts to fall. It beats hard against the windows and streets. Lynn sits by the window alone. For many days, she has felt sad and tired. Small troubles and worries make her upset. She stays away from friends and quiets herself down, thinking the dark mood will never leave. Strong wind shakes the old tree in the street. Its leaves are bent by the storm, but the tree still stands straight. Rain washes off the dirt on every leaf and stone. Watching the rain, Lynn slowly calms down. She understands that storms are not only bad. They clean the dirty air, wash away tiredness, and let everything start fresh. Slowly, thunder stops. The heavy rain turns into light drizzle. Dark clouds move away, and the sky becomes clear again. Cool wind blows in, bringing the fresh smell of grass and wet earth. Lynn takes a deep breath. This storm brought more than rain. It brought peace and hope. It washed away her sadness and gave her a new start. After the storm, everything looks bright again. ----------- The Storm That Healed A storm arrives carrying more than just rain. Dark clouds roll across the pale evening sky, swallowing the last trace of sunlight. Thunder rumbles in the distance, low and heavy, before the downpour crashes down upon the quiet town. The rain pounds against rooftops and windows, washing over every dusty corner of the streets. Lynn sits alone by the window, staring blankly outside. For weeks, her heart has been tangled in quiet sorrows. Disappointments, unspoken worries, and endless self-doubt have weighed her down, turning her days gray and lifeless. She has isolated herself from noise and company, believing the dullness inside her would never fade. The wind howls and shakes the branches of the old tree standing in the alley. Its leaves are violently tossed and bent by the storm, yet the trunk remains steady, rooted firmly in the ground. Rain pours relentlessly, cleaning every leaf, every stone, every speck of dirt that has gathered through days of heat and stillness. As Lynn watches, her tight chest slowly loosens. She realizes storms are not only destructive. They wash away dust. They clear the heavy air. They break stagnation and make room for new growth. Through the chaotic rain, she sees calm hidden within the wildness. The world does not end in a storm—it resets. It breathes again. Gradually, the thunder fades. The fierce rain softens into a gentle drizzle. The dark clouds drift apart, revealing a clean, quiet sky. Fresh wind blows through the open window, carrying the pure scent of wet soil and green leaves. Lynn closes her eyes and takes a deep breath. This storm brought more than rain. It brought clarity. It brought release. It washed away her lingering despair and gave her heart a quiet, gentle restart. When she opens her eyes again, everything feels lighter. The world looks brighter, softer, and full of silent hope. After the storm, everything begins anew ----------- The Rain That Changed Everything A storm arrives carrying more than just rain. The sky turned grey in only a few minutes. Wind rushed through the empty streets, and then the rain came down hard. Noah sat alone in his small room. He had been feeling lost for a long time. He tried his best, but nothing seemed to go right. He felt tired, lonely, and stuck inside his own sad thoughts. He stared outside at the storm. The trees shook wildly. The world looked cold and messy. But as he watched, he noticed something strange. The rain cleaned everything. It washed the dust off the roads. It cleaned the dark, dirty leaves. It made the whole town look new again. Slowly, the storm became softer. The loud thunder faded away. The heavy rain turned into quiet drops. The air outside felt cool, clean, and peaceful. Noah finally stood up. He realized storms were not only scary. Sometimes the hardest moments in life are like this rain. They come loud and sudden, and they break everything old. But they also clear the way for something better. This storm brought more than rain. It brought a quiet chance to start over. When the sun softly peeked out of the clouds, Noah smiled. For the first time in a long while, he felt hope again. ----------- More Than Rain A storm arrives carrying more than just rain. Jake had been feeling stuck for a long time. Small troubles kept piling up, and he lost his passion for the things he once loved. Every day felt dull and gray, and he could not find a way out of his low mood. One evening, dark clouds covered the sky. Strong winds swept through the streets, and heavy rain began to pour down. Thunder rumbled in the distance, shaking the quiet neighborhood. Jake stood by the window, watching the storm. The rain washed dust from the roads and refreshed the dry trees. The whole world looked clean and bright after being soaked. As he watched, the heavy weight in his heart slowly lifted. He realized storms were not just scary. They washed away tiredness and cleared the stale air. Hard times in life were just like this storm. Though painful at first, they could sweep away confusion and bring a new start. Soon the rain stopped. The sun peeked through the clouds, and a faint rainbow appeared in the sky. The fresh wind carried the sweet smell of grass. This storm brought more than rain. It brought hope and courage. Jake took a deep breath, and made up his mind to face life with a new attitude. | O16: A storm arrives carrying more than just rain. It came with shadow and silence, rolling over the rooftops to disturb the lazy peace I had been hiding in for far too long. For weeks, I had been living in a gentle kind of numbness. Nothing terrible had happened, yet nothing felt right either. I drifted through each day mechanically, tired of small mistakes, tired of unspoken pressure, and tired of the quiet weight sitting in my chest. I stopped reaching for joy, stopped chasing change, and convinced myself that flat, unremarkable calm was the safest way to live. Then the sky broke open. The sunlight vanished in minutes. The wind rose suddenly, sweeping through the streets and shaking every branch in the old trees outside my window. The first raindrops tapped lightly against the glass, hesitant, before the storm crashed down in full force. Heavy rain flooded the sidewalks. Low, distant thunder rumbled through the air, shaking the quiet walls of my room. I stood by the window and watched. I watched the rain wash away layers of dust that had settled through weeks of dry heat. I watched the dull, faded world outside turn fresh and vibrant, every leaf greener, every stone cleaner. The storm did not damage. It purified. It stripped away the old, stagnant stillness and replaced it with raw, breathing life. In that moment, I understood myself better. I had been afraid of chaos, afraid of struggle, afraid of anything that might disrupt my boring safe life. But in avoiding storms, I had also avoided growth. I had let my heart grow stale, just like the dusty summer streets before the rain. The storm raged outside, but inside me, something began to calm. All my hidden weariness, my quiet frustration, my long-held numbness—it all felt washed away with the downpour. I realized that difficulty does not always come to hurt us. Sometimes it comes to reset us, to clear what is heavy, and to make room for something new. Slowly, the thunder faded. The violent rain softened into a gentle fall. The dark clouds drifted apart, and faint, pale light spilled back over the neighborhood. The air drifted through my open window, cool, clean, and rich with the fresh scent of wet earth and new grass. I took a deep breath. This storm had brought more than just rain. It brought clarity to my confused mind, release to my trapped emotions, and a quiet courage I had forgotten I owned. It ended my lifeless stillness and gifted me a brand-new beginning. I no longer feared the wind or the dark. I knew now that after every storm; I do not just return to peace. I return stronger, lighter, and ready to walk into a clearer sky.
A17: E8tQQtddL4Z8NvhbbqY8K5O4cfO2 | B17: yes | C17: 1 | D17: 1 | E17: 1 | F17: 1 | G17: 1 | H17: 211 | I17: 2026-07-02 11:31:18 | J17: 2026-07-02 11:31:18 | L17: yes | M17: yes | N17: turn marvel endgame into a novel ----------- ----------- marvel ----------- earth, avengers, sponge bob, monkey d luffy, goku, gojo, ----------- messi,ronaldo, haaland,mbappe, spain,portugal,argentina,france,england,norway,brazil, pele, maradona, ronaldinho, croatia, mexico city, neymar ----------- football field, goals, hulk,spiderman, peterparker, ----------- I go hotel, he hit me, I hit him, he call police, i hit police, police boom boom guy, me go hospital, me heal, me go to jail, me go out jail, me go restaurant, me eat food, me no pay, me hit server, me call police, police tazer me, me go jail x2, me hit police, me get gun, me pew pew, me got pew pew, me pain, me in red, me die | O17: I go hotel, he hit me, I hit him, he call police, i hit police, police boom boom guy, me go hospital, me heal, me go to jail, me go out jail, me go restaurant, me eat food, me no pay, me hit server, me call police, police tazer me, me go jail x2, me hit police, me get gun, me pew pew, me got pew pew, me pain, me in red, me die, me reincarnated into a world with hippopotomonstrossessquippdaliophobia and people with pneumonoultramicroscopicsilicovolcanoconiosis. me go, me sick, me go nurse, me got stab, me hurt, me kill nurse, me arrested, me go join x3, me break bars, me hit mate, me king, me get ak47, me go boom boom, me walk in red, me hit police, me no die, me conquer, me emperor, me fight SEALS, me win, me got bomb, me throw grenade, places go boom boom, me go city, guy run, me chase, guy scared, me terror, me throw bomb, city go boom, nuke hit me, me go incinerated, me die x2. Me consicious, me on statue, me got thrown rotten eggs, me clown, no like me, me got stepped on, me angry, me reincarated x2. me get nuke, me press, earth go boom boom, me win.
A18: ENqphjWfdORTcp5Rm7ZI8lVt24g2 | B18: yes | C18: 1 | D18: 1 | E18: 1 | F18: 1 | G18: 1 | H18: 0 | I18: 2026-07-02 09:31:03 | J18: 2026-07-02 09:31:03 | L18: no | M18: no
A19: FCANzDkmkYT1W6HgapUhdnZN0xo2 | B19: yes | C19: 1 | D19: 1 | E19: 1 | F19: 1 | G19: 1 | H19: 795 | I19: 2026-07-01 08:53:33 | J19: 2026-07-01 08:53:33 | L19: no | M19: no | O19: the stench of a fresh corpse filled the air of the stall, detective Rhea could only pinch his nose in regret once again like he had already done for the past 6 bodies this week. He was just a few seconds too late once again, the severed arm of the victim floated steadily on the toilet water as it began to shift to red. Bootylicious had struck once again and had added another 7 confirmed murders to his long line of victims in his 5 years. they say he moves with the night, silent but deadly. Only 2 clues were ever picked up by the citizens and the detective, He only attacks those who shower once and he always leaves only one single body part in the toilet bowl. It didn't matter how big or small it was, it could be a full head, or it could be a tooth. But that was how you knew it was bootylicious. Detective Rhea had already come to the conclusion that the story of bootylicious wasn't adding up. it wasn't the speed or accuracy of these murders, but the fact that it had been happening consistently for 5 years. The truth was that the town had already been driven to two showers daily by fear. so how could bootylicious be possibly finding new victims at such a consistent and fast rate. There was obviously a 2nd factor at play here and yet no dots could be connected so far. Another strange factor that is present is that every year there is one victim that goes missing, but the body parts were never placed anywhere. these factors made it so the case could never be solved on one straight path, consistently deviating off course for another anomaly in the pattern. Detective Rhea immediately planned to place in effect the. idea they've had for a while, a prisoner on death row was brought out of his cell for the sole purpose of being bait for bootylicious. The plan was in motion, the inmate had only showered once today, and the detective had placed trackers all over his body parts, so he could see where the rest of them end up. he also coated the inmate in a special dust that can only be seen by a specific light, which would be able to catch bootylicious's prints if he tried anything. The clock hit twelve and in an instant a blur of shadows rushed into the room, Detective Rhea immediately ordered his men to open fire and bullets began to fly around in the room, the commotion fully destroyed the whole room and as the dust settled, the inmate was gone and there were bullet holes everywhere, blood was splattered on the floor and around the walls, but on further inspection, all of the blood had only traces of the inmates DNA. This meant none of them landed on Bootylicious and the inmate had been most likely used as a meat shield by him. immediately the squad began testing the 2 counter measures that Detective Rhea had placed, but somehow bootylicious had accounted for every single one. It seemed this time he had dropped off every single of the inmates parts into separate toilets around the town, and somehow no disturbance other than the bullet holes were caught by the dust. It seemed like bootylicious was just an anomaly, some entity that for some reason had a hatred of single daily showerers. But suddenly, Detective Rhea revealed his hidden trap card. He actually had a high tech camera placed in the room that only he knew about, and when checking the footage, they could finally clearly see him. Bootylicious had a slim build, almost like a ghoul. his hands were long and thin, like he was decaying corpse And his face looked disfigured and dead skin was present all around him. It seemed like he was infact some dead corpse that had some hidden vengeance on this town and those weird factors involving hygiene. But now Detective Rhea had a huge breakthrough in the case. he now knew what bootylicious looked like. meaning he was capable of being caught off guard. But it seemed like after the incident, Bootylicious had vanished. All the missing victim cases began slowly ending, before completely stopping. When they attempted to do the test again, bootylicious did not appear. It seemed like he had ended his rampage after his identity had been discovered. But not all the pieces of the puzzle were finished, the yearly missing cases were never solved and the incident in Detective Rhea's childhood was never brought up in the case again. But with bootylicious gone and subsequently no more possibly chances to get clues, the case had gone cold and eventually ended.
A20: GC4oYcvlWFdKmK6Nkgi8i5hXCng1 | B20: yes | C20: 1 | D20: 1 | E20: 1 | F20: 1 | G20: 1 | H20: 553 | I20: 2026-07-02 14:24:35 | J20: 2026-07-02 14:24:35 | L20: no | M20: no | O20: Ahoy, yousorry sack for sea salt and self-pity So here you are, three months out, strain' at the same bleed in' horizon like it owes you answers. Let me tell you somethin', you barnacled fool—I've been around longer than your grandaddy's grandaddy, and I've seen more whining' sailors than you've had hot dinners. You think you're the first sorry soul to gaze across my back and feel "profound"? Please. I've carried tea clippers, whalers, and cowardly pirates who cried for their mamas in a squall. You ain't special. You call me "vast and empty"? I'm neither. I'm teeming' with life you can't see 'cause you're too busy moping' at the rail. There's krill below you by the billion, sharks gliding' like daggers, and whales singing' songs older than your precious poetry. But no—you're up there scribbling' in your journal about "the cruel mistress sea." Cruel? I gave you wind, I gave you current, I even threw in a calm day so you could dry your socks. What more do you want? A bloody handshake? And them stars you're always gazing' at like a lovesick puppy? They ain't twinkling' for you. They're waypoints, you dolt. I've been showing me to sailors for millennia, and most of 'me had the good sense to USE 'me instead of waxing' lyrical about their lonely souls. The moon? She's been watchin' me longer than any human drew breath, and trust me—she's rolling' her cratered eyes at your dramatics. The whales ain't singing' for your broken heart. They're gossiping' about how you haul on the braces like a landsman with a blister. The gulls ain't following' you out of respect—they're waiting' for you to drop your damn biscuit overboard. And them dolphins? They're not playing' for your amusement. They're laughing' at your sorry rigging' and the way you tie them knots like a lubber who learned from a picture book. Here's the hard tack, shipmate. Stop asking' the ocean to give you meaning'. I ain't your mama, your priest, or your sweetheart back in port. I'm just water—a whole lot of it, with a temper and a tide. You want a sign? This letter IS your sign. It's me sayin' quit your bellyaching', trim your sails proper, and remember that bein' alone ain't the same as bein' lonely. I've seen real loneliness. I've seen men lost for years, watchin' their crewmates die of scurvy and still cracking' jokes. I've seen whalers chase leviathans into the ice with nothin' but grit and madness. And you? You're floating' on a sturdy ship with a full galley and a dry bunk, moaning' into your beard like a tragic hero. Get over yourself. When you make port, I expect you to stumble ashore with a tale worth telling'—not another soggy sonnet about the waves. I want a story about a squall you beat, a fish you caught, a laugh you shared with your crew. 'Cause that's what I give you, you ungrateful whelp—not meaning', but a stage. What you do with it is your own damn business. Now batten down your feeling's, haul on your backbone, and sail proper. And if I catch you scribbling' one more verse about my "cruel beauty," I'll send a rogue wave to knock that quill right out your hand. Fair winds, you dramatic squid, The Sea Herself
A21: JOXonotBYmMnqSLfh2NltHD8uXB2 | B21: yes | C21: 1 | D21: 1 | E21: 1 | F21: 1 | G21: 1 | H21: 448 | I21: 2026-07-01 14:17:50 | J21: 2026-07-01 14:17:50 | L21: yes | M21: no | N21: I went on a school trip once, and i got lost. it was in the morning, i was prepared to go out, happily with all my friends, then, we departed, we were joking around and having fun on the bus an hour later, we have arrived. it was a field trip, a trip to explore the forest, the forest was quite dark and scary, but we had our friends, so it was better, a while later we all sat down and ate lunch, after i finished, i saw something in the forest, i got curious and went towards it. when i came back, everyone was gone, when the last voice faded into the trees, i didn't move at first. i waited for a joke, for someone to call my name. But the forest only swallowed the silence whole and left him standing in it alone. for a while i was relieved to be free of the group's noise and pressure. For a few minutes, the solitude feels like a gift. Then the sun drops, and the gift turns into a cage. i was stretching his legs, taking a deep breath, smiling to myself. but then the absence hit, no footsteps behind me, no voices calling ahead. my relief curdles into dread. i am lost, it's dark, and the only sound is my own heartbeat. Then — a twig snaps nearby. Not an animal, but something that sounds like it walked on two feet. i freeze. Heart pounding, breathing shallow. The snapped twig is followed by another, then a low whistle — a simple tune, out of place in the dark. there was a shadow, that's all i needs to keep running. The shadow isn't chasing, just standing there motionless. After hours of alien, twisting woods, my foot hits a familiar root. The shape of it, the way the ground slopes here — i know this spot. i stop. my heart, which has been pounding with fear, now hammers with something else hope, maybe. I didn't trust it. I listened, waiting for the forest to trick me, for the whistling to start again. But there's only silence. Then, a voice. Not the pursuer's tune, but a shout. A name. my name. I opened my mouth. At first, nothing came out—my throat is raw from holding back fear. But then i shouts, voice cracking: "Here! I'm here!" Branches rustle. A figure emerges from the darkness. It's his teacher. The man looks pale, exhausted. He's been searching for all night. For a long moment, neither speaks. Then his teacher says, "You're alive." and we all went on the bus and we got home safely | O21: I went on a school trip once, and I got lost. It was in the morning, I was prepared to go out, happily with all my friends, then, we departed, we were joking around and having fun on the bus. An hour later, we arrived. It was a field trip, a trip to explore the forest. The forest was quite dark and scary, but we had our friends, so it was better. A while later we all sat down and ate lunch. After I finished, I saw something in the forest, I got curious and went towards it. When I came back, everyone was gone. When the last voice faded into the trees, I didn't move at first. I waited for a joke, for someone to call my name. But the forest only swallowed the silence whole and left me standing in it alone. For a while I was relieved to be free of the group's noise and pressure. For a few minutes, the solitude felt like a gift. Then the sun dropped, and the gift turned into a cage. I was stretching my legs, taking a deep breath, smiling to myself. But then the absence hit — no footsteps behind me, no voices calling ahead. My relief curdled into dread. I was lost, it was dark, and the only sound was my own heartbeat. Then — a twig snapped nearby. Not an animal, but something that sounded like it walked on two feet. I froze. Heart pounding, breathing shallow. The snapped twig was followed by another, then a low whistle — a simple tune, out of place in the dark. There was a shadow, that's all I needed to keep running. The shadow wasn't chasing, just standing there motionless. After hours of alien, twisting woods, my foot hit a familiar root. The shape of it, the way the ground sloped here — I knew this spot. I stopped. My heart, which had been pounding with fear, now hammered with something else — hope, maybe. I didn't trust it. I listened, waiting for the forest to trick me, for the whistling to start again. But there was only silence. Then, a voice. Not the pursuer's tune, but a shout. A name. My name. I opened my mouth. At first, nothing came out — my throat was raw from holding back fear. But then I shouted, voice cracking: "Here! I'm here!" Branches rustled. A figure emerged from the darkness. It was my teacher. The man looked pale, exhausted. He had been searching all night. For a long moment, neither of us spoke. Then my teacher said, "You're alive." And we all went on the bus and got home safely.
A22: JfiRrqZrDzOGZuUmcQ0xNNqqRPt2 | B22: yes | C22: 1 | D22: 1 | E22: 1 | F22: 1 | G22: 1 | H22: 385 | I22: 2026-07-01 09:16:18 | J22: 2026-07-01 09:16:18 | L22: no | M22: no | O22: This girl loves to stay at her grandma house and her name is call Olivia . She doesn't like to leave her hometown because all the people around there is very kind to her never been mean to her, her thoughts were never leaving her hometown and she loves her family a lot at trust them the most. But one day she find something suspicions in her grandma house and in her family she felt like their hiding something from her she was trying to find out what is the thing her family is hiding but after some day she leave it she doesn't really care about it she stared going out to walk around in her hometown. There's a aunty name call Ms. Helena Ms. Helena sells flowers and Oliva likes to go there because she the like the flowers Ms. Helena sell and she likes the aunty because she's always kind to her and also give her free flowers for her only, every evening Olivia goes to the flower shop to relax and talk with Ms. Helena. As Olivia family was hiding a secret from her , well for some days she ignore it she doesn't really take it as serious matter but day by day she see changes in her grandma house so she thought to ask her family about it but they did not answer her so she started to get confused because they never ignore her question before this was their first time they ignore it. Now she knew it her family is definitely hiding something from but also at the same time she was sad because their not telling her and also she trust them a lot. Olivia is now thinking a lot of things she stop going out now days and she started less talking with peoples around her thoughts were now leaving her hometown because her family stop talking with her she knows there is something wrong but their not sharing with her, she was really hurt . she doesn't wants to leave her hometown she really feels sad but because of her family and her mind is not okay now. but afterfew days she thought not to leave because her parents don't have any one other than her and also she has a lot of memoirs
A23: Jr8NNAZgvmgiYpNb4K6qyiuo4tW2 | B23: yes | C23: 1 | D23: 1 | E23: 1 | F23: 1 | G23: 1 | H23: 252 | I23: 2026-07-02 09:17:45 | J23: 2026-07-02 09:17:45 | L23: no | M23: no | O23: The cool breeze fills the air. The sea was alive. Waves swashing around, sometimes hitting whatever he was on. The sailor. He has been aimlessly drifting around for days now. He gave up counting after the second sunrise without land. A letter arrived on a Tuesday, smelling of salt and something burnt. He unfolded it twice before reading, his hands steady but his breath shallow. "The sea remembers you" it said. "You cannot outrun what you carry". He folded the letter back and tucked it away. Preferably to serve as a reminder of his actions. Soon another bottle came, followed by another. Each filled with letters of their own, different in ways but still are connected. At this point, the letters are enough could keep him company. And drive the emptiness and and longlines of being alone away. But all of them always end up at the same place, beneath his dangling feet above the ocean. No matter which direction he turns, the bottles are there. Like it is trying to get his attention. But the sailor just doesnt know from where. Each day that passes, more bottled letters arrive, each with warnings of what is about to come, and some even personal. By now, the sailor realises he is not alone, but who is sending these messages and how it always ended up finding him is a thought that is embedded at the ack of his mind. One sudden thought builds up, "what if I ignore and go against the letters?"
A24: KSH5ttdNftVFL6Gd0J4yzvu2FBp1 | B24: yes | C24: 1 | D24: 1 | E24: 1 | F24: 1 | G24: 1 | H24: 171 | I24: 2026-07-01 12:00:22 | J24: 2026-07-01 12:00:22 | L24: no | M24: no | O24: in my life, everyday feels like a cycle of arguments, and by the end of the day, i always brushed it off like it is not important and wont do anything to my life. As i was walking home after a heated argument, a flicker of light appeared in a distance looking around like he was looking for something desperately. when we locked eyes together, he suddenly sprinted at me and stopped to explain to me what was going on. As he get closer, he started to look identical to me but tired. He didn't speak, he just showed me that in the next 10 years if i kept on doing this bad habits, i will have a failed relationship, a missed promotion and lots of broken trusts. Then he spoke to me that one small bad habit, repeated daily, built that outcome. I thought this was nonsense and replied, "it's just one bad day", he counters it with "One bad day times 3,650 days.". Then i realized the truth is,
A25: KUrkPMRkNAhX9hnzS29LtPHaO5x2 | B25: yes | C25: 1 | D25: 1 | E25: 1 | F25: 1 | G25: 1 | H25: 265 | I25: 2026-07-02 14:23:47 | J25: 2026-07-02 14:23:47 | L25: no | M25: no | O25: Every school, at the end of the academic year they will do a field trip for student to go. Since me and my friends want to be productive instead of wasting our holiday by staying at home, so we decided to join the field trip. On the field trip day, I wake up early to prepare to go to school for going to museum which is organize by our school. When I reach there, my friends are already waiting for me, we chatted for a while and finally the bus for our trip has arrive. My friend and I quickly put down our bags in the bus and rush toward the back seat. Since that museum is very far, most of us in the has pass out from all the school projects. When we wake up, we found out that we have reach the outside the museum. When we reach main entrance for the museum, we were shocked because the museum is so huge and fancy. Following our teachers steps we have reached the reception to get a guide for us. He began to show us all the historical artifacts and the story behind them. After showing those to us, he took us to the art gallery he gave us an hour to walk around and explore. We were amazed by how all detail of the art that we found. On the next room, he took us to a room full of statue of famous historical people. But one has caught my attention, other figure has name and their stories, but this one has nothing.
A26: KgqLQajP4thdhVywhC6DGIFB1ZC3 | B26: yes | C26: 1 | D26: 2 | E26: 4 | F26: 4 | G26: 1 | H26: 1838 | I26: 2026-07-01 08:51:25 | J26: 2026-07-01 09:42:45 | K26: 51.3 | L26: no | M26: no | O26: There once was a guy, a man named Paul. His father named him after the famed apostle. Now, he walked the streets of New York City, the big apple, while filled with the forbidden apple. He knew above all else he had a great downfall, he knew he shouldn't have fallen into such disgraceful acts, drinking, drugs, smoking. Now he is left all alone, he ran away from his family that was calling for him to change for the better. Since high school he had started the poisoning, stopped all good he had and started the path the other way. But by now, he knew, he made a mistake. But he would never return to his family or his church, scared to return. Why? He doesn't know himself. He was quite sure of what he was, a stray. A stray man, not dog, not cat. He had nothing, nobody. All but the drugs he couldn't stop, even when he couldn't afford to eat. he was a quarter century old by now, at least he was fairly certain he was. Now today, things were different. He was walking past an alley when he heard a soft faint bark. There was a small puppy, a mix breed, he couldn't tell it's age, but he knew he had to do something. For in his heart, no matter what, had a compassion and love that never rested. He took the young pup, brought it to some cover, for the sky was shooting down pellets of rain upon the city that never sleeps. The pup was hungry, he could tell. But so was he. He knew he had to do something, but he could only think of one way, one way he didn't dare to do. The church he used to go every Sunday was roughly 20 miles east of where he was, so he did what must be done. The two strays went off, the pup in the arms of the homeless man. Stopped in between every mile or so, for he was weak, extremely so. But he had this newfound strength in him, a gift he knew was either from his heart for the puppy, or a happy father who is glad for his return. After hours, he finally arrived back at the doors he used to enter, the church he used to worship at, and the same pastor that used to teach him Sunday school, now greeted him in. Since that day, everything changed for him. He went back home, finally got clean, went to college, and no matter what kept that same pup that saved him by his side forever and ever. And he regained a powerful relationship, with the powerful father he finally renewed faith in. For the stray no longer strays, we all can regain what we once had, and more. There was a guy, he had nothing. He would sleep on benches, eat from trash, he was trash, or at least that was what he thought. nobody would turn their head, nobody would stop to help. He was used to it. It didn't bother the lad, for he was alone, unloved, a stray. He always told himself he deserved what he got. He has been clean for nearly a year now, though his clothes stay stained. He recalled his downfall, he would dream back, hoping to return. The streets of New York City, he strayed alone. Just another junkie. To everyone else. You can never fall, unless you were up. The guy had a named, he used to be a man of god, his father had bestowed upon him the great name of Paul, he missed his father. Paul used to go to church every Sunday, prayed every night. But then he stopped. Why? At a tender young age he fell into temptation, the drink and the unholy substances. Now, he walked the streets of the big apple, as he tried to resist the forbidden apple. Here goes his day, a special day: Paul walked down a block, he wasn't sure where, nor did he care, he was looking for some change, he hoped would be on the ground, dropped by tourists or some irresponsible residents. He didn't find money, but he found something more, something he always loved. He found what he say as himself, a stray. A young puppy lying on the sidewalk, looked to be a mutt, cast aside. Paul picked up the puppy, pet him, he found a friend. He brought the puppy into a back alley, he placed him gently on a piece of cardboard, the puppy was sleepy, tired, starved. Paul took to the streets in search of food, he only had 5 dollars to his name. He didn't bother, he bought a hot dog with half of his net worth, to feed the little dog. For he knew above all else, the puppy was completely innocent, not a thing of hate in it's heart. The puppy gobbled up the sausage, leaving the dry bread for Paul, so he ate the final bit of food for the rest of the day. He can't afford more. Paul never dared to return to church, afraid his pastor and community would be heartbroken on his fall, but today he went, not for himself, but for his new companion. The two strays knocked on the door of the old chapel, There once was a guy, a man named Paul. His father named him after the famed apostle. Now, he walked the streets of New York City, the big apple, while filled with the forbidden apple. He knew above all else he had a great downfall, he knew he shouldn't have fallen into such disgraceful acts, drinking, drugs, smoking. Now he is left all alone, he ran away from his family that was calling for him to change for the better. Since high school he had started the poisoning, stopped all good he had and started the path the other way. But by now, he knew, he made a mistake. But he would never return to his family or his church, scared to return. Why? He doesn't know himself. He was quite sure of what he was, a stray. A stray man, not dog, not cat. He had nothing, nobody. All but the drugs he couldn't stop, even when he couldn't afford to eat. he was a quarter century old by now, at least he was fairly certain he was. Now today, things were different. He was walking past an alley when he heard a soft faint bark. There was a small puppy, a mix breed, he couldn't tell it's age, but he knew he had to do something. For in his heart, no matter what, had a compassion and love that never rested. He took the young pup, brought it to some cover, for the sky was shooting down pellets of rain upon the city that never sleeps. The pup was hungry, he could tell. But so was he. He knew he had to do something, but he could only think of one way, one way he didn't dare to do. The church he used to go every Sunday was roughly 20 miles east of where he was, so he did what must be done. The two strays went off, the pup in the arms of the homeless man. Stopped in between every mile or so, for he was weak, extremely so. But he had this newfound strength in him, a gift he knew was either from his heart for the puppy, or a happy father who is glad for his return. After hours, he finally arrived back at the doors he used to enter, the church he used to worship at, and the same pastor that used to teach him Sunday school, now greeted him in. Since that day, everything changed for him. He went back home, finally got clean, went to college, and no matter what kept that same pup that saved him by his side forever and ever. And he regained a powerful relationship, with the powerful father he finally renewed faith in. For the stray no longer strays, we all can regain what we once had, and more. There once was a guy, a man named Paul. His father named him after the famed apostle. Now, he walked the streets of New York City, the big apple, while filled with the forbidden apple. He knew above all else he had a great downfall, he knew he shouldn't have fallen into such disgraceful acts, drinking, drugs, smoking. Now he is left all alone, he ran away from his family that was calling for him to change for the better. Since high school he had started the poisoning, stopped all good he had and started the path the other way. But by now, he knew, he made a mistake. But he would never return to his family or his church, scared to return. Why? He doesn't know himself. He was quite sure of what he was, a stray. A stray man, not dog, not cat. He had nothing, nobody. All but the drugs he couldn't stop, even when he couldn't afford to eat. he was a quarter century old by now, at least he was fairly certain he was. Now today, things were different. He was walking past an alley when he heard a soft faint bark. There was a small puppy, a mix breed, he couldn't tell it's age, but he knew he had to do something. For in his heart, no matter what, had a compassion and love that never rested. He took the young pup, brought it to some cover, for the sky was shooting down pellets of rain upon the city that never sleeps. The pup was hungry, he could tell. But so was he. He knew he had to do something, but he could only think of one way, one way he didn't dare to do. The church he used to go every Sunday was roughly 20 miles east of where he was, so he did what must be done. The two strays went off, the pup in the arms of the homeless man. Stopped in between every mile or so, for he was weak, extremely so. But he had this newfound strength in him, a gift he knew was either from his heart for the puppy, or a happy father who is glad for his return. After hours, he finally arrived back at the doors he used to enter, the church he used to worship at, and the same pastor that used to teach him Sunday school, now greeted him in. Since that day, everything changed for him. He went back home, finally got clean, went to college, and no matter what kept that same pup that saved him by his side forever and ever. And he regained a powerful relationship, with the powerful father he finally renewed faith in. For the stray no longer strays, we all can regain what we once had, and more.
